Workbook

Sheet DIÁRIO (2)
C2: =SUM(C4:C65) -> 0 | D2: =SUM(D4:D65) -> 25563.22 | E2: =SUM(E4:E65) -> 610.67 | F2: =SUM(F4:F65) -> 0 | G2: =SUM(G4:G65) -> 9840 | H2: =SUM(H4:H65) -> 0 | I2: =SUM(I4:I65) -> 71849.5 | J2: =SUM(J4:J65) -> 23973.66 | ... T2: =SUM(T4:T65) -> 104100 | U2: =SUM(C2:T2) -> 334330.49
C3: 45944 | D3: 45945 | E3: 45946 | F3: 45947 | G3: 45948 | H3: 45949 | I3: 45950 | J3: 45951 | K3: 45952 | L3: 45953 | M3: 45954 | N3: 45955 | O3: 45956 | P3: 45957 | Q3: 45958 | R3: 45959 | S3: 45960 | T3: 45961 | U3: TOTAL
B4: Tecidos | C4: =SUMIFS('CONTAS A PAGAR SIMULAÇÃO'!$N:$N,'CONTAS A PAGAR SIMULAÇÃO'!$K:$K,'DIÁRIO (2)'!C$3,'CONTAS A PAGAR SIMULAÇÃO'!$S:$S,'DIÁRIO (2)'!$B4) -> 0 | D4: =SUMIFS('CONTAS A PAGAR SIMULAÇÃO'!$N:$N,'CONTAS A PAGAR SIMULAÇÃO'!$K:$K,'DIÁRIO (2)'!D$3,'CONTAS A PAGAR SIMULAÇÃO'!$S:$S,'DIÁRIO (2)'!$B4) -> 14002.12 | E4: =SUMIFS('CONTAS A PAGAR SIMULAÇÃO'!$N:$N,'CONTAS A PAGAR SIMULAÇÃO'!$K:$K,'DIÁRIO (2)'!E$3,'CONTAS A PAGAR SIMULAÇÃO'!$S:$S,'DIÁRIO (2)'!$B4) -> 610.67 | F4: =SUMIFS('CONTAS A PAGAR SIMULAÇÃO'!$N:$N,'CONTAS A PAGAR SIMULAÇÃO'!$K:$K,'DIÁRIO (2)'!F$3,'CONTAS A PAGAR SIMULAÇÃO'!$S:$S,'DIÁRIO (2)'!$B4) -> 0 | G4: =SUMIFS('CONTAS A PAGAR SIMULAÇÃO'!$N:$N,'CONTAS A PAGAR SIMULAÇÃO'!$K:$K,'DIÁRIO (2)'!G$3,'CONTAS A PAGAR SIMULAÇÃO'!$S:$S,'DIÁRIO (2)'!$B4) -> 9840 | H4: =SUMIFS('CONTAS A PAGAR SIMULAÇÃO'!$N:$N,'CONTAS A PAGAR SIMULAÇÃO'!$K:$K,'DIÁRIO (2)'!H$3,'CONTAS A PAGAR SIMULAÇÃO'!$S:$S,'DIÁRIO (2)'!$B4) -> 0 | I4: =SUMIFS('CONTAS A PAGAR SIMULAÇÃO'!$N:$N,'CONTAS A PAGAR SIMULAÇÃO'!$K:$K,'DIÁRIO (2)'!I$3,'CONTAS A PAGAR SIMULAÇÃO'!$S:$S,'DIÁRIO (2)'!$B4) -> 22248.8 | J4: =SUMIFS('CONTAS A PAGAR SIMULAÇÃO'!$N:$N,'CONTAS A PAGAR SIMULAÇÃO'!$K:$K,'DIÁRIO (2)'!J$3,'CONTAS A PAGAR SIMULAÇÃO'!$S:$S,'DIÁRIO (2)'!$B4) -> 9840 | ... T4: =SUMIFS('CONTAS A PAGAR SIMULAÇÃO'!$N:$N,'CONTAS A PAGAR SIMULAÇÃO'!$K:$K,'DIÁRIO (2)'!T$3,'CONTAS A PAGAR SIMULAÇÃO'!$S:$S,'DIÁRIO (2)'!$B4) -> 0 | U4: =SUM(C4:T4) -> 108613.34
B5: Lavanderia | C5: =SUMIFS('CONTAS A PAGAR SIMULAÇÃO'!$N:$N,'CONTAS A PAGAR SIMULAÇÃO'!$K:$K,'DIÁRIO (2)'!C$3,'CONTAS A PAGAR SIMULAÇÃO'!$S:$S,'DIÁRIO (2)'!$B5) -> 0 | D5: =SUMIFS('CONTAS A PAGAR SIMULAÇÃO'!$N:$N,'CONTAS A PAGAR SIMULAÇÃO'!$K:$K,'DIÁRIO (2)'!D$3,'CONTAS A PAGAR SIMULAÇÃO'!$S:$S,'DIÁRIO (2)'!$B5) -> 5210 | E5: =SUMIFS('CONTAS A PAGAR SIMULAÇÃO'!$N:$N,'CONTAS A PAGAR SIMULAÇÃO'!$K:$K,'DIÁRIO (2)'!E$3,'CONTAS A PAGAR SIMULAÇÃO'!$S:$S,'DIÁRIO (2)'!$B5) -> 0 | F5: =SUMIFS('CONTAS A PAGAR SIMULAÇÃO'!$N:$N,'CONTAS A PAGAR SIMULAÇÃO'!$K:$K,'DIÁRIO (2)'!F$3,'CONTAS A PAGAR SIMULAÇÃO'!$S:$S,'DIÁRIO (2)'!$B5) -> 0 | G5: =SUMIFS('CONTAS A PAGAR SIMULAÇÃO'!$N:$N,'CONTAS A PAGAR SIMULAÇÃO'!$K:$K,'DIÁRIO (2)'!G$3,'CONTAS A PAGAR SIMULAÇÃO'!$S:$S,'DIÁRIO (2)'!$B5) -> 0 | H5: =SUMIFS('CONTAS A PAGAR SIMULAÇÃO'!$N:$N,'CONTAS A PAGAR SIMULAÇÃO'!$K:$K,'DIÁRIO (2)'!H$3,'CONTAS A PAGAR SIMULAÇÃO'!$S:$S,'DIÁRIO (2)'!$B5) -> 0 | I5: =SUMIFS('CONTAS A PAGAR SIMULAÇÃO'!$N:$N,'CONTAS A PAGAR SIMULAÇÃO'!$K:$K,'DIÁRIO (2)'!I$3,'CONTAS A PAGAR SIMULAÇÃO'!$S:$S,'DIÁRIO (2)'!$B5) -> 3620.5 | J5: =SUMIFS('CONTAS A PAGAR SIMULAÇÃO'!$N:$N,'CONTAS A PAGAR SIMULAÇÃO'!$K:$K,'DIÁRIO (2)'!J$3,'CONTAS A PAGAR SIMULAÇÃO'!$S:$S,'DIÁRIO (2)'!$B5) -> 0 | ... T5: =SUMIFS('CONTAS A PAGAR SIMULAÇÃO'!$N:$N,'CONTAS A PAGAR SIMULAÇÃO'!$K:$K,'DIÁRIO (2)'!T$3,'CONTAS A PAGAR SIMULAÇÃO'!$S:$S,'DIÁRIO (2)'!$B5) -> 0 | U5: =SUM(C5:T5) -> 15260.5
B6: Travete | C6: =SUMIFS('CONTAS A PAGAR SIMULAÇÃO'!$N:$N,'CONTAS A PAGAR SIMULAÇÃO'!$K:$K,'DIÁRIO (2)'!C$3,'CONTAS A PAGAR SIMULAÇÃO'!$S:$S,'DIÁRIO (2)'!$B6) -> 0 | D6: =SUMIFS('CONTAS A PAGAR SIMULAÇÃO'!$N:$N,'CONTAS A PAGAR SIMULAÇÃO'!$K:$K,'DIÁRIO (2)'!D$3,'CONTAS A PAGAR SIMULAÇÃO'!$S:$S,'DIÁRIO (2)'!$B6) -> 0 | E6: =SUMIFS('CONTAS A PAGAR SIMULAÇÃO'!$N:$N,'CONTAS A PAGAR SIMULAÇÃO'!$K:$K,'DIÁRIO (2)'!E$3,'CONTAS A PAGAR SIMULAÇÃO'!$S:$S,'DIÁRIO (2)'!$B6) -> 0 | F6: =SUMIFS('CONTAS A PAGAR SIMULAÇÃO'!$N:$N,'CONTAS A PAGAR SIMULAÇÃO'!$K:$K,'DIÁRIO (2)'!F$3,'CONTAS A PAGAR SIMULAÇÃO'!$S:$S,'DIÁRIO (2)'!$B6) -> 0 | G6: =SUMIFS('CONTAS A PAGAR SIMULAÇÃO'!$N:$N,'CONTAS A PAGAR SIMULAÇÃO'!$K:$K,'DIÁRIO (2)'!G$3,'CONTAS A PAGAR SIMULAÇÃO'!$S:$S,'DIÁRIO (2)'!$B6) -> 0 | H6: =SUMIFS('CONTAS A PAGAR SIMULAÇÃO'!$N:$N,'CONTAS A PAGAR SIMULAÇÃO'!$K:$K,'DIÁRIO (2)'!H$3,'CONTAS A PAGAR SIMULAÇÃO'!$S:$S,'DIÁRIO (2)'!$B6) -> 0 | I6: =SUMIFS('CONTAS A PAGAR SIMULAÇÃO'!$N:$N,'CONTAS A PAGAR SIMULAÇÃO'!$K:$K,'DIÁRIO (2)'!I$3,'CONTAS A PAGAR SIMULAÇÃO'!$S:$S,'DIÁRIO (2)'!$B6) -> 881 | J6: =SUMIFS('CONTAS A PAGAR SIMULAÇÃO'!$N:$N,'CONTAS A PAGAR SIMULAÇÃO'!$K:$K,'DIÁRIO (2)'!J$3,'CONTAS A PAGAR SIMULAÇÃO'!$S:$S,'DIÁRIO (2)'!$B6) -> 0 | ... T6: =SUMIFS('CONTAS A PAGAR SIMULAÇÃO'!$N:$N,'CONTAS A PAGAR SIMULAÇÃO'!$K:$K,'DIÁRIO (2)'!T$3,'CONTAS A PAGAR SIMULAÇÃO'!$S:$S,'DIÁRIO (2)'!$B6) -> 0 | U6: =SUM(C6:T6) -> 881
B7: Facção | C7: =SUMIFS('CONTAS A PAGAR SIMULAÇÃO'!$N:$N,'CONTAS A PAGAR SIMULAÇÃO'!$K:$K,'DIÁRIO (2)'!C$3,'CONTAS A PAGAR SIMULAÇÃO'!$S:$S,'DIÁRIO (2)'!$B7) -> 0 | D7: =SUMIFS('CONTAS A PAGAR SIMULAÇÃO'!$N:$N,'CONTAS A PAGAR SIMULAÇÃO'!$K:$K,'DIÁRIO (2)'!D$3,'CONTAS A PAGAR SIMULAÇÃO'!$S:$S,'DIÁRIO (2)'!$B7) -> 0 | E7: =SUMIFS('CONTAS A PAGAR SIMULAÇÃO'!$N:$N,'CONTAS A PAGAR SIMULAÇÃO'!$K:$K,'DIÁRIO (2)'!E$3,'CONTAS A PAGAR SIMULAÇÃO'!$S:$S,'DIÁRIO (2)'!$B7) -> 0 | F7: =SUMIFS('CONTAS A PAGAR SIMULAÇÃO'!$N:$N,'CONTAS A PAGAR SIMULAÇÃO'!$K:$K,'DIÁRIO (2)'!F$3,'CONTAS A PAGAR SIMULAÇÃO'!$S:$S,'DIÁRIO (2)'!$B7) -> 0 | G7: =SUMIFS('CONTAS A PAGAR SIMULAÇÃO'!$N:$N,'CONTAS A PAGAR SIMULAÇÃO'!$K:$K,'DIÁRIO (2)'!G$3,'CONTAS A PAGAR SIMULAÇÃO'!$S:$S,'DIÁRIO (2)'!$B7) -> 0 | H7: =SUMIFS('CONTAS A PAGAR SIMULAÇÃO'!$N:$N,'CONTAS A PAGAR SIMULAÇÃO'!$K:$K,'DIÁRIO (2)'!H$3,'CONTAS A PAGAR SIMULAÇÃO'!$S:$S,'DIÁRIO (2)'!$B7) -> 0 | I7: =SUMIFS('CONTAS A PAGAR SIMULAÇÃO'!$N:$N,'CONTAS A PAGAR SIMULAÇÃO'!$K:$K,'DIÁRIO (2)'!I$3,'CONTAS A PAGAR SIMULAÇÃO'!$S:$S,'DIÁRIO (2)'!$B7) -> 34977.5 | J7: =SUMIFS('CONTAS A PAGAR SIMULAÇÃO'!$N:$N,'CONTAS A PAGAR SIMULAÇÃO'!$K:$K,'DIÁRIO (2)'!J$3,'CONTAS A PAGAR SIMULAÇÃO'!$S:$S,'DIÁRIO (2)'!$B7) -> 0 | ... T7: =SUMIFS('CONTAS A PAGAR SIMULAÇÃO'!$N:$N,'CONTAS A PAGAR SIMULAÇÃO'!$K:$K,'DIÁRIO (2)'!T$3,'CONTAS A PAGAR SIMULAÇÃO'!$S:$S,'DIÁRIO (2)'!$B7) -> 0 | U7: =SUM(C7:T7) -> 46858
B8: Acabamento Externo | C8: =SUMIFS('CONTAS A PAGAR SIMULAÇÃO'!$N:$N,'CONTAS A PAGAR SIMULAÇÃO'!$K:$K,'DIÁRIO (2)'!C$3,'CONTAS A PAGAR SIMULAÇÃO'!$S:$S,'DIÁRIO (2)'!$B8) -> 0 | D8: =SUMIFS('CONTAS A PAGAR SIMULAÇÃO'!$N:$N,'CONTAS A PAGAR SIMULAÇÃO'!$K:$K,'DIÁRIO (2)'!D$3,'CONTAS A PAGAR SIMULAÇÃO'!$S:$S,'DIÁRIO (2)'!$B8) -> 0 | E8: =SUMIFS('CONTAS A PAGAR SIMULAÇÃO'!$N:$N,'CONTAS A PAGAR SIMULAÇÃO'!$K:$K,'DIÁRIO (2)'!E$3,'CONTAS A PAGAR SIMULAÇÃO'!$S:$S,'DIÁRIO (2)'!$B8) -> 0 | F8: =SUMIFS('CONTAS A PAGAR SIMULAÇÃO'!$N:$N,'CONTAS A PAGAR SIMULAÇÃO'!$K:$K,'DIÁRIO (2)'!F$3,'CONTAS A PAGAR SIMULAÇÃO'!$S:$S,'DIÁRIO (2)'!$B8) -> 0 | G8: =SUMIFS('CONTAS A PAGAR SIMULAÇÃO'!$N:$N,'CONTAS A PAGAR SIMULAÇÃO'!$K:$K,'DIÁRIO (2)'!G$3,'CONTAS A PAGAR SIMULAÇÃO'!$S:$S,'DIÁRIO (2)'!$B8) -> 0 | H8: =SUMIFS('CONTAS A PAGAR SIMULAÇÃO'!$N:$N,'CONTAS A PAGAR SIMULAÇÃO'!$K:$K,'DIÁRIO (2)'!H$3,'CONTAS A PAGAR SIMULAÇÃO'!$S:$S,'DIÁRIO (2)'!$B8) -> 0 | I8: =SUMIFS('CONTAS A PAGAR SIMULAÇÃO'!$N:$N,'CONTAS A PAGAR SIMULAÇÃO'!$K:$K,'DIÁRIO (2)'!I$3,'CONTAS A PAGAR SIMULAÇÃO'!$S:$S,'DIÁRIO (2)'!$B8) -> 0 | J8: =SUMIFS('CONTAS A PAGAR SIMULAÇÃO'!$N:$N,'CONTAS A PAGAR SIMULAÇÃO'!$K:$K,'DIÁRIO (2)'!J$3,'CONTAS A PAGAR SIMULAÇÃO'!$S:$S,'DIÁRIO (2)'!$B8) -> 0 | ... T8: =SUMIFS('CONTAS A PAGAR SIMULAÇÃO'!$N:$N,'CONTAS A PAGAR SIMULAÇÃO'!$K:$K,'DIÁRIO (2)'!T$3,'CONTAS A PAGAR SIMULAÇÃO'!$S:$S,'DIÁRIO (2)'!$B8) -> 0 | U8: =SUM(C8:T8) -> 0
B9: Aviamento | C9: =SUMIFS('CONTAS A PAGAR SIMULAÇÃO'!$N:$N,'CONTAS A PAGAR SIMULAÇÃO'!$K:$K,'DIÁRIO (2)'!C$3,'CONTAS A PAGAR SIMULAÇÃO'!$S:$S,'DIÁRIO (2)'!$B9) -> 0 | D9: =SUMIFS('CONTAS A PAGAR SIMULAÇÃO'!$N:$N,'CONTAS A PAGAR SIMULAÇÃO'!$K:$K,'DIÁRIO (2)'!D$3,'CONTAS A PAGAR SIMULAÇÃO'!$S:$S,'DIÁRIO (2)'!$B9) -> 2182.6 | E9: =SUMIFS('CONTAS A PAGAR SIMULAÇÃO'!$N:$N,'CONTAS A PAGAR SIMULAÇÃO'!$K:$K,'DIÁRIO (2)'!E$3,'CONTAS A PAGAR SIMULAÇÃO'!$S:$S,'DIÁRIO (2)'!$B9) -> 0 | F9: =SUMIFS('CONTAS A PAGAR SIMULAÇÃO'!$N:$N,'CONTAS A PAGAR SIMULAÇÃO'!$K:$K,'DIÁRIO (2)'!F$3,'CONTAS A PAGAR SIMULAÇÃO'!$S:$S,'DIÁRIO (2)'!$B9) -> 0 | G9: =SUMIFS('CONTAS A PAGAR SIMULAÇÃO'!$N:$N,'CONTAS A PAGAR SIMULAÇÃO'!$K:$K,'DIÁRIO (2)'!G$3,'CONTAS A PAGAR SIMULAÇÃO'!$S:$S,'DIÁRIO (2)'!$B9) -> 0 | H9: =SUMIFS('CONTAS A PAGAR SIMULAÇÃO'!$N:$N,'CONTAS A PAGAR SIMULAÇÃO'!$K:$K,'DIÁRIO (2)'!H$3,'CONTAS A PAGAR SIMULAÇÃO'!$S:$S,'DIÁRIO (2)'!$B9) -> 0 | I9: =SUMIFS('CONTAS A PAGAR SIMULAÇÃO'!$N:$N,'CONTAS A PAGAR SIMULAÇÃO'!$K:$K,'DIÁRIO (2)'!I$3,'CONTAS A PAGAR SIMULAÇÃO'!$S:$S,'DIÁRIO (2)'!$B9) -> 0 | J9: =SUMIFS('CONTAS A PAGAR SIMULAÇÃO'!$N:$N,'CONTAS A PAGAR SIMULAÇÃO'!$K:$K,'DIÁRIO (2)'!J$3,'CONTAS A PAGAR SIMULAÇÃO'!$S:$S,'DIÁRIO (2)'!$B9) -> 2000 | ... T9: =SUMIFS('CONTAS A PAGAR SIMULAÇÃO'!$N:$N,'CONTAS A PAGAR SIMULAÇÃO'!$K:$K,'DIÁRIO (2)'!T$3,'CONTAS A PAGAR SIMULAÇÃO'!$S:$S,'DIÁRIO (2)'!$B9) -> 0 | U9: =SUM(C9:T9) -> 10509.63
B10: Etiquetas | C10: =SUMIFS('CONTAS A PAGAR SIMULAÇÃO'!$N:$N,'CONTAS A PAGAR SIMULAÇÃO'!$K:$K,'DIÁRIO (2)'!C$3,'CONTAS A PAGAR SIMULAÇÃO'!$S:$S,'DIÁRIO (2)'!$B10) -> 0 | D10: =SUMIFS('CONTAS A PAGAR SIMULAÇÃO'!$N:$N,'CONTAS A PAGAR SIMULAÇÃO'!$K:$K,'DIÁRIO (2)'!D$3,'CONTAS A PAGAR SIMULAÇÃO'!$S:$S,'DIÁRIO (2)'!$B10) -> 0 | E10: =SUMIFS('CONTAS A PAGAR SIMULAÇÃO'!$N:$N,'CONTAS A PAGAR SIMULAÇÃO'!$K:$K,'DIÁRIO (2)'!E$3,'CONTAS A PAGAR SIMULAÇÃO'!$S:$S,'DIÁRIO (2)'!$B10) -> 0 | F10: =SUMIFS('CONTAS A PAGAR SIMULAÇÃO'!$N:$N,'CONTAS A PAGAR SIMULAÇÃO'!$K:$K,'DIÁRIO (2)'!F$3,'CONTAS A PAGAR SIMULAÇÃO'!$S:$S,'DIÁRIO (2)'!$B10) -> 0 | G10: =SUMIFS('CONTAS A PAGAR SIMULAÇÃO'!$N:$N,'CONTAS A PAGAR SIMULAÇÃO'!$K:$K,'DIÁRIO (2)'!G$3,'CONTAS A PAGAR SIMULAÇÃO'!$S:$S,'DIÁRIO (2)'!$B10) -> 0 | H10: =SUMIFS('CONTAS A PAGAR SIMULAÇÃO'!$N:$N,'CONTAS A PAGAR SIMULAÇÃO'!$K:$K,'DIÁRIO (2)'!H$3,'CONTAS A PAGAR SIMULAÇÃO'!$S:$S,'DIÁRIO (2)'!$B10) -> 0 | I10: =SUMIFS('CONTAS A PAGAR SIMULAÇÃO'!$N:$N,'CONTAS A PAGAR SIMULAÇÃO'!$K:$K,'DIÁRIO (2)'!I$3,'CONTAS A PAGAR SIMULAÇÃO'!$S:$S,'DIÁRIO (2)'!$B10) -> 0 | J10: =SUMIFS('CONTAS A PAGAR SIMULAÇÃO'!$N:$N,'CONTAS A PAGAR SIMULAÇÃO'!$K:$K,'DIÁRIO (2)'!J$3,'CONTAS A PAGAR SIMULAÇÃO'!$S:$S,'DIÁRIO (2)'!$B10) -> 0 | ... T10: =SUMIFS('CONTAS A PAGAR SIMULAÇÃO'!$N:$N,'CONTAS A PAGAR SIMULAÇÃO'!$K:$K,'DIÁRIO (2)'!T$3,'CONTAS A PAGAR SIMULAÇÃO'!$S:$S,'DIÁRIO (2)'!$B10) -> 0 | U10: =SUM(C10:T10) -> 5294
B11: Bordado Industrial | C11: =SUMIFS('CONTAS A PAGAR SIMULAÇÃO'!$N:$N,'CONTAS A PAGAR SIMULAÇÃO'!$K:$K,'DIÁRIO (2)'!C$3,'CONTAS A PAGAR SIMULAÇÃO'!$S:$S,'DIÁRIO (2)'!$B11) -> 0 | D11: =SUMIFS('CONTAS A PAGAR SIMULAÇÃO'!$N:$N,'CONTAS A PAGAR SIMULAÇÃO'!$K:$K,'DIÁRIO (2)'!D$3,'CONTAS A PAGAR SIMULAÇÃO'!$S:$S,'DIÁRIO (2)'!$B11) -> 0 | E11: =SUMIFS('CONTAS A PAGAR SIMULAÇÃO'!$N:$N,'CONTAS A PAGAR SIMULAÇÃO'!$K:$K,'DIÁRIO (2)'!E$3,'CONTAS A PAGAR SIMULAÇÃO'!$S:$S,'DIÁRIO (2)'!$B11) -> 0 | F11: =SUMIFS('CONTAS A PAGAR SIMULAÇÃO'!$N:$N,'CONTAS A PAGAR SIMULAÇÃO'!$K:$K,'DIÁRIO (2)'!F$3,'CONTAS A PAGAR SIMULAÇÃO'!$S:$S,'DIÁRIO (2)'!$B11) -> 0 | G11: =SUMIFS('CONTAS A PAGAR SIMULAÇÃO'!$N:$N,'CONTAS A PAGAR SIMULAÇÃO'!$K:$K,'DIÁRIO (2)'!G$3,'CONTAS A PAGAR SIMULAÇÃO'!$S:$S,'DIÁRIO (2)'!$B11) -> 0 | H11: =SUMIFS('CONTAS A PAGAR SIMULAÇÃO'!$N:$N,'CONTAS A PAGAR SIMULAÇÃO'!$K:$K,'DIÁRIO (2)'!H$3,'CONTAS A PAGAR SIMULAÇÃO'!$S:$S,'DIÁRIO (2)'!$B11) -> 0 | I11: =SUMIFS('CONTAS A PAGAR SIMULAÇÃO'!$N:$N,'CONTAS A PAGAR SIMULAÇÃO'!$K:$K,'DIÁRIO (2)'!I$3,'CONTAS A PAGAR SIMULAÇÃO'!$S:$S,'DIÁRIO (2)'!$B11) -> 0 | J11: =SUMIFS('CONTAS A PAGAR SIMULAÇÃO'!$N:$N,'CONTAS A PAGAR SIMULAÇÃO'!$K:$K,'DIÁRIO (2)'!J$3,'CONTAS A PAGAR SIMULAÇÃO'!$S:$S,'DIÁRIO (2)'!$B11) -> 0 | ... T11: =SUMIFS('CONTAS A PAGAR SIMULAÇÃO'!$N:$N,'CONTAS A PAGAR SIMULAÇÃO'!$K:$K,'DIÁRIO (2)'!T$3,'CONTAS A PAGAR SIMULAÇÃO'!$S:$S,'DIÁRIO (2)'!$B11) -> 0 | U11: =SUM(C11:T11) -> 0
B12: Embalagens | C12: =SUMIFS('CONTAS A PAGAR SIMULAÇÃO'!$N:$N,'CONTAS A PAGAR SIMULAÇÃO'!$K:$K,'DIÁRIO (2)'!C$3,'CONTAS A PAGAR SIMULAÇÃO'!$S:$S,'DIÁRIO (2)'!$B12) -> 0 | D12: =SUMIFS('CONTAS A PAGAR SIMULAÇÃO'!$N:$N,'CONTAS A PAGAR SIMULAÇÃO'!$K:$K,'DIÁRIO (2)'!D$3,'CONTAS A PAGAR SIMULAÇÃO'!$S:$S,'DIÁRIO (2)'!$B12) -> 0 | E12: =SUMIFS('CONTAS A PAGAR SIMULAÇÃO'!$N:$N,'CONTAS A PAGAR SIMULAÇÃO'!$K:$K,'DIÁRIO (2)'!E$3,'CONTAS A PAGAR SIMULAÇÃO'!$S:$S,'DIÁRIO (2)'!$B12) -> 0 | F12: =SUMIFS('CONTAS A PAGAR SIMULAÇÃO'!$N:$N,'CONTAS A PAGAR SIMULAÇÃO'!$K:$K,'DIÁRIO (2)'!F$3,'CONTAS A PAGAR SIMULAÇÃO'!$S:$S,'DIÁRIO (2)'!$B12) -> 0 | G12: =SUMIFS('CONTAS A PAGAR SIMULAÇÃO'!$N:$N,'CONTAS A PAGAR SIMULAÇÃO'!$K:$K,'DIÁRIO (2)'!G$3,'CONTAS A PAGAR SIMULAÇÃO'!$S:$S,'DIÁRIO (2)'!$B12) -> 0 | H12: =SUMIFS('CONTAS A PAGAR SIMULAÇÃO'!$N:$N,'CONTAS A PAGAR SIMULAÇÃO'!$K:$K,'DIÁRIO (2)'!H$3,'CONTAS A PAGAR SIMULAÇÃO'!$S:$S,'DIÁRIO (2)'!$B12) -> 0 | I12: =SUMIFS('CONTAS A PAGAR SIMULAÇÃO'!$N:$N,'CONTAS A PAGAR SIMULAÇÃO'!$K:$K,'DIÁRIO (2)'!I$3,'CONTAS A PAGAR SIMULAÇÃO'!$S:$S,'DIÁRIO (2)'!$B12) -> 0 | J12: =SUMIFS('CONTAS A PAGAR SIMULAÇÃO'!$N:$N,'CONTAS A PAGAR SIMULAÇÃO'!$K:$K,'DIÁRIO (2)'!J$3,'CONTAS A PAGAR SIMULAÇÃO'!$S:$S,'DIÁRIO (2)'!$B12) -> 0 | ... T12: =SUMIFS('CONTAS A PAGAR SIMULAÇÃO'!$N:$N,'CONTAS A PAGAR SIMULAÇÃO'!$K:$K,'DIÁRIO (2)'!T$3,'CONTAS A PAGAR SIMULAÇÃO'!$S:$S,'DIÁRIO (2)'!$B12) -> 0 | U12: =SUM(C12:T12) -> 0
B13: Criação de Modelos | C13: =SUMIFS('CONTAS A PAGAR SIMULAÇÃO'!$N:$N,'CONTAS A PAGAR SIMULAÇÃO'!$K:$K,'DIÁRIO (2)'!C$3,'CONTAS A PAGAR SIMULAÇÃO'!$S:$S,'DIÁRIO (2)'!$B13) -> 0 | D13: =SUMIFS('CONTAS A PAGAR SIMULAÇÃO'!$N:$N,'CONTAS A PAGAR SIMULAÇÃO'!$K:$K,'DIÁRIO (2)'!D$3,'CONTAS A PAGAR SIMULAÇÃO'!$S:$S,'DIÁRIO (2)'!$B13) -> 0 | E13: =SUMIFS('CONTAS A PAGAR SIMULAÇÃO'!$N:$N,'CONTAS A PAGAR SIMULAÇÃO'!$K:$K,'DIÁRIO (2)'!E$3,'CONTAS A PAGAR SIMULAÇÃO'!$S:$S,'DIÁRIO (2)'!$B13) -> 0 | F13: =SUMIFS('CONTAS A PAGAR SIMULAÇÃO'!$N:$N,'CONTAS A PAGAR SIMULAÇÃO'!$K:$K,'DIÁRIO (2)'!F$3,'CONTAS A PAGAR SIMULAÇÃO'!$S:$S,'DIÁRIO (2)'!$B13) -> 0 | G13: =SUMIFS('CONTAS A PAGAR SIMULAÇÃO'!$N:$N,'CONTAS A PAGAR SIMULAÇÃO'!$K:$K,'DIÁRIO (2)'!G$3,'CONTAS A PAGAR SIMULAÇÃO'!$S:$S,'DIÁRIO (2)'!$B13) -> 0 | H13: =SUMIFS('CONTAS A PAGAR SIMULAÇÃO'!$N:$N,'CONTAS A PAGAR SIMULAÇÃO'!$K:$K,'DIÁRIO (2)'!H$3,'CONTAS A PAGAR SIMULAÇÃO'!$S:$S,'DIÁRIO (2)'!$B13) -> 0 | I13: =SUMIFS('CONTAS A PAGAR SIMULAÇÃO'!$N:$N,'CONTAS A PAGAR SIMULAÇÃO'!$K:$K,'DIÁRIO (2)'!I$3,'CONTAS A PAGAR SIMULAÇÃO'!$S:$S,'DIÁRIO (2)'!$B13) -> 0 | J13: =SUMIFS('CONTAS A PAGAR SIMULAÇÃO'!$N:$N,'CONTAS A PAGAR SIMULAÇÃO'!$K:$K,'DIÁRIO (2)'!J$3,'CONTAS A PAGAR SIMULAÇÃO'!$S:$S,'DIÁRIO (2)'!$B13) -> 0 | ... T13: =SUMIFS('CONTAS A PAGAR SIMULAÇÃO'!$N:$N,'CONTAS A PAGAR SIMULAÇÃO'!$K:$K,'DIÁRIO (2)'!T$3,'CONTAS A PAGAR SIMULAÇÃO'!$S:$S,'DIÁRIO (2)'!$B13) -> 0 | U13: =SUM(C13:T13) -> 0
B14: Salário e Ordenados | C14: =SUMIFS('CONTAS A PAGAR SIMULAÇÃO'!$N:$N,'CONTAS A PAGAR SIMULAÇÃO'!$K:$K,'DIÁRIO (2)'!C$3,'CONTAS A PAGAR SIMULAÇÃO'!$S:$S,'DIÁRIO (2)'!$B14) -> 0 | D14: =SUMIFS('CONTAS A PAGAR SIMULAÇÃO'!$N:$N,'CONTAS A PAGAR SIMULAÇÃO'!$K:$K,'DIÁRIO (2)'!D$3,'CONTAS A PAGAR SIMULAÇÃO'!$S:$S,'DIÁRIO (2)'!$B14) -> 0 | E14: =SUMIFS('CONTAS A PAGAR SIMULAÇÃO'!$N:$N,'CONTAS A PAGAR SIMULAÇÃO'!$K:$K,'DIÁRIO (2)'!E$3,'CONTAS A PAGAR SIMULAÇÃO'!$S:$S,'DIÁRIO (2)'!$B14) -> 0 | F14: =SUMIFS('CONTAS A PAGAR SIMULAÇÃO'!$N:$N,'CONTAS A PAGAR SIMULAÇÃO'!$K:$K,'DIÁRIO (2)'!F$3,'CONTAS A PAGAR SIMULAÇÃO'!$S:$S,'DIÁRIO (2)'!$B14) -> 0 | G14: =SUMIFS('CONTAS A PAGAR SIMULAÇÃO'!$N:$N,'CONTAS A PAGAR SIMULAÇÃO'!$K:$K,'DIÁRIO (2)'!G$3,'CONTAS A PAGAR SIMULAÇÃO'!$S:$S,'DIÁRIO (2)'!$B14) -> 0 | H14: =SUMIFS('CONTAS A PAGAR SIMULAÇÃO'!$N:$N,'CONTAS A PAGAR SIMULAÇÃO'!$K:$K,'DIÁRIO (2)'!H$3,'CONTAS A PAGAR SIMULAÇÃO'!$S:$S,'DIÁRIO (2)'!$B14) -> 0 | I14: =SUMIFS('CONTAS A PAGAR SIMULAÇÃO'!$N:$N,'CONTAS A PAGAR SIMULAÇÃO'!$K:$K,'DIÁRIO (2)'!I$3,'CONTAS A PAGAR SIMULAÇÃO'!$S:$S,'DIÁRIO (2)'!$B14) -> 170 | J14: =SUMIFS('CONTAS A PAGAR SIMULAÇÃO'!$N:$N,'CONTAS A PAGAR SIMULAÇÃO'!$K:$K,'DIÁRIO (2)'!J$3,'CONTAS A PAGAR SIMULAÇÃO'!$S:$S,'DIÁRIO (2)'!$B14) -> 0 | ... T14: =SUMIFS('CONTAS A PAGAR SIMULAÇÃO'!$N:$N,'CONTAS A PAGAR SIMULAÇÃO'!$K:$K,'DIÁRIO (2)'!T$3,'CONTAS A PAGAR SIMULAÇÃO'!$S:$S,'DIÁRIO (2)'!$B14) -> 0 | U14: =SUM(C14:T14) -> 340
B15: Vale Transporte | C15: =SUMIFS('CONTAS A PAGAR SIMULAÇÃO'!$N:$N,'CONTAS A PAGAR SIMULAÇÃO'!$K:$K,'DIÁRIO (2)'!C$3,'CONTAS A PAGAR SIMULAÇÃO'!$S:$S,'DIÁRIO (2)'!$B15) -> 0 | D15: =SUMIFS('CONTAS A PAGAR SIMULAÇÃO'!$N:$N,'CONTAS A PAGAR SIMULAÇÃO'!$K:$K,'DIÁRIO (2)'!D$3,'CONTAS A PAGAR SIMULAÇÃO'!$S:$S,'DIÁRIO (2)'!$B15) -> 0 | E15: =SUMIFS('CONTAS A PAGAR SIMULAÇÃO'!$N:$N,'CONTAS A PAGAR SIMULAÇÃO'!$K:$K,'DIÁRIO (2)'!E$3,'CONTAS A PAGAR SIMULAÇÃO'!$S:$S,'DIÁRIO (2)'!$B15) -> 0 | F15: =SUMIFS('CONTAS A PAGAR SIMULAÇÃO'!$N:$N,'CONTAS A PAGAR SIMULAÇÃO'!$K:$K,'DIÁRIO (2)'!F$3,'CONTAS A PAGAR SIMULAÇÃO'!$S:$S,'DIÁRIO (2)'!$B15) -> 0 | G15: =SUMIFS('CONTAS A PAGAR SIMULAÇÃO'!$N:$N,'CONTAS A PAGAR SIMULAÇÃO'!$K:$K,'DIÁRIO (2)'!G$3,'CONTAS A PAGAR SIMULAÇÃO'!$S:$S,'DIÁRIO (2)'!$B15) -> 0 | H15: =SUMIFS('CONTAS A PAGAR SIMULAÇÃO'!$N:$N,'CONTAS A PAGAR SIMULAÇÃO'!$K:$K,'DIÁRIO (2)'!H$3,'CONTAS A PAGAR SIMULAÇÃO'!$S:$S,'DIÁRIO (2)'!$B15) -> 0 | I15: =SUMIFS('CONTAS A PAGAR SIMULAÇÃO'!$N:$N,'CONTAS A PAGAR SIMULAÇÃO'!$K:$K,'DIÁRIO (2)'!I$3,'CONTAS A PAGAR SIMULAÇÃO'!$S:$S,'DIÁRIO (2)'!$B15) -> 0 | J15: =SUMIFS('CONTAS A PAGAR SIMULAÇÃO'!$N:$N,'CONTAS A PAGAR SIMULAÇÃO'!$K:$K,'DIÁRIO (2)'!J$3,'CONTAS A PAGAR SIMULAÇÃO'!$S:$S,'DIÁRIO (2)'!$B15) -> 0 | ... T15: =SUMIFS('CONTAS A PAGAR SIMULAÇÃO'!$N:$N,'CONTAS A PAGAR SIMULAÇÃO'!$K:$K,'DIÁRIO (2)'!T$3,'CONTAS A PAGAR SIMULAÇÃO'!$S:$S,'DIÁRIO (2)'!$B15) -> 0 | U15: =SUM(C15:T15) -> 0
... B65: Fgts, Gps e Pis | C65: =SUMIFS('CONTAS A PAGAR SIMULAÇÃO'!$N:$N,'CONTAS A PAGAR SIMULAÇÃO'!$K:$K,'DIÁRIO (2)'!C$3,'CONTAS A PAGAR SIMULAÇÃO'!$S:$S,'DIÁRIO (2)'!$B65) -> 0 | D65: =SUMIFS('CONTAS A PAGAR SIMULAÇÃO'!$N:$N,'CONTAS A PAGAR SIMULAÇÃO'!$K:$K,'DIÁRIO (2)'!D$3,'CONTAS A PAGAR SIMULAÇÃO'!$S:$S,'DIÁRIO (2)'!$B65) -> 0 | E65: =SUMIFS('CONTAS A PAGAR SIMULAÇÃO'!$N:$N,'CONTAS A PAGAR SIMULAÇÃO'!$K:$K,'DIÁRIO (2)'!E$3,'CONTAS A PAGAR SIMULAÇÃO'!$S:$S,'DIÁRIO (2)'!$B65) -> 0 | F65: =SUMIFS('CONTAS A PAGAR SIMULAÇÃO'!$N:$N,'CONTAS A PAGAR SIMULAÇÃO'!$K:$K,'DIÁRIO (2)'!F$3,'CONTAS A PAGAR SIMULAÇÃO'!$S:$S,'DIÁRIO (2)'!$B65) -> 0 | G65: =SUMIFS('CONTAS A PAGAR SIMULAÇÃO'!$N:$N,'CONTAS A PAGAR SIMULAÇÃO'!$K:$K,'DIÁRIO (2)'!G$3,'CONTAS A PAGAR SIMULAÇÃO'!$S:$S,'DIÁRIO (2)'!$B65) -> 0 | H65: =SUMIFS('CONTAS A PAGAR SIMULAÇÃO'!$N:$N,'CONTAS A PAGAR SIMULAÇÃO'!$K:$K,'DIÁRIO (2)'!H$3,'CONTAS A PAGAR SIMULAÇÃO'!$S:$S,'DIÁRIO (2)'!$B65) -> 0 | I65: =SUMIFS('CONTAS A PAGAR SIMULAÇÃO'!$N:$N,'CONTAS A PAGAR SIMULAÇÃO'!$K:$K,'DIÁRIO (2)'!I$3,'CONTAS A PAGAR SIMULAÇÃO'!$S:$S,'DIÁRIO (2)'!$B65) -> 3989.34 | J65: =SUMIFS('CONTAS A PAGAR SIMULAÇÃO'!$N:$N,'CONTAS A PAGAR SIMULAÇÃO'!$K:$K,'DIÁRIO (2)'!J$3,'CONTAS A PAGAR SIMULAÇÃO'!$S:$S,'DIÁRIO (2)'!$B65) -> 0 | ... T65: =SUMIFS('CONTAS A PAGAR SIMULAÇÃO'!$N:$N,'CONTAS A PAGAR SIMULAÇÃO'!$K:$K,'DIÁRIO (2)'!T$3,'CONTAS A PAGAR SIMULAÇÃO'!$S:$S,'DIÁRIO (2)'!$B65) -> 0 | U65: =SUM(C65:T65) -> 3989.34

Sheet POR FORNECEDOR
A1: PESSOA | B1: JULHO | C1: AGOSTO | D1: SETEMBRO | E1: OUTUBRO | F1: NOVEMBRO | G1: DEZEMBRO | H1: TOTAL
A2: ALVO TEXTIL | B2: =SUMIFS('CONTAS A PAGAR'!$N:$N,'CONTAS A PAGAR'!$H:$H,'POR FORNECEDOR'!$A2,'CONTAS A PAGAR'!$Z:$Z,'POR FORNECEDOR'!B$1) -> 0 | C2: =SUMIFS('CONTAS A PAGAR'!$N:$N,'CONTAS A PAGAR'!$H:$H,'POR FORNECEDOR'!$A2,'CONTAS A PAGAR'!$Z:$Z,'POR FORNECEDOR'!C$1) -> 0 | D2: =SUMIFS('CONTAS A PAGAR'!$N:$N,'CONTAS A PAGAR'!$H:$H,'POR FORNECEDOR'!$A2,'CONTAS A PAGAR'!$Z:$Z,'POR FORNECEDOR'!D$1) -> 0 | E2: =SUMIFS('CONTAS A PAGAR'!$N:$N,'CONTAS A PAGAR'!$H:$H,'POR FORNECEDOR'!$A2,'CONTAS A PAGAR'!$Z:$Z,'POR FORNECEDOR'!E$1) -> 0 | F2: =SUMIFS('CONTAS A PAGAR'!$N:$N,'CONTAS A PAGAR'!$H:$H,'POR FORNECEDOR'!$A2,'CONTAS A PAGAR'!$Z:$Z,'POR FORNECEDOR'!F$1) -> 0 | G2: =SUMIFS('CONTAS A PAGAR'!$N:$N,'CONTAS A PAGAR'!$H:$H,'POR FORNECEDOR'!$A2,'CONTAS A PAGAR'!$Z:$Z,'POR FORNECEDOR'!G$1) -> 0 | H2: =SUM(E2:G2) -> 0
A3: LÍDER TECIDOS | B3: =SUMIFS('CONTAS A PAGAR'!$N:$N,'CONTAS A PAGAR'!$H:$H,'POR FORNECEDOR'!$A3,'CONTAS A PAGAR'!$Z:$Z,'POR FORNECEDOR'!B$1) -> 0 | C3: =SUMIFS('CONTAS A PAGAR'!$N:$N,'CONTAS A PAGAR'!$H:$H,'POR FORNECEDOR'!$A3,'CONTAS A PAGAR'!$Z:$Z,'POR FORNECEDOR'!C$1) -> 0 | D3: =SUMIFS('CONTAS A PAGAR'!$N:$N,'CONTAS A PAGAR'!$H:$H,'POR FORNECEDOR'!$A3,'CONTAS A PAGAR'!$Z:$Z,'POR FORNECEDOR'!D$1) -> 0 | E3: =SUMIFS('CONTAS A PAGAR'!$N:$N,'CONTAS A PAGAR'!$H:$H,'POR FORNECEDOR'!$A3,'CONTAS A PAGAR'!$Z:$Z,'POR FORNECEDOR'!E$1) -> 0 | F3: =SUMIFS('CONTAS A PAGAR'!$N:$N,'CONTAS A PAGAR'!$H:$H,'POR FORNECEDOR'!$A3,'CONTAS A PAGAR'!$Z:$Z,'POR FORNECEDOR'!F$1) -> 0 | G3: =SUMIFS('CONTAS A PAGAR'!$N:$N,'CONTAS A PAGAR'!$H:$H,'POR FORNECEDOR'!$A3,'CONTAS A PAGAR'!$Z:$Z,'POR FORNECEDOR'!G$1) -> 0 | H3: =SUM(E3:G3) -> 0
A4: VICUNHA TEXTIL S/A. | B4: =SUMIFS('CONTAS A PAGAR'!$N:$N,'CONTAS A PAGAR'!$H:$H,'POR FORNECEDOR'!$A4,'CONTAS A PAGAR'!$Z:$Z,'POR FORNECEDOR'!B$1) -> 0 | C4: =SUMIFS('CONTAS A PAGAR'!$N:$N,'CONTAS A PAGAR'!$H:$H,'POR FORNECEDOR'!$A4,'CONTAS A PAGAR'!$Z:$Z,'POR FORNECEDOR'!C$1) -> 0 | D4: =SUMIFS('CONTAS A PAGAR'!$N:$N,'CONTAS A PAGAR'!$H:$H,'POR FORNECEDOR'!$A4,'CONTAS A PAGAR'!$Z:$Z,'POR FORNECEDOR'!D$1) -> 0 | E4: =SUMIFS('CONTAS A PAGAR'!$N:$N,'CONTAS A PAGAR'!$H:$H,'POR FORNECEDOR'!$A4,'CONTAS A PAGAR'!$Z:$Z,'POR FORNECEDOR'!E$1) -> 0 | F4: =SUMIFS('CONTAS A PAGAR'!$N:$N,'CONTAS A PAGAR'!$H:$H,'POR FORNECEDOR'!$A4,'CONTAS A PAGAR'!$Z:$Z,'POR FORNECEDOR'!F$1) -> 0 | G4: =SUMIFS('CONTAS A PAGAR'!$N:$N,'CONTAS A PAGAR'!$H:$H,'POR FORNECEDOR'!$A4,'CONTAS A PAGAR'!$Z:$Z,'POR FORNECEDOR'!G$1) -> 0 | H4: =SUM(E4:G4) -> 0
A5: EXCIM IMPORTAÇÃO E EXPORTAÇÃO LTDA | B5: =SUMIFS('CONTAS A PAGAR'!$N:$N,'CONTAS A PAGAR'!$H:$H,'POR FORNECEDOR'!$A5,'CONTAS A PAGAR'!$Z:$Z,'POR FORNECEDOR'!B$1) -> 0 | C5: =SUMIFS('CONTAS A PAGAR'!$N:$N,'CONTAS A PAGAR'!$H:$H,'POR FORNECEDOR'!$A5,'CONTAS A PAGAR'!$Z:$Z,'POR FORNECEDOR'!C$1) -> 0 | D5: =SUMIFS('CONTAS A PAGAR'!$N:$N,'CONTAS A PAGAR'!$H:$H,'POR FORNECEDOR'!$A5,'CONTAS A PAGAR'!$Z:$Z,'POR FORNECEDOR'!D$1) -> 0 | E5: =SUMIFS('CONTAS A PAGAR'!$N:$N,'CONTAS A PAGAR'!$H:$H,'POR FORNECEDOR'!$A5,'CONTAS A PAGAR'!$Z:$Z,'POR FORNECEDOR'!E$1) -> 0 | F5: =SUMIFS('CONTAS A PAGAR'!$N:$N,'CONTAS A PAGAR'!$H:$H,'POR FORNECEDOR'!$A5,'CONTAS A PAGAR'!$Z:$Z,'POR FORNECEDOR'!F$1) -> 0 | G5: =SUMIFS('CONTAS A PAGAR'!$N:$N,'CONTAS A PAGAR'!$H:$H,'POR FORNECEDOR'!$A5,'CONTAS A PAGAR'!$Z:$Z,'POR FORNECEDOR'!G$1) -> 0 | H5: =SUM(E5:G5) -> 0
A6: SANTISTA TEXTIL | B6: =SUMIFS('CONTAS A PAGAR'!$N:$N,'CONTAS A PAGAR'!$H:$H,'POR FORNECEDOR'!$A6,'CONTAS A PAGAR'!$Z:$Z,'POR FORNECEDOR'!B$1) -> 0 | C6: =SUMIFS('CONTAS A PAGAR'!$N:$N,'CONTAS A PAGAR'!$H:$H,'POR FORNECEDOR'!$A6,'CONTAS A PAGAR'!$Z:$Z,'POR FORNECEDOR'!C$1) -> 0 | D6: =SUMIFS('CONTAS A PAGAR'!$N:$N,'CONTAS A PAGAR'!$H:$H,'POR FORNECEDOR'!$A6,'CONTAS A PAGAR'!$Z:$Z,'POR FORNECEDOR'!D$1) -> 0 | E6: =SUMIFS('CONTAS A PAGAR'!$N:$N,'CONTAS A PAGAR'!$H:$H,'POR FORNECEDOR'!$A6,'CONTAS A PAGAR'!$Z:$Z,'POR FORNECEDOR'!E$1) -> 0 | F6: =SUMIFS('CONTAS A PAGAR'!$N:$N,'CONTAS A PAGAR'!$H:$H,'POR FORNECEDOR'!$A6,'CONTAS A PAGAR'!$Z:$Z,'POR FORNECEDOR'!F$1) -> 0 | G6: =SUMIFS('CONTAS A PAGAR'!$N:$N,'CONTAS A PAGAR'!$H:$H,'POR FORNECEDOR'!$A6,'CONTAS A PAGAR'!$Z:$Z,'POR FORNECEDOR'!G$1) -> 0 | H6: =SUM(E6:G6) -> 0
A7: CEDRO TEXTIL | B7: =SUMIFS('CONTAS A PAGAR'!$N:$N,'CONTAS A PAGAR'!$H:$H,'POR FORNECEDOR'!$A7,'CONTAS A PAGAR'!$Z:$Z,'POR FORNECEDOR'!B$1) -> 0 | C7: =SUMIFS('CONTAS A PAGAR'!$N:$N,'CONTAS A PAGAR'!$H:$H,'POR FORNECEDOR'!$A7,'CONTAS A PAGAR'!$Z:$Z,'POR FORNECEDOR'!C$1) -> 0 | D7: =SUMIFS('CONTAS A PAGAR'!$N:$N,'CONTAS A PAGAR'!$H:$H,'POR FORNECEDOR'!$A7,'CONTAS A PAGAR'!$Z:$Z,'POR FORNECEDOR'!D$1) -> 0 | E7: =SUMIFS('CONTAS A PAGAR'!$N:$N,'CONTAS A PAGAR'!$H:$H,'POR FORNECEDOR'!$A7,'CONTAS A PAGAR'!$Z:$Z,'POR FORNECEDOR'!E$1) -> 0 | F7: =SUMIFS('CONTAS A PAGAR'!$N:$N,'CONTAS A PAGAR'!$H:$H,'POR FORNECEDOR'!$A7,'CONTAS A PAGAR'!$Z:$Z,'POR FORNECEDOR'!F$1) -> 0 | G7: =SUMIFS('CONTAS A PAGAR'!$N:$N,'CONTAS A PAGAR'!$H:$H,'POR FORNECEDOR'!$A7,'CONTAS A PAGAR'!$Z:$Z,'POR FORNECEDOR'!G$1) -> 0 | H7: 473000 | I7: AMILTON
A8: JOAO - CAPITAL DE GIRO | B8: =SUMIFS('CONTAS A PAGAR'!$N:$N,'CONTAS A PAGAR'!$H:$H,'POR FORNECEDOR'!$A8,'CONTAS A PAGAR'!$Z:$Z,'POR FORNECEDOR'!B$1) -> 0 | C8: =SUMIFS('CONTAS A PAGAR'!$N:$N,'CONTAS A PAGAR'!$H:$H,'POR FORNECEDOR'!$A8,'CONTAS A PAGAR'!$Z:$Z,'POR FORNECEDOR'!C$1) -> 0 | D8: =SUMIFS('CONTAS A PAGAR'!$N:$N,'CONTAS A PAGAR'!$H:$H,'POR FORNECEDOR'!$A8,'CONTAS A PAGAR'!$Z:$Z,'POR FORNECEDOR'!D$1) -> 0 | E8: =SUMIFS('CONTAS A PAGAR'!$N:$N,'CONTAS A PAGAR'!$H:$H,'POR FORNECEDOR'!$A8,'CONTAS A PAGAR'!$Z:$Z,'POR FORNECEDOR'!E$1) -> 0 | F8: =SUMIFS('CONTAS A PAGAR'!$N:$N,'CONTAS A PAGAR'!$H:$H,'POR FORNECEDOR'!$A8,'CONTAS A PAGAR'!$Z:$Z,'POR FORNECEDOR'!F$1) -> 0 | G8: =SUMIFS('CONTAS A PAGAR'!$N:$N,'CONTAS A PAGAR'!$H:$H,'POR FORNECEDOR'!$A8,'CONTAS A PAGAR'!$Z:$Z,'POR FORNECEDOR'!G$1) -> 0 | H8: =SUM(E8:G8) -> 0
A9: TEXTIL CANATIBA LTDA | B9: =SUMIFS('CONTAS A PAGAR'!$N:$N,'CONTAS A PAGAR'!$H:$H,'POR FORNECEDOR'!$A9,'CONTAS A PAGAR'!$Z:$Z,'POR FORNECEDOR'!B$1) -> 0 | C9: =SUMIFS('CONTAS A PAGAR'!$N:$N,'CONTAS A PAGAR'!$H:$H,'POR FORNECEDOR'!$A9,'CONTAS A PAGAR'!$Z:$Z,'POR FORNECEDOR'!C$1) -> 0 | D9: =SUMIFS('CONTAS A PAGAR'!$N:$N,'CONTAS A PAGAR'!$H:$H,'POR FORNECEDOR'!$A9,'CONTAS A PAGAR'!$Z:$Z,'POR FORNECEDOR'!D$1) -> 0 | E9: =SUMIFS('CONTAS A PAGAR'!$N:$N,'CONTAS A PAGAR'!$H:$H,'POR FORNECEDOR'!$A9,'CONTAS A PAGAR'!$Z:$Z,'POR FORNECEDOR'!E$1) -> 0 | F9: =SUMIFS('CONTAS A PAGAR'!$N:$N,'CONTAS A PAGAR'!$H:$H,'POR FORNECEDOR'!$A9,'CONTAS A PAGAR'!$Z:$Z,'POR FORNECEDOR'!F$1) -> 0 | G9: =SUMIFS('CONTAS A PAGAR'!$N:$N,'CONTAS A PAGAR'!$H:$H,'POR FORNECEDOR'!$A9,'CONTAS A PAGAR'!$Z:$Z,'POR FORNECEDOR'!G$1) -> 0 | H9: =SUM(E9:G9) -> 0
A10: SERGITEX TEXTIL RANDAL | B10: =SUMIFS('CONTAS A PAGAR'!$N:$N,'CONTAS A PAGAR'!$H:$H,'POR FORNECEDOR'!$A10,'CONTAS A PAGAR'!$Z:$Z,'POR FORNECEDOR'!B$1) -> 0 | C10: =SUMIFS('CONTAS A PAGAR'!$N:$N,'CONTAS A PAGAR'!$H:$H,'POR FORNECEDOR'!$A10,'CONTAS A PAGAR'!$Z:$Z,'POR FORNECEDOR'!C$1) -> 0 | D10: =SUMIFS('CONTAS A PAGAR'!$N:$N,'CONTAS A PAGAR'!$H:$H,'POR FORNECEDOR'!$A10,'CONTAS A PAGAR'!$Z:$Z,'POR FORNECEDOR'!D$1) -> 0 | E10: =SUMIFS('CONTAS A PAGAR'!$N:$N,'CONTAS A PAGAR'!$H:$H,'POR FORNECEDOR'!$A10,'CONTAS A PAGAR'!$Z:$Z,'POR FORNECEDOR'!E$1) -> 0 | F10: =SUMIFS('CONTAS A PAGAR'!$N:$N,'CONTAS A PAGAR'!$H:$H,'POR FORNECEDOR'!$A10,'CONTAS A PAGAR'!$Z:$Z,'POR FORNECEDOR'!F$1) -> 0 | G10: =SUMIFS('CONTAS A PAGAR'!$N:$N,'CONTAS A PAGAR'!$H:$H,'POR FORNECEDOR'!$A10,'CONTAS A PAGAR'!$Z:$Z,'POR FORNECEDOR'!G$1) -> 0 | H10: =SUM(E10:G10) -> 0
A11: CIA FIACAO E TECIDOS CEDRO E CACHOE | B11: =SUMIFS('CONTAS A PAGAR'!$N:$N,'CONTAS A PAGAR'!$H:$H,'POR FORNECEDOR'!$A11,'CONTAS A PAGAR'!$Z:$Z,'POR FORNECEDOR'!B$1) -> 0 | C11: =SUMIFS('CONTAS A PAGAR'!$N:$N,'CONTAS A PAGAR'!$H:$H,'POR FORNECEDOR'!$A11,'CONTAS A PAGAR'!$Z:$Z,'POR FORNECEDOR'!C$1) -> 0 | D11: =SUMIFS('CONTAS A PAGAR'!$N:$N,'CONTAS A PAGAR'!$H:$H,'POR FORNECEDOR'!$A11,'CONTAS A PAGAR'!$Z:$Z,'POR FORNECEDOR'!D$1) -> 0 | E11: =SUMIFS('CONTAS A PAGAR'!$N:$N,'CONTAS A PAGAR'!$H:$H,'POR FORNECEDOR'!$A11,'CONTAS A PAGAR'!$Z:$Z,'POR FORNECEDOR'!E$1) -> 0 | F11: =SUMIFS('CONTAS A PAGAR'!$N:$N,'CONTAS A PAGAR'!$H:$H,'POR FORNECEDOR'!$A11,'CONTAS A PAGAR'!$Z:$Z,'POR FORNECEDOR'!F$1) -> 0 | G11: =SUMIFS('CONTAS A PAGAR'!$N:$N,'CONTAS A PAGAR'!$H:$H,'POR FORNECEDOR'!$A11,'CONTAS A PAGAR'!$Z:$Z,'POR FORNECEDOR'!G$1) -> 0 | H11: =SUM(E11:G11) -> 0
A12: TEXTIL FAVERO LTDA | B12: =SUMIFS('CONTAS A PAGAR'!$N:$N,'CONTAS A PAGAR'!$H:$H,'POR FORNECEDOR'!$A12,'CONTAS A PAGAR'!$Z:$Z,'POR FORNECEDOR'!B$1) -> 0 | C12: =SUMIFS('CONTAS A PAGAR'!$N:$N,'CONTAS A PAGAR'!$H:$H,'POR FORNECEDOR'!$A12,'CONTAS A PAGAR'!$Z:$Z,'POR FORNECEDOR'!C$1) -> 0 | D12: =SUMIFS('CONTAS A PAGAR'!$N:$N,'CONTAS A PAGAR'!$H:$H,'POR FORNECEDOR'!$A12,'CONTAS A PAGAR'!$Z:$Z,'POR FORNECEDOR'!D$1) -> 0 | E12: =SUMIFS('CONTAS A PAGAR'!$N:$N,'CONTAS A PAGAR'!$H:$H,'POR FORNECEDOR'!$A12,'CONTAS A PAGAR'!$Z:$Z,'POR FORNECEDOR'!E$1) -> 0 | F12: =SUMIFS('CONTAS A PAGAR'!$N:$N,'CONTAS A PAGAR'!$H:$H,'POR FORNECEDOR'!$A12,'CONTAS A PAGAR'!$Z:$Z,'POR FORNECEDOR'!F$1) -> 0 | G12: =SUMIFS('CONTAS A PAGAR'!$N:$N,'CONTAS A PAGAR'!$H:$H,'POR FORNECEDOR'!$A12,'CONTAS A PAGAR'!$Z:$Z,'POR FORNECEDOR'!G$1) -> 0 | H12: =SUM(E12:G12) -> 0
A13: TEXTIL FAVERO | B13: =SUMIFS('CONTAS A PAGAR'!$N:$N,'CONTAS A PAGAR'!$H:$H,'POR FORNECEDOR'!$A13,'CONTAS A PAGAR'!$Z:$Z,'POR FORNECEDOR'!B$1) -> 0 | C13: =SUMIFS('CONTAS A PAGAR'!$N:$N,'CONTAS A PAGAR'!$H:$H,'POR FORNECEDOR'!$A13,'CONTAS A PAGAR'!$Z:$Z,'POR FORNECEDOR'!C$1) -> 0 | D13: =SUMIFS('CONTAS A PAGAR'!$N:$N,'CONTAS A PAGAR'!$H:$H,'POR FORNECEDOR'!$A13,'CONTAS A PAGAR'!$Z:$Z,'POR FORNECEDOR'!D$1) -> 0 | E13: =SUMIFS('CONTAS A PAGAR'!$N:$N,'CONTAS A PAGAR'!$H:$H,'POR FORNECEDOR'!$A13,'CONTAS A PAGAR'!$Z:$Z,'POR FORNECEDOR'!E$1) -> 0 | F13: =SUMIFS('CONTAS A PAGAR'!$N:$N,'CONTAS A PAGAR'!$H:$H,'POR FORNECEDOR'!$A13,'CONTAS A PAGAR'!$Z:$Z,'POR FORNECEDOR'!F$1) -> 0 | G13: =SUMIFS('CONTAS A PAGAR'!$N:$N,'CONTAS A PAGAR'!$H:$H,'POR FORNECEDOR'!$A13,'CONTAS A PAGAR'!$Z:$Z,'POR FORNECEDOR'!G$1) -> 0 | H13: =SUM(E13:G13) -> 0
E22: rossi.caetano@cedro.ind.br

Sheet CONTAS A PAGAR SIMULAÇÃO
A1: EMP. CADASTRO | B1: EMP.REFERENTE | C1: ID | D1: ID.ITEM | E1: DOCUMENTO | F1: COD. PESSOA | G1: CNPJ | H1: PESSOA | I1: DT. CAD. | J1: DT. EMISSÃO | K1: DT. VENC. | L1: DT. BAIXA | M1: FORMA PAGTO. | N1: VALOR | O1: VALOR PAGO | P1: SIT | Q1: ID.PL.CONTAS | R1: COD. PL CONTAS | S1: PLANO DE CONTAS | T1: CENTRO DE CUSTO | U1: COD.CONTA | V1: CONTA | W1: ORIGEM CAD.PESSOAS | X1: OBS.: | Y1: MÊS | Z1: MÊS TEXTO
A2: 1154 | B2: 1154 | C2: 985 | D2: 6 | E2: 002822-6/_x000D_ 6 | F2: 1979 | H2: ALVO TEXTIL | I2: 45616 | J2: 45616 | K2: 45836 | L2: 45839 | M2: CHEQUE - EMPRESA | N2: 4800 | O2: 4800 | P2: B | Q2: 26 | R2: 02.01.09 | S2: Tecidos | T2: CODI.COM JEANS | V2: ITAU ALV | W2: Sem Origem | Y2: =IF(L2="",K2,L2) -> 45839 | Z2: =TEXT(Y2,"MMMM") -> julho
A3: 1154 | B3: 1154 | C3: 986 | D3: 1 | E3: 002823-1/_x000D_ 6 | F3: 1979 | H3: ALVO TEXTIL | I3: 45616 | J3: 45616 | K3: 45838 | L3: 45839 | M3: CHEQUE - EMPRESA | N3: 4800 | O3: 4800 | P3: B | Q3: 26 | R3: 02.01.09 | S3: Tecidos | T3: CODI.COM JEANS | V3: ITAU ALV | W3: Sem Origem | Y3: =IF(L3="",K3,L3) -> 45839 | Z3: =TEXT(Y3,"MMMM") -> julho
A4: 1154 | B4: 1154 | C4: 1189 | D4: 6 | E4: 002842-6/_x000D_ 6 | F4: 1985 | H4: LÍDER TECIDOS | I4: 45653 | J4: 45653 | K4: 45838 | L4: 45839 | M4: CHEQUE - EMPRESA | N4: 4880 | O4: 4880 | P4: B | Q4: 26 | R4: 02.01.09 | S4: Tecidos | T4: CODI.COM JEANS | V4: ITAU ALV | W4: Sem Origem | Y4: =IF(L4="",K4,L4) -> 45839 | Z4: =TEXT(Y4,"MMMM") -> julho
A5: 1154 | B5: 1154 | C5: 1645 | D5: 1 | E5: 002892-4/_x000D_ 42 | F5: 1985 | H5: LÍDER TECIDOS | I5: 45733 | J5: 45733 | K5: 45838 | L5: 45839 | M5: CHEQUE - EMPRESA | N5: 4920 | O5: 4920 | P5: B | Q5: 26 | R5: 02.01.09 | S5: Tecidos | T5: DESPESAS FONECEDORES | V5: ITAU ALV | W5: Sem Origem | Y5: =IF(L5="",K5,L5) -> 45839 | Z5: =TEXT(Y5,"MMMM") -> julho
A6: 1154 | B6: 1154 | C6: 1963 | D6: 1 | E6: 002880-2/_x000D_ 3 | F6: 2182 | H6: BLESSED LAVANDERIA | I6: 45757 | J6: 45757 | K6: 45838 | L6: 45839 | M6: CHEQUE - EMPRESA | N6: 4200 | O6: 4200 | P6: B | Q6: 28 | R6: 02.01.11 | S6: Lavanderia | T6: DESPESAS FONECEDORES | V6: ITAU ALV | W6: Sem Origem | Y6: =IF(L6="",K6,L6) -> 45839 | Z6: =TEXT(Y6,"MMMM") -> julho
A7: 1154 | B7: 1154 | C7: 2037 | D7: 2 | E7: 0722555-2_x000D_ /3 | F7: 1526 | G7: 07.332.190/0007-89 | H7: VICUNHA TEXTIL S/A. | I7: 45769 | J7: 45769 | K7: 45839 | L7: 45839 | M7: BOLETO BANCÁRIO | N7: 2487.92 | O7: 2487.92 | P7: B | Q7: 26 | R7: 02.01.09 | S7: Tecidos | T7: DESPESAS FONECEDORES | V7: ITAU ALV | W7: Sem Origem | X7: Cyros Tecidos Sarja | Y7: =IF(L7="",K7,L7) -> 45839 | Z7: =TEXT(Y7,"MMMM") -> julho
A8: 1154 | B8: 1154 | C8: 2198 | D8: 1 | E8: 2T-OP271_x000D_ -1/1 | F8: 1957 | H8: ROGERIO - TRAVETE | I8: 45782 | J8: 45782 | K8: 45843 | L8: 45839 | M8: PIX ITAU ALV | N8: 119 | O8: 119 | P8: B | Q8: 27 | R8: 02.01.10 | S8: Travete | T8: DESPESAS FONECEDORES | V8: ITAU ALV | W8: Sem Origem | X8: Pagamento de Ordens de Serviço:895, | Y8: =IF(L8="",K8,L8) -> 45839 | Z8: =TEXT(Y8,"MMMM") -> julho
A9: 1154 | B9: 1154 | C9: 2238 | D9: 1 | E9: 2T-OP274_x000D_ -1/1 | F9: 1957 | H9: ROGERIO - TRAVETE | I9: 45783 | J9: 45783 | K9: 45843 | L9: 45839 | M9: PIX ITAU ALV | N9: 195 | O9: 195 | P9: B | Q9: 27 | R9: 02.01.10 | S9: Travete | T9: DESPESAS FONECEDORES | V9: ITAU ALV | W9: Sem Origem | X9: Pagamento de Ordens de Serviço:904, | Y9: =IF(L9="",K9,L9) -> 45839 | Z9: =TEXT(Y9,"MMMM") -> julho
A10: 1154 | B10: 1154 | C10: 2501 | D10: 1 | E10: 2T-OP268_x000D_ -1/1 | F10: 2142 | H10: ADRIANO-FACÇÃO | I10: 45807 | J10: 45807 | K10: 45810 | L10: 45839 | M10: PIX ITAU ALV | N10: 1963.5 | O10: 1963.5 | P10: B | Q10: 21 | R10: 02.01.04 | S10: Facção | T10: DESPESAS FONECEDORES | V10: ITAU ALV | W10: Sem Origem | Y10: =IF(L10="",K10,L10) -> 45839 | Z10: =TEXT(Y10,"MMMM") -> julho
A11: 1154 | B11: 1154 | C11: 2502 | D11: 1 | E11: 2T-OP283_x000D_ -1/1 | F11: 1956 | H11: EMERSON - FACÇÃO | I11: 45807 | J11: 45807 | K11: 45810 | L11: 45839 | M11: PIX ITAU ALV | N11: 2310 | O11: 2310 | P11: B | Q11: 21 | R11: 02.01.04 | S11: Facção | T11: DESPESAS FONECEDORES | V11: ITAU ALV | W11: Sem Origem | Y11: =IF(L11="",K11,L11) -> 45839 | Z11: =TEXT(Y11,"MMMM") -> julho
A12: 1154 | B12: 1154 | C12: 2652 | D12: 1 | E12: 2T-OP324_x000D_ -1/1 | F12: 2531 | H12: JUNIOR FACÇÃO | I12: 45824 | J12: 45824 | K12: 45824 | L12: 45839 | M12: PIX ITAU ALV | N12: 1680 | O12: 1680 | P12: B | Q12: 21 | R12: 02.01.04 | S12: Facção | T12: DESPESAS FONECEDORES | V12: ITAU ALV | W12: Sem Origem | X12: Pagamento de Ordens de Serviço:1056, | Y12: =IF(L12="",K12,L12) -> 45839 | Z12: =TEXT(Y12,"MMMM") -> julho
A13: 1154 | B13: 1154 | C13: 2691 | D13: 1 | E13: 2T-OP331_x000D_ -1/1 | F13: 1954 | H13: HERON - FACÇÃO | I13: 45825 | J13: 45825 | K13: 45831 | L13: 45839 | M13: PIX ITAU ALV | N13: 2070 | O13: 2070 | P13: B | Q13: 21 | R13: 02.01.04 | S13: Facção | T13: DESPESAS FONECEDORES | V13: ITAU ALV | W13: Sem Origem | X13: Pagamento de Ordens de Serviço:1077, | Y13: =IF(L13="",K13,L13) -> 45839 | Z13: =TEXT(Y13,"MMMM") -> julho
A14: 1154 | B14: 1154 | C14: 2694 | D14: 1 | E14: 2T-OP332_x000D_ -1/1 | F14: 1954 | H14: HERON - FACÇÃO | I14: 45825 | J14: 45825 | K14: 45838 | L14: 45839 | M14: PIX ITAU ALV | N14: 1771 | O14: 1771 | P14: B | Q14: 21 | R14: 02.01.04 | S14: Facção | T14: DESPESAS FONECEDORES | V14: ITAU ALV | W14: Sem Origem | X14: Pagamento de Ordens de Serviço:1080, | Y14: =IF(L14="",K14,L14) -> 45839 | Z14: =TEXT(Y14,"MMMM") -> julho
A15: 1154 | B15: 1154 | C15: 2697 | D15: 1 | E15: 2T-OP333_x000D_ -1/1 | F15: 2142 | H15: ADRIANO-FACÇÃO | I15: 45825 | J15: 45825 | K15: 45831 | L15: 45839 | M15: PIX ITAU ALV | N15: 2116 | O15: 2116 | P15: B | Q15: 21 | R15: 02.01.04 | S15: Facção | T15: DESPESAS FONECEDORES | V15: ITAU ALV | W15: Sem Origem | X15: Pagamento de Ordens de Serviço:1083, | Y15: =IF(L15="",K15,L15) -> 45839 | Z15: =TEXT(Y15,"MMMM") -> julho
A16: 1154 | B16: 1154 | C16: 2704 | D16: 1 | E16: 2T-OP332_x000D_ -1/1 | F16: 2569 | H16: DIVINO-ACABAMENTO | I16: 45826 | J16: 45826 | K16: 45843 | L16: 45840 | M16: PIX ITAU ALV | N16: 323.4 | O16: 323.4 | P16: B | Q16: 18 | R16: 02.01.01 | S16: Acabamento Externo | T16: DESPESAS FONECEDORES | V16: ITAU ALV | W16: Sem Origem | X16: Pagamento de Ordens de Serviço:1086, | Y16: =IF(L16="",K16,L16) -> 45840 | Z16: =TEXT(Y16,"MMMM") -> julho
A17: 1154 | B17: 1154 | C17: 2605 | D17: 1 | E17: 2T-OP310_x000D_ -1/1 | F17: 2569 | H17: DIVINO-ACABAMENTO | I17: 45817 | J17: 45817 | K17: 45843 | L17: 45840 | M17: PIX ITAU ALV | N17: 655.2 | O17: 655.2 | P17: B | Q17: 18 | R17: 02.01.01 | S17: Acabamento Externo | T17: DESPESAS FONECEDORES | V17: ITAU ALV | W17: Sem Origem | X17: Pagamento de Ordens de Serviço:1041, | Y17: =IF(L17="",K17,L17) -> 45840 | Z17: =TEXT(Y17,"MMMM") -> julho
A18: 1154 | B18: 1154 | C18: 2606 | D18: 1 | E18: 2T-OP305_x000D_ -1/1 | F18: 2569 | H18: DIVINO-ACABAMENTO | I18: 45817 | J18: 45817 | K18: 45843 | L18: 45840 | M18: PIX ITAU ALV | N18: 420 | O18: 420 | P18: B | Q18: 18 | R18: 02.01.01 | S18: Acabamento Externo | T18: DESPESAS FONECEDORES | V18: ITAU ALV | W18: Sem Origem | X18: Pagamento de Ordens de Serviço:1042, | Y18: =IF(L18="",K18,L18) -> 45840 | Z18: =TEXT(Y18,"MMMM") -> julho
A19: 1154 | B19: 1154 | C19: 2607 | D19: 1 | E19: 2T-OP309_x000D_ -1/1 | F19: 2569 | H19: DIVINO-ACABAMENTO | I19: 45817 | J19: 45817 | K19: 45843 | L19: 45840 | M19: PIX ITAU ALV | N19: 252 | O19: 252 | P19: B | Q19: 18 | R19: 02.01.01 | S19: Acabamento Externo | T19: DESPESAS FONECEDORES | V19: ITAU ALV | W19: Sem Origem | X19: Pagamento de Ordens de Serviço:1043, | Y19: =IF(L19="",K19,L19) -> 45840 | Z19: =TEXT(Y19,"MMMM") -> julho
A20: 1154 | B20: 1154 | C20: 2575 | D20: 1 | E20: 2T-OP303_x000D_ -1/1 | F20: 2569 | H20: DIVINO-ACABAMENTO | I20: 45813 | J20: 45813 | K20: 45843 | L20: 45840 | M20: PIX ITAU ALV | N20: 882 | O20: 882 | P20: B | Q20: 18 | R20: 02.01.01 | S20: Acabamento Externo | T20: DESPESAS FONECEDORES | V20: ITAU ALV | W20: Sem Origem | X20: Pagamento de Ordens de Serviço:1040, | Y20: =IF(L20="",K20,L20) -> 45840 | Z20: =TEXT(Y20,"MMMM") -> julho
A21: 1154 | B21: 1154 | C21: 2615 | D21: 1 | E21: 2T-OP299_x000D_ -1/1 | F21: 2569 | H21: DIVINO-ACABAMENTO | I21: 45819 | J21: 45819 | K21: 45843 | L21: 45840 | M21: PIX ITAU ALV | N21: 428.4 | O21: 428.4 | P21: B | Q21: 18 | R21: 02.01.01 | S21: Acabamento Externo | T21: DESPESAS FONECEDORES | V21: ITAU ALV | W21: Sem Origem | X21: Pagamento de Ordens de Serviço:1044, | Y21: =IF(L21="",K21,L21) -> 45840 | Z21: =TEXT(Y21,"MMMM") -> julho
A22: 1154 | B22: 1154 | C22: 2807 | D22: 1 | E22: 45658 | F22: 1991 | H22: DESPESAS ESCRITORIO | I22: 45840 | J22: 45840 | K22: 45840 | L22: 45840 | M22: DINHEIRO | N22: 30 | O22: 30 | P22: B | Q22: 35 | R22: 02.02.05 | S22: Combustíveis | T22: CODI.COM JEANS | V22: ITAU ALV | W22: Sem Origem | X22: MOTO | Y22: =IF(L22="",K22,L22) -> 45840 | Z22: =TEXT(Y22,"MMMM") -> julho
A23: 1154 | B23: 1154 | C23: 2809 | D23: 1 | E23: 45658 | F23: 1991 | H23: DESPESAS ESCRITORIO | I23: 45840 | J23: 45840 | K23: 45840 | L23: 45840 | M23: DINHEIRO | N23: 860 | O23: 860 | P23: B | Q23: 42 | R23: 02.02.12 | S23: Manutenção de Máquinas e Peças | T23: CODI.COM JEANS | V23: ITAU ALV | W23: Sem Origem | X23: Manutenção Máquina de Corte | Y23: =IF(L23="",K23,L23) -> 45840 | Z23: =TEXT(Y23,"MMMM") -> julho
A24: 1154 | B24: 1154 | C24: 2729 | D24: 1 | E24: 2T-OP316_x000D_ -1/1 | F24: 2569 | H24: DIVINO-ACABAMENTO | I24: 45831 | J24: 45831 | K24: 45843 | L24: 45840 | M24: PIX ITAU ALV | N24: 378 | O24: 378 | P24: B | Q24: 18 | R24: 02.01.01 | S24: Acabamento Externo | T24: DESPESAS FONECEDORES | V24: ITAU ALV | W24: Sem Origem | X24: Pagamento de Ordens de Serviço:1103, | Y24: =IF(L24="",K24,L24) -> 45840 | Z24: =TEXT(Y24,"MMMM") -> julho
A25: 1154 | B25: 1154 | C25: 2730 | D25: 1 | E25: 2T-OP292_x000D_ -1/1 | F25: 2569 | H25: DIVINO-ACABAMENTO | I25: 45831 | J25: 45831 | K25: 45843 | L25: 45840 | M25: PIX ITAU ALV | N25: 417.9 | O25: 417.9 | P25: B | Q25: 18 | R25: 02.01.01 | S25: Acabamento Externo | T25: DESPESAS FONECEDORES | V25: ITAU ALV | W25: Sem Origem | X25: Pagamento de Ordens de Serviço:1102, | Y25: =IF(L25="",K25,L25) -> 45840 | Z25: =TEXT(Y25,"MMMM") -> julho
A26: 1154 | B26: 1154 | C26: 2731 | D26: 1 | E26: 2T-OP318_x000D_ -1/1 | F26: 2569 | H26: DIVINO-ACABAMENTO | I26: 45831 | J26: 45831 | K26: 45843 | L26: 45840 | M26: PIX ITAU ALV | N26: 336 | O26: 336 | P26: B | Q26: 18 | R26: 02.01.01 | S26: Acabamento Externo | T26: DESPESAS FONECEDORES | V26: ITAU ALV | W26: Sem Origem | X26: Pagamento de Ordens de Serviço:1104, | Y26: =IF(L26="",K26,L26) -> 45840 | Z26: =TEXT(Y26,"MMMM") -> julho
A27: 1154 | B27: 1154 | C27: 2736 | D27: 1 | E27: 2T-OP288_x000D_ -1/1 | F27: 2569 | H27: DIVINO-ACABAMENTO | I27: 45831 | J27: 45831 | K27: 45843 | L27: 45840 | M27: PIX ITAU ALV | N27: 382.2 | O27: 382.2 | P27: B | Q27: 18 | R27: 02.01.01 | S27: Acabamento Externo | T27: DESPESAS FONECEDORES | V27: ITAU ALV | W27: Sem Origem | X27: Pagamento de Ordens de Serviço:1105, | Y27: =IF(L27="",K27,L27) -> 45840 | Z27: =TEXT(Y27,"MMMM") -> julho
A28: 1154 | B28: 1154 | C28: 2737 | D28: 1 | E28: 2T-OP290_x000D_ -1/1 | F28: 2569 | H28: DIVINO-ACABAMENTO | I28: 45832 | J28: 45832 | K28: 45843 | L28: 45840 | M28: PIX ITAU ALV | N28: 550.2 | O28: 550.2 | P28: B | Q28: 18 | R28: 02.01.01 | S28: Acabamento Externo | T28: DESPESAS FONECEDORES | V28: ITAU ALV | W28: Sem Origem | X28: Pagamento de Ordens de Serviço:1106, | Y28: =IF(L28="",K28,L28) -> 45840 | Z28: =TEXT(Y28,"MMMM") -> julho
A29: 1154 | B29: 1154 | C29: 2742 | D29: 1 | E29: 2T-OP328_x000D_ -1/1 | F29: 2569 | H29: DIVINO-ACABAMENTO | I29: 45832 | J29: 45832 | K29: 45843 | L29: 45840 | M29: PIX ITAU ALV | N29: 646.8 | O29: 646.8 | P29: B | Q29: 18 | R29: 02.01.01 | S29: Acabamento Externo | T29: DESPESAS FONECEDORES | V29: ITAU ALV | W29: Sem Origem | X29: Pagamento de Ordens de Serviço:1107, | Y29: =IF(L29="",K29,L29) -> 45840 | Z29: =TEXT(Y29,"MMMM") -> julho
A30: 1154 | B30: 1154 | C30: 2761 | D30: 1 | E30: 2T-OP325_x000D_ -1/1 | F30: 2569 | H30: DIVINO-ACABAMENTO | I30: 45833 | J30: 45833 | K30: 45843 | L30: 45840 | M30: PIX ITAU ALV | N30: 525 | O30: 525 | P30: B | Q30: 18 | R30: 02.01.01 | S30: Acabamento Externo | T30: DESPESAS FONECEDORES | V30: ITAU ALV | W30: Sem Origem | X30: Pagamento de Ordens de Serviço:1117, | Y30: =IF(L30="",K30,L30) -> 45840 | Z30: =TEXT(Y30,"MMMM") -> julho
A31: 1154 | B31: 1154 | C31: 2769 | D31: 1 | E31: 2T-OP280_x000D_ -1/1 | F31: 2569 | H31: DIVINO-ACABAMENTO | I31: 45835 | J31: 45835 | K31: 45843 | L31: 45840 | M31: PIX ITAU ALV | N31: 478.8 | O31: 478.8 | P31: B | Q31: 18 | R31: 02.01.01 | S31: Acabamento Externo | T31: DESPESAS FONECEDORES | V31: ITAU ALV | W31: Sem Origem | X31: Pagamento de Ordens de Serviço:1118, | Y31: =IF(L31="",K31,L31) -> 45840 | Z31: =TEXT(Y31,"MMMM") -> julho
A32: 1154 | B32: 1154 | C32: 2771 | D32: 1 | E32: 2T-OP269_x000D_ -1/1 | F32: 2569 | H32: DIVINO-ACABAMENTO | I32: 45835 | J32: 45835 | K32: 45845 | L32: 45840 | M32: PIX ITAU ALV | N32: 762.3 | O32: 762.3 | P32: B | Q32: 18 | R32: 02.01.01 | S32: Acabamento Externo | T32: DESPESAS FONECEDORES | V32: ITAU ALV | W32: Sem Origem | Y32: =IF(L32="",K32,L32) -> 45840 | Z32: =TEXT(Y32,"MMMM") -> julho
A33: 1154 | B33: 1154 | C33: 2778 | D33: 1 | E33: 2T-OP333_x000D_ -1/1 | F33: 2569 | H33: DIVINO-ACABAMENTO | I33: 45839 | J33: 45839 | K33: 45843 | L33: 45840 | M33: PIX ITAU ALV | N33: 386.4 | O33: 386.4 | P33: B | Q33: 18 | R33: 02.01.01 | S33: Acabamento Externo | T33: DESPESAS FONECEDORES | V33: ITAU ALV | W33: Sem Origem | X33: Pagamento de Ordens de Serviço:1119, | Y33: =IF(L33="",K33,L33) -> 45840 | Z33: =TEXT(Y33,"MMMM") -> julho
A34: 1154 | B34: 1154 | C34: 2748 | D34: 1 | E34: 2T-OP338_x000D_ -1/1 | F34: 2142 | H34: ADRIANO-FACÇÃO | I34: 45832 | J34: 45832 | K34: 45845 | L34: 45841 | M34: PIX ITAU ALV | N34: 6440 | O34: 6440 | P34: B | Q34: 21 | R34: 02.01.04 | S34: Facção | T34: DESPESAS FONECEDORES | V34: ITAU ALV | W34: Sem Origem | X34: Pagamento de Ordens de Serviço:1108, | Y34: =IF(L34="",K34,L34) -> 45841 | Z34: =TEXT(Y34,"MMMM") -> julho
A35: 1154 | B35: 1154 | C35: 2842 | D35: 1 | E35: 45658 | F35: 1991 | H35: DESPESAS ESCRITORIO | I35: 45841 | J35: 45841 | K35: 45841 | L35: 45841 | M35: CARTÃO DÉBITO | N35: 20.18 | O35: 20.18 | P35: B | Q35: 72 | R35: 02.03.03 | S35: Alimentação | T35: CODI.COM JEANS | V35: ITAU ALV | W35: Sem Origem | X35: Pão dia 01/07 | Y35: =IF(L35="",K35,L35) -> 45841 | Z35: =TEXT(Y35,"MMMM") -> julho
A36: 1154 | B36: 1154 | C36: 2843 | D36: 1 | E36: 45658 | F36: 1991 | H36: DESPESAS ESCRITORIO | I36: 45841 | J36: 45841 | K36: 45841 | L36: 45841 | M36: CARTÃO DÉBITO | N36: 45.99 | O36: 45.99 | P36: B | Q36: 29 | R36: 02.01.12 | S36: Outros Insumos | T36: CODI.COM JEANS | V36: ITAU ALV | W36: Sem Origem | X36: Despesas repassadas Lourival | Y36: =IF(L36="",K36,L36) -> 45841 | Z36: =TEXT(Y36,"MMMM") -> julho
A37: 1154 | B37: 1154 | C37: 2844 | D37: 1 | E37: 45658 | F37: 1991 | H37: DESPESAS ESCRITORIO | I37: 45841 | J37: 45841 | K37: 45841 | L37: 45841 | M37: DINHEIRO | N37: 28 | O37: 28 | P37: B | Q37: 54 | R37: 02.02.24 | S37: Manutenção de Veiculos e Estacionamento | T37: CODI.COM JEANS | V37: ITAU ALV | W37: Sem Origem | X37: Troca de Óleo Moto | Y37: =IF(L37="",K37,L37) -> 45841 | Z37: =TEXT(Y37,"MMMM") -> julho
A38: 1154 | B38: 1154 | C38: 2845 | D38: 1 | E38: 45658 | F38: 1991 | H38: DESPESAS ESCRITORIO | I38: 45841 | J38: 45841 | K38: 45841 | L38: 45841 | M38: CARTÃO DÉBITO | N38: 238.59 | O38: 238.59 | P38: B | Q38: 35 | R38: 02.02.05 | S38: Combustíveis | T38: CODI.COM JEANS | V38: ITAU ALV | W38: Sem Origem | X38: Combustível Carro | Y38: =IF(L38="",K38,L38) -> 45841 | Z38: =TEXT(Y38,"MMMM") -> julho
A39: 1154 | B39: 1154 | C39: 2846 | D39: 1 | E39: 45658 | F39: 1991 | H39: DESPESAS ESCRITORIO | I39: 45841 | J39: 45841 | K39: 45841 | L39: 45841 | M39: CARTÃO DÉBITO | N39: 155.86 | O39: 155.86 | P39: B | Q39: 35 | R39: 02.02.05 | S39: Combustíveis | T39: CODI.COM JEANS | V39: ITAU ALV | W39: Sem Origem | X39: Combustível Carro | Y39: =IF(L39="",K39,L39) -> 45841 | Z39: =TEXT(Y39,"MMMM") -> julho
A40: 1154 | B40: 1154 | C40: 2847 | D40: 1 | E40: 45658 | F40: 1991 | H40: DESPESAS ESCRITORIO | I40: 45841 | J40: 45841 | K40: 45841 | L40: 45841 | M40: CARTÃO DÉBITO | N40: 42.8 | O40: 42.8 | P40: B | Q40: 29 | R40: 02.01.12 | S40: Outros Insumos | T40: CODI.COM JEANS | V40: ITAU ALV | W40: Sem Origem | Y40: =IF(L40="",K40,L40) -> 45841 | Z40: =TEXT(Y40,"MMMM") -> julho
A41: 1154 | B41: 1154 | C41: 2572 | D41: 1 | E41: 2T-OP283_x000D_ -1/1 | F41: 1957 | H41: ROGERIO - TRAVETE | I41: 45813 | J41: 45813 | K41: 45845 | L41: 45841 | M41: PIX ITAU ALV | N41: 210 | O41: 210 | P41: B | Q41: 27 | R41: 02.01.10 | S41: Travete | T41: DESPESAS FONECEDORES | V41: ITAU ALV | W41: Sem Origem | Y41: =IF(L41="",K41,L41) -> 45841 | Z41: =TEXT(Y41,"MMMM") -> julho
A42: 1154 | B42: 1154 | C42: 2695 | D42: 1 | E42: 2T-OP332_x000D_ -1/1 | F42: 1957 | H42: ROGERIO - TRAVETE | I42: 45825 | J42: 45825 | K42: 45843 | L42: 45841 | M42: PIX ITAU ALV | N42: 154 | O42: 154 | P42: B | Q42: 27 | R42: 02.01.10 | S42: Travete | T42: DESPESAS FONECEDORES | V42: ITAU ALV | W42: Sem Origem | X42: Pagamento de Ordens de Serviço:1081, | Y42: =IF(L42="",K42,L42) -> 45841 | Z42: =TEXT(Y42,"MMMM") -> julho
A43: 1154 | B43: 1154 | C43: 2692 | D43: 1 | E43: 2T-OP331_x000D_ -1/1 | F43: 1957 | H43: ROGERIO - TRAVETE | I43: 45825 | J43: 45825 | K43: 45843 | L43: 45841 | M43: PIX ITAU ALV | N43: 180 | O43: 180 | P43: B | Q43: 27 | R43: 02.01.10 | S43: Travete | T43: DESPESAS FONECEDORES | V43: ITAU ALV | W43: Sem Origem | X43: Pagamento de Ordens de Serviço:1078, | Y43: =IF(L43="",K43,L43) -> 45841 | Z43: =TEXT(Y43,"MMMM") -> julho
A44: 1154 | B44: 1154 | C44: 2520 | D44: 1 | E44: 2T-OP306_x000D_ -1/1 | F44: 1957 | H44: ROGERIO - TRAVETE | I44: 45810 | J44: 45810 | K44: 45843 | L44: 45841 | M44: PIX ITAU ALV | N44: 275 | O44: 275 | P44: B | Q44: 27 | R44: 02.01.10 | S44: Travete | T44: DESPESAS FONECEDORES | V44: ITAU ALV | W44: Sem Origem | X44: Pagamento de Ordens de Serviço:1004, | Y44: =IF(L44="",K44,L44) -> 45841 | Z44: =TEXT(Y44,"MMMM") -> julho
A45: 1154 | B45: 1154 | C45: 1966 | D45: 1 | E45: 002883-2/_x000D_ 3 | F45: 1958 | H45: ROMERONDES - LAVANDERIA | I45: 45757 | J45: 45757 | K45: 45838 | L45: 45841 | M45: CHEQUE - EMPRESA | N45: 2000 | O45: 2000 | P45: B | Q45: 28 | R45: 02.01.11 | S45: Lavanderia | T45: DESPESAS FONECEDORES | V45: ITAU ALV | W45: Sem Origem | Y45: =IF(L45="",K45,L45) -> 45841 | Z45: =TEXT(Y45,"MMMM") -> julho
A46: 1154 | B46: 1154 | C46: 1954 | D46: 1 | E46: 002939-2/_x000D_ 2 | F46: 2501 | G46: 6177741000129 | H46: LAVANDERIA AMAZONAS - LEONARDO | I46: 45757 | J46: 45757 | K46: 45838 | L46: 45841 | M46: CHEQUE - EMPRESA | N46: 1070 | O46: 1070 | P46: B | Q46: 28 | R46: 02.01.11 | S46: Lavanderia | T46: DESPESAS FONECEDORES | V46: ITAU ALV | W46: Sem Origem | X46: (Parte em cheque de Clientes 25/05/2025) | Y46: =IF(L46="",K46,L46) -> 45841 | Z46: =TEXT(Y46,"MMMM") -> julho
A47: 1154 | B47: 1154 | C47: 2806 | D47: 1 | E47: 45839 | F47: 2030 | H47: DIOGO MODELAGEM | I47: 45840 | J47: 45840 | K47: 45842 | L47: 45842 | M47: PIX ITAU ALV | N47: 6320 | O47: 6320 | P47: B | Q47: 56 | R47: 02.02.26 | S47: Criação de Modelos | T47: CODI.COM JEANS | V47: ITAU ALV | W47: Sem Origem | Y47: =IF(L47="",K47,L47) -> 45842 | Z47: =TEXT(Y47,"MMMM") -> julho
A48: 1154 | B48: 1154 | C48: 2852 | D48: 1 | E48: 45658 | F48: 1991 | H48: DESPESAS ESCRITORIO | I48: 45842 | J48: 45841 | K48: 45841 | L48: 45842 | M48: DINHEIRO | N48: 30.6 | O48: 30.6 | P48: B | Q48: 29 | R48: 02.01.12 | S48: Outros Insumos | T48: CODI.COM JEANS | V48: ITAU ALV | W48: Sem Origem | X48: Pedágio Jaraguá | Y48: =IF(L48="",K48,L48) -> 45842 | Z48: =TEXT(Y48,"MMMM") -> julho
A49: 1154 | B49: 1154 | C49: 2853 | D49: 1 | E49: 45658 | F49: 1991 | H49: DESPESAS ESCRITORIO | I49: 45842 | J49: 45842 | K49: 45842 | L49: 45842 | M49: CARTÃO DÉBITO | N49: 15.3 | O49: 15.3 | P49: B | Q49: 29 | R49: 02.01.12 | S49: Outros Insumos | T49: CODI.COM JEANS | V49: ITAU ALV | W49: Sem Origem | X49: Pedágio Jaraguá | Y49: =IF(L49="",K49,L49) -> 45842 | Z49: =TEXT(Y49,"MMMM") -> julho
A50: 1154 | B50: 1154 | C50: 2854 | D50: 1 | E50: 45658 | F50: 1991 | H50: DESPESAS ESCRITORIO | I50: 45842 | J50: 45842 | K50: 45842 | L50: 45842 | M50: PIX ITAU ALV | N50: 675.95 | O50: 675.95 | P50: B | Q50: 99 | R50: 02.05.01 | S50: Compra de Computadores e Eletrônicos | T50: CODI.COM JEANS | V50: ITAU ALV | W50: Sem Origem | X50: Computador Empresa | Y50: =IF(L50="",K50,L50) -> 45842 | Z50: =TEXT(Y50,"MMMM") -> julho
A51: 1154 | B51: 1154 | C51: 2753 | D51: 1 | E51: 2T-OP339_x000D_ -1/1 | F51: 2267 | H51: AURELIO-FACÇÃO | I51: 45832 | J51: 45832 | K51: 45845 | L51: 45842 | M51: PIX ITAU ALV | N51: 5733 | O51: 5733 | P51: B | Q51: 21 | R51: 02.01.04 | S51: Facção | T51: DESPESAS FONECEDORES | V51: ITAU ALV | W51: Sem Origem | X51: Pagamento de Ordens de Serviço:1111, | Y51: =IF(L51="",K51,L51) -> 45842 | Z51: =TEXT(Y51,"MMMM") -> julho
A52: 1154 | B52: 1154 | C52: 2876 | D52: 1 | E52: 45658 | F52: 1991 | H52: DESPESAS ESCRITORIO | I52: 45845 | J52: 45845 | K52: 45845 | L52: 45845 | M52: PIX ITAU ALV | N52: 30 | O52: 30 | P52: B | Q52: 75 | R52: 02.03.06 | S52: Exame Adminissional/Demissional | T52: CODI.COM JEANS | V52: ITAU ALV | W52: Sem Origem | X52: EXAME ADMISSIONAL DOUGLAS | Y52: =IF(L52="",K52,L52) -> 45845 | Z52: =TEXT(Y52,"MMMM") -> julho
A53: 1154 | B53: 1154 | C53: 2877 | D53: 1 | E53: 45658 | F53: 2356 | H53: AJUDA DE CUSTO - SEMANA | I53: 45845 | J53: 45845 | K53: 45845 | L53: 45845 | M53: PIX ITAU ALV | N53: 820 | O53: 820 | P53: B | Q53: 87 | R53: 02.03.17 | S53: Vale Transporte | T53: CODI.COM JEANS | V53: ITAU ALV | W53: Sem Origem | X53: Ajuda de custo dias 07/07 até 11/07 | Y53: =IF(L53="",K53,L53) -> 45845 | Z53: =TEXT(Y53,"MMMM") -> julho
A54: 1154 | B54: 1154 | C54: 2878 | D54: 1 | E54: 45658 | F54: 1991 | H54: DESPESAS ESCRITORIO | I54: 45845 | J54: 45845 | K54: 45845 | L54: 45845 | M54: CARTÃO DÉBITO | N54: 25.63 | O54: 25.63 | P54: B | Q54: 35 | R54: 02.02.05 | S54: Combustíveis | T54: CODI.COM JEANS | V54: ITAU ALV | W54: Sem Origem | X54: Combustível Carro | Y54: =IF(L54="",K54,L54) -> 45845 | Z54: =TEXT(Y54,"MMMM") -> julho
A55: 1154 | B55: 1154 | C55: 2879 | D55: 1 | E55: 45658 | F55: 1991 | H55: DESPESAS ESCRITORIO | I55: 45845 | J55: 45845 | K55: 45845 | L55: 45845 | M55: CARTÃO DÉBITO | N55: 46.1 | O55: 46.1 | P55: B | Q55: 72 | R55: 02.03.03 | S55: Alimentação | T55: CODI.COM JEANS | V55: ITAU ALV | W55: Sem Origem | X55: Pão dias 03/07 até 05/07 | Y55: =IF(L55="",K55,L55) -> 45845 | Z55: =TEXT(Y55,"MMMM") -> julho
A56: 1154 | B56: 1154 | C56: 2880 | D56: 1 | E56: 45658 | F56: 1991 | H56: DESPESAS ESCRITORIO | I56: 45845 | J56: 45845 | K56: 45845 | L56: 45845 | M56: CARTÃO DÉBITO | N56: 211.68 | O56: 211.68 | P56: B | Q56: 35 | R56: 02.02.05 | S56: Combustíveis | T56: CODI.COM JEANS | V56: ITAU ALV | W56: Sem Origem | X56: Combustível carro | Y56: =IF(L56="",K56,L56) -> 45845 | Z56: =TEXT(Y56,"MMMM") -> julho
A57: 1154 | B57: 1154 | C57: 1999 | D57: 4 | E57: 45781 | F57: 2512 | H57: HEITOR FORRO DE BOLSO TACTEL | I57: 45761 | J57: 45761 | K57: 45845 | L57: 45845 | M57: BOLETO BANCÁRIO | N57: 2370 | O57: 2370 | P57: B | Q57: 23 | R57: 02.01.06 | S57: Aviamento | T57: DESPESAS FONECEDORES | V57: ITAU ALV | W57: Sem Origem | X57: Forro De Bolso | Y57: =IF(L57="",K57,L57) -> 45845 | Z57: =TEXT(Y57,"MMMM") -> julho
A58: 1154 | B58: 1154 | C58: 2201 | D58: 1 | E58: 2T-OP272_x000D_ -1/1 | F58: 1957 | H58: ROGERIO - TRAVETE | I58: 45782 | J58: 45782 | K58: 45843 | L58: 45845 | M58: PIX ITAU ALV | N58: 119 | O58: 119 | P58: B | Q58: 27 | R58: 02.01.10 | S58: Travete | T58: DESPESAS FONECEDORES | V58: ITAU ALV | W58: Sem Origem | X58: Pagamento de Ordens de Serviço:898, | Y58: =IF(L58="",K58,L58) -> 45845 | Z58: =TEXT(Y58,"MMMM") -> julho
A59: 1154 | B59: 1154 | C59: 2230 | D59: 2 | E59: 0724947-2_x000D_ /7 | F59: 1526 | G59: 07.332.190/0007-89 | H59: VICUNHA TEXTIL S/A. | I59: 45783 | J59: 45783 | K59: 45845 | L59: 45845 | M59: BOLETO BANCÁRIO | N59: 806.4 | O59: 806.4 | P59: B | Q59: 26 | R59: 02.01.09 | S59: Tecidos | T59: DESPESAS FONECEDORES | V59: ITAU ALV | W59: Sem Origem | X59: Tecido - Bardot Plus | Y59: =IF(L59="",K59,L59) -> 45845 | Z59: =TEXT(Y59,"MMMM") -> julho
A60: 1154 | B60: 1154 | C60: 2288 | D60: 1 | E60: 2T-OP280_x000D_ -1/1 | F60: 1957 | H60: ROGERIO - TRAVETE | I60: 45786 | J60: 45786 | K60: 45843 | L60: 45845 | M60: PIX ITAU ALV | N60: 228 | O60: 228 | P60: B | Q60: 27 | R60: 02.01.10 | S60: Travete | T60: DESPESAS FONECEDORES | V60: ITAU ALV | W60: Sem Origem | X60: Pagamento de Ordens de Serviço:920, | Y60: =IF(L60="",K60,L60) -> 45845 | Z60: =TEXT(Y60,"MMMM") -> julho
A61: 1154 | B61: 1154 | C61: 2334 | D61: 1 | E61: 2T-OP286_x000D_ -1/1 | F61: 1957 | H61: ROGERIO - TRAVETE | I61: 45791 | J61: 45791 | K61: 45843 | L61: 45845 | M61: PIX ITAU ALV | N61: 156 | O61: 156 | P61: B | Q61: 27 | R61: 02.01.10 | S61: Travete | T61: DESPESAS FONECEDORES | V61: ITAU ALV | W61: Sem Origem | X61: Pagamento de Ordens de Serviço:938, | Y61: =IF(L61="",K61,L61) -> 45845 | Z61: =TEXT(Y61,"MMMM") -> julho
A62: 1154 | B62: 1154 | C62: 2324 | D62: 1 | E62: 2T-OP284_x000D_ -1/1 | F62: 1957 | H62: ROGERIO - TRAVETE | I62: 45791 | J62: 45791 | K62: 45843 | L62: 45845 | M62: PIX ITAU ALV | N62: 204 | O62: 204 | P62: B | Q62: 27 | R62: 02.01.10 | S62: Travete | T62: DESPESAS FONECEDORES | V62: ITAU ALV | W62: Sem Origem | X62: Pagamento de Ordens de Serviço:933, | Y62: =IF(L62="",K62,L62) -> 45845 | Z62: =TEXT(Y62,"MMMM") -> julho
A63: 1154 | B63: 1154 | C63: 2406 | D63: 1 | E63: 2T-OP294_x000D_ -1/1 | F63: 1957 | H63: ROGERIO - TRAVETE | I63: 45797 | J63: 45797 | K63: 45843 | L63: 45845 | M63: PIX ITAU ALV | N63: 169 | O63: 169 | P63: B | Q63: 27 | R63: 02.01.10 | S63: Travete | T63: DESPESAS FONECEDORES | V63: ITAU ALV | W63: Sem Origem | X63: Pagamento de Ordens de Serviço:966, | Y63: =IF(L63="",K63,L63) -> 45845 | Z63: =TEXT(Y63,"MMMM") -> julho
A64: 1154 | B64: 1154 | C64: 2516 | D64: 1 | E64: 2T-OP304_x000D_ -1/1 | F64: 1957 | H64: ROGERIO - TRAVETE | I64: 45810 | J64: 45810 | K64: 45843 | L64: 45845 | M64: PIX ITAU ALV | N64: 266 | O64: 266 | P64: B | Q64: 27 | R64: 02.01.10 | S64: Travete | T64: DESPESAS FONECEDORES | V64: ITAU ALV | W64: Sem Origem | X64: Pagamento de Ordens de Serviço:1000, | Y64: =IF(L64="",K64,L64) -> 45845 | Z64: =TEXT(Y64,"MMMM") -> julho
A65: 1154 | B65: 1154 | C65: 2517 | D65: 1 | E65: 2T-OP305_x000D_ -1/1 | F65: 1957 | H65: ROGERIO - TRAVETE | I65: 45810 | J65: 45810 | K65: 45843 | L65: 45845 | M65: PIX ITAU ALV | N65: 200 | O65: 200 | P65: B | Q65: 27 | R65: 02.01.10 | S65: Travete | T65: DESPESAS FONECEDORES | V65: ITAU ALV | W65: Sem Origem | X65: Pagamento de Ordens de Serviço:1002, | Y65: =IF(L65="",K65,L65) -> 45845 | Z65: =TEXT(Y65,"MMMM") -> julho
A66: 1154 | B66: 1154 | C66: 2537 | D66: 1 | E66: 2T-OP310_x000D_ -1/1 | F66: 1957 | H66: ROGERIO - TRAVETE | I66: 45811 | J66: 45811 | K66: 45843 | L66: 45845 | M66: PIX ITAU ALV | N66: 312 | O66: 312 | P66: B | Q66: 27 | R66: 02.01.10 | S66: Travete | T66: DESPESAS FONECEDORES | V66: ITAU ALV | W66: Sem Origem | X66: Pagamento de Ordens de Serviço:1016, | Y66: =IF(L66="",K66,L66) -> 45845 | Z66: =TEXT(Y66,"MMMM") -> julho
A67: 1154 | B67: 1154 | C67: 2540 | D67: 1 | E67: 2T-OP311_x000D_ -1/1 | F67: 1957 | H67: ROGERIO - TRAVETE | I67: 45811 | J67: 45811 | K67: 45843 | L67: 45845 | M67: PIX ITAU ALV | N67: 120 | O67: 120 | P67: B | Q67: 27 | R67: 02.01.10 | S67: Travete | T67: DESPESAS FONECEDORES | V67: ITAU ALV | W67: Sem Origem | X67: Pagamento de Ordens de Serviço:1019, | Y67: =IF(L67="",K67,L67) -> 45845 | Z67: =TEXT(Y67,"MMMM") -> julho
A68: 1154 | B68: 1154 | C68: 2553 | D68: 1 | E68: 2T-OP316_x000D_ -1/1 | F68: 1957 | H68: ROGERIO - TRAVETE | I68: 45811 | J68: 45811 | K68: 45843 | L68: 45845 | M68: PIX ITAU ALV | N68: 180 | O68: 180 | P68: B | Q68: 18 | R68: 02.01.01 | S68: Acabamento Externo | T68: DESPESAS FONECEDORES | V68: ITAU ALV | W68: Sem Origem | X68: Pagamento de Ordens de Serviço:1028, | Y68: =IF(L68="",K68,L68) -> 45845 | Z68: =TEXT(Y68,"MMMM") -> julho
A69: 1154 | B69: 1154 | C69: 2556 | D69: 1 | E69: 2T-OP317_x000D_ -1/1 | F69: 1957 | H69: ROGERIO - TRAVETE | I69: 45811 | J69: 45811 | K69: 45843 | L69: 45845 | M69: PIX ITAU ALV | N69: 100 | O69: 100 | P69: B | Q69: 27 | R69: 02.01.10 | S69: Travete | T69: DESPESAS FONECEDORES | V69: ITAU ALV | W69: Sem Origem | X69: Pagamento de Ordens de Serviço:1031, | Y69: =IF(L69="",K69,L69) -> 45845 | Z69: =TEXT(Y69,"MMMM") -> julho
A70: 1154 | B70: 1154 | C70: 2451 | D70: 1 | E70: 2T-OP297_x000D_ -1/1 | F70: 1957 | H70: ROGERIO - TRAVETE | I70: 45803 | J70: 45803 | K70: 45843 | L70: 45845 | M70: PIX ITAU ALV | N70: 242 | O70: 242 | P70: B | Q70: 27 | R70: 02.01.10 | S70: Travete | T70: DESPESAS FONECEDORES | V70: ITAU ALV | W70: Sem Origem | X70: Pagamento de Ordens de Serviço:975, | Y70: =IF(L70="",K70,L70) -> 45845 | Z70: =TEXT(Y70,"MMMM") -> julho
A71: 1154 | B71: 1154 | C71: 2468 | D71: 1 | E71: 2T-OP300_x000D_ -1/1 | F71: 1957 | H71: ROGERIO - TRAVETE | I71: 45804 | J71: 45804 | K71: 45843 | L71: 45845 | M71: PIX ITAU ALV | N71: 390 | O71: 390 | P71: B | Q71: 27 | R71: 02.01.10 | S71: Travete | T71: DESPESAS FONECEDORES | V71: ITAU ALV | W71: Sem Origem | X71: Pagamento de Ordens de Serviço:984, | Y71: =IF(L71="",K71,L71) -> 45845 | Z71: =TEXT(Y71,"MMMM") -> julho
... A79: 1154 | B79: 1154 | C79: 2666 | D79: 1 | E79: 2T-OP327_x000D_ -1/1 | F79: 1957 | H79: ROGERIO - TRAVETE | I79: 45825 | J79: 45825 | K79: 45843 | L79: 45845 | M79: PIX ITAU ALV | N79: 408 | O79: 408 | P79: B | Q79: 27 | R79: 02.01.10 | S79: Travete | T79: DESPESAS FONECEDORES | V79: ITAU ALV | W79: Sem Origem | X79: Pagamento de Ordens de Serviço:1066, | Y79: =IF(L79="",K79,L79) -> 45845 | Z79: =TEXT(Y79,"MMMM") -> julho
A80: 1154 | B80: 1154 | C80: 2573 | D80: 1 | E80: 2T-OP268_x000D_ -1/1 | F80: 1957 | H80: ROGERIO - TRAVETE | I80: 45813 | J80: 45813 | K80: 45845 | L80: 45845 | M80: PIX ITAU ALV | N80: 187 | O80: 187 | P80: B | Q80: 27 | R80: 02.01.10 | S80: Travete | T80: DESPESAS FONECEDORES | V80: ITAU ALV | W80: Sem Origem | Y80: =IF(L80="",K80,L80) -> 45845 | Z80: =TEXT(Y80,"MMMM") -> julho
A81: 1154 | B81: 1154 | C81: 2600 | D81: 1 | E81: 45658 | F81: 2635 | G81: 02.384.871/0001-81 | H81: EXCIM IMPORTAÇÃO E EXPORTAÇÃO LTDA | I81: 45817 | J81: 45817 | K81: 45844 | L81: 45845 | M81: BOLETO BANCÁRIO | N81: 257.82 | O81: 257.82 | P81: B | Q81: 26 | R81: 02.01.09 | S81: Tecidos | T81: DESPESAS FONECEDORES | V81: ITAU ALV | W81: Sem Origem | Y81: =IF(L81="",K81,L81) -> 45845 | Z81: =TEXT(Y81,"MMMM") -> julho
A82: 1154 | B82: 1154 | C82: 1758 | D82: 2 | E82: 00040067_x000D_ 0-2/5 | F82: 1976 | G82: 61.520.607/0018-35 | H82: SANTISTA TEXTIL | I82: 45740 | J82: 45734 | K82: 45846 | L82: 45846 | M82: BOLETO BANCÁRIO | N82: 17010.76 | O82: 17010.76 | P82: B | Q82: 26 | R82: 02.01.09 | S82: Tecidos | T82: DESPESAS FONECEDORES | V82: ITAU ALV | W82: Sem Origem | X82: 2T Tecido | Y82: =IF(L82="",K82,L82) -> 45846 | Z82: =TEXT(Y82,"MMMM") -> julho
A83: 1154 | B83: 1154 | C83: 2900 | D83: 1 | E83: 45658 | F83: 2071 | H83: DANIEL ENNOS | I83: 45846 | J83: 45846 | K83: 45842 | L83: 45846 | M83: PIX ITAU ALV | N83: 660 | O83: 660 | P83: B | Q83: 53 | R83: 02.02.23 | S83: Publicidade | T83: CODI.COM JEANS | V83: ITAU ALV | W83: Sem Origem | X83: 22 Vídeos | Y83: =IF(L83="",K83,L83) -> 45846 | Z83: =TEXT(Y83,"MMMM") -> julho
A84: 1154 | B84: 1154 | C84: 2901 | D84: 1 | E84: 45658 | F84: 2511 | H84: PILOTOS (CRIAÇÂO DE PEÇAS) | I84: 45846 | J84: 45846 | K84: 45842 | L84: 45846 | M84: PIX ITAU ALV | N84: 1650 | O84: 1650 | P84: B | Q84: 56 | R84: 02.02.26 | S84: Criação de Modelos | T84: CODI.COM JEANS | V84: ITAU ALV | W84: Sem Origem | Y84: =IF(L84="",K84,L84) -> 45846 | Z84: =TEXT(Y84,"MMMM") -> julho
A85: 1154 | B85: 1154 | C85: 2902 | D85: 1 | E85: 45658 | F85: 2119 | H85: JEFFERSON MODELO | I85: 45846 | J85: 45846 | K85: 45842 | L85: 45846 | M85: PIX ITAU ALV | N85: 1320 | O85: 1320 | P85: B | Q85: 53 | R85: 02.02.23 | S85: Publicidade | T85: CODI.COM JEANS | V85: ITAU ALV | W85: Sem Origem | Y85: =IF(L85="",K85,L85) -> 45846 | Z85: =TEXT(Y85,"MMMM") -> julho
A86: 1154 | B86: 1154 | C86: 2903 | D86: 1 | E86: 45658 | F86: 2118 | H86: PAULO FOTÓGRAFO | I86: 45846 | J86: 45846 | K86: 45842 | L86: 45846 | M86: PIX ITAU ALV | N86: 1250 | O86: 1250 | P86: B | Q86: 53 | R86: 02.02.23 | S86: Publicidade | T86: CODI.COM JEANS | V86: ITAU ALV | W86: Sem Origem | Y86: =IF(L86="",K86,L86) -> 45846 | Z86: =TEXT(Y86,"MMMM") -> julho
A87: 1154 | B87: 1154 | C87: 1424 | D87: 4 | E87: 45904 | F87: 2071 | H87: DANIEL ENNOS | I87: 45695 | J87: 45695 | K87: 45844 | L87: 45846 | M87: PIX ITAU ALV | N87: 4500 | O87: 4500 | P87: B | Q87: 83 | R87: 02.03.13 | S87: Salário e Ordenados | T87: DESPESA COLABORADORES | V87: ITAU ALV | W87: Sem Origem | Y87: =IF(L87="",K87,L87) -> 45846 | Z87: =TEXT(Y87,"MMMM") -> julho
A88: 1154 | B88: 1154 | C88: 2885 | D88: 1 | E88: 45658 | F88: 2374 | H88: CRISLANDIA ESTOQUE FABRICA | I88: 45846 | J88: 45846 | K88: 45842 | L88: 45846 | M88: PIX ITAU ALV | N88: 1255.44 | O88: 1255.44 | P88: B | Q88: 83 | R88: 02.03.13 | S88: Salário e Ordenados | T88: DESPESA COLABORADORES | V88: ITAU ALV | W88: Sem Origem | Y88: =IF(L88="",K88,L88) -> 45846 | Z88: =TEXT(Y88,"MMMM") -> julho
A89: 1154 | B89: 1154 | C89: 2886 | D89: 1 | E89: 45658 | F89: 2064 | H89: WENDER WALLAN | I89: 45846 | J89: 45846 | K89: 45842 | L89: 45846 | M89: PIX ITAU ALV | N89: 2883.88 | O89: 2883.88 | P89: B | Q89: 83 | R89: 02.03.13 | S89: Salário e Ordenados | T89: DESPESA COLABORADORES | V89: ITAU ALV | W89: Sem Origem | Y89: =IF(L89="",K89,L89) -> 45846 | Z89: =TEXT(Y89,"MMMM") -> julho
A90: 1154 | B90: 1154 | C90: 2887 | D90: 1 | E90: 45658 | F90: 2063 | H90: DELVA GERENTE DO ESTOQUE | I90: 45846 | J90: 45846 | K90: 45842 | L90: 45846 | M90: PIX ITAU ALV | N90: 2000 | O90: 2000 | P90: B | Q90: 83 | R90: 02.03.13 | S90: Salário e Ordenados | T90: DESPESA COLABORADORES | V90: ITAU ALV | W90: Sem Origem | Y90: =IF(L90="",K90,L90) -> 45846 | Z90: =TEXT(Y90,"MMMM") -> julho
A91: 1154 | B91: 1154 | C91: 2888 | D91: 1 | E91: 45658 | F91: 2060 | H91: AILTON CORTADOR | I91: 45846 | J91: 45846 | K91: 45842 | L91: 45846 | M91: PIX ITAU ALV | N91: 2276.22 | O91: 2276.22 | P91: B | Q91: 83 | R91: 02.03.13 | S91: Salário e Ordenados | T91: DESPESA COLABORADORES | V91: ITAU ALV | W91: Sem Origem | Y91: =IF(L91="",K91,L91) -> 45846 | Z91: =TEXT(Y91,"MMMM") -> julho
A92: 1154 | B92: 1154 | C92: 2889 | D92: 1 | E92: 45658 | F92: 2371 | H92: JHULLYA VENDAS LOJA | I92: 45846 | J92: 45846 | K92: 45842 | L92: 45846 | M92: PIX ITAU ALV | N92: 1103.29 | O92: 1103.29 | P92: B | Q92: 83 | R92: 02.03.13 | S92: Salário e Ordenados | T92: DESPESA COLABORADORES | V92: ITAU ALV | W92: Sem Origem | Y92: =IF(L92="",K92,L92) -> 45846 | Z92: =TEXT(Y92,"MMMM") -> julho
A93: 1154 | B93: 1154 | C93: 2890 | D93: 1 | E93: 45658 | F93: 2112 | H93: MARIA EDUARDA VENDAS FÁBRICA | I93: 45846 | J93: 45846 | K93: 45842 | L93: 45846 | M93: PIX ITAU ALV | N93: 1218 | O93: 1218 | P93: B | Q93: 83 | R93: 02.03.13 | S93: Salário e Ordenados | T93: DESPESA COLABORADORES | V93: ITAU ALV | W93: Sem Origem | Y93: =IF(L93="",K93,L93) -> 45846 | Z93: =TEXT(Y93,"MMMM") -> julho
A94: 1154 | B94: 1154 | C94: 2891 | D94: 1 | E94: 45658 | F94: 2120 | H94: GABY VENDAS LOJA | I94: 45846 | J94: 45846 | K94: 45842 | L94: 45846 | M94: PIX ITAU ALV | N94: 1118 | O94: 1118 | P94: B | Q94: 83 | R94: 02.03.13 | S94: Salário e Ordenados | T94: DESPESA COLABORADORES | V94: ITAU ALV | W94: Sem Origem | Y94: =IF(L94="",K94,L94) -> 45846 | Z94: =TEXT(Y94,"MMMM") -> julho
A95: 1154 | B95: 1154 | C95: 2892 | D95: 1 | E95: 45658 | F95: 2180 | H95: ADRIANA VENDAS FÁBRICA | I95: 45846 | J95: 45846 | K95: 45842 | L95: 45846 | M95: PIX ITAU ALV | N95: 1318 | O95: 1318 | P95: B | Q95: 83 | R95: 02.03.13 | S95: Salário e Ordenados | T95: DESPESA COLABORADORES | V95: ITAU ALV | W95: Sem Origem | Y95: =IF(L95="",K95,L95) -> 45846 | Z95: =TEXT(Y95,"MMMM") -> julho
... A104: 1154 | B104: 1154 | C104: 2912 | D104: 1 | E104: 45658 | F104: 2707 | H104: COMBUSTÍVEL MOTO | I104: 45847 | J104: 45847 | K104: 45847 | L104: 45847 | M104: DINHEIRO | N104: 24.09 | O104: 24.09 | P104: B | Q104: 35 | R104: 02.02.05 | S104: Combustíveis | T104: CODI.COM JEANS | V104: ITAU ALV | W104: Sem Origem | Y104: =IF(L104="",K104,L104) -> 45847 | Z104: =TEXT(Y104,"MMMM") -> julho
A105: 1154 | B105: 1154 | C105: 2202 | D105: 1 | E105: 2T-OP272_x000D_ -1/1 | F105: 1965 | H105: SILMA - ACABAMENTO | I105: 45782 | J105: 45782 | K105: 45843 | L105: 45847 | M105: PIX ITAU ALV | N105: 285.6 | O105: 285.6 | P105: B | Q105: 18 | R105: 02.01.01 | S105: Acabamento Externo | T105: DESPESAS FONECEDORES | V105: ITAU ALV | W105: Sem Origem | X105: Pagamento de Ordens de Serviço:899, | Y105: =IF(L105="",K105,L105) -> 45847 | Z105: =TEXT(Y105,"MMMM") -> julho
A106: 1154 | B106: 1154 | C106: 2199 | D106: 1 | E106: 2T-OP271_x000D_ -1/1 | F106: 1965 | H106: SILMA - ACABAMENTO | I106: 45782 | J106: 45782 | K106: 45843 | L106: 45847 | M106: PIX ITAU ALV | N106: 285.6 | O106: 285.6 | P106: B | Q106: 18 | R106: 02.01.01 | S106: Acabamento Externo | T106: DESPESAS FONECEDORES | V106: ITAU ALV | W106: Sem Origem | X106: Pagamento de Ordens de Serviço:896, | Y106: =IF(L106="",K106,L106) -> 45847 | Z106: =TEXT(Y106,"MMMM") -> julho
A107: 1154 | B107: 1154 | C107: 2156 | D107: 1 | E107: 00012941_x000D_ 3-1/2 | F107: 1949 | H107: CEDRO TEXTIL | I107: 45777 | J107: 45777 | K107: 45658 | L107: 45847 | M107: BOLETO BANCÁRIO | N107: 2159.86 | O107: 2159.86 | P107: B | Q107: 26 | R107: 02.01.09 | S107: Tecidos | T107: DESPESAS FONECEDORES | V107: ITAU ALV | W107: Sem Origem | X107: DUO ELASTI FLAT | Y107: =IF(L107="",K107,L107) -> 45847 | Z107: =TEXT(Y107,"MMMM") -> julho
A108: 1154 | B108: 1154 | C108: 2407 | D108: 1 | E108: 2T-OP294_x000D_ -1/1 | F108: 1965 | H108: SILMA - ACABAMENTO | I108: 45797 | J108: 45797 | K108: 45843 | L108: 45847 | M108: PIX ITAU ALV | N108: 405.6 | O108: 405.6 | P108: B | Q108: 18 | R108: 02.01.01 | S108: Acabamento Externo | T108: DESPESAS FONECEDORES | V108: ITAU ALV | W108: Sem Origem | X108: Pagamento de Ordens de Serviço:967, | Y108: =IF(L108="",K108,L108) -> 45847 | Z108: =TEXT(Y108,"MMMM") -> julho
A109: 1154 | B109: 1154 | C109: 2330 | D109: 1 | E109: 2T-OP285_x000D_ -1/1 | F109: 1965 | H109: SILMA - ACABAMENTO | I109: 45791 | J109: 45791 | K109: 45843 | L109: 45847 | M109: PIX ITAU ALV | N109: 655.2 | O109: 655.2 | P109: B | Q109: 18 | R109: 02.01.01 | S109: Acabamento Externo | T109: DESPESAS FONECEDORES | V109: ITAU ALV | W109: Sem Origem | X109: Pagamento de Ordens de Serviço:937, | Y109: =IF(L109="",K109,L109) -> 45847 | Z109: =TEXT(Y109,"MMMM") -> julho
A110: 1154 | B110: 1154 | C110: 2398 | D110: 1 | E110: 2T-OP291_x000D_ -1/1 | F110: 1965 | H110: SILMA - ACABAMENTO | I110: 45797 | J110: 45797 | K110: 45843 | L110: 45847 | M110: PIX ITAU ALV | N110: 600 | O110: 600 | P110: B | Q110: 18 | R110: 02.01.01 | S110: Acabamento Externo | T110: DESPESAS FONECEDORES | V110: ITAU ALV | W110: Sem Origem | X110: Pagamento de Ordens de Serviço:959, | Y110: =IF(L110="",K110,L110) -> 45847 | Z110: =TEXT(Y110,"MMMM") -> julho
A111: 1154 | B111: 1154 | C111: 2335 | D111: 1 | E111: 2T-OP286_x000D_ -1/1 | F111: 1965 | H111: SILMA - ACABAMENTO | I111: 45791 | J111: 45791 | K111: 45843 | L111: 45847 | M111: PIX ITAU ALV | N111: 374.4 | O111: 374.4 | P111: B | Q111: 18 | R111: 02.01.01 | S111: Acabamento Externo | T111: DESPESAS FONECEDORES | V111: ITAU ALV | W111: Sem Origem | X111: Pagamento de Ordens de Serviço:940, | Y111: =IF(L111="",K111,L111) -> 45847 | Z111: =TEXT(Y111,"MMMM") -> julho
A112: 1154 | B112: 1154 | C112: 2348 | D112: 1 | E112: 2T-OP289_x000D_ -1/1 | F112: 1965 | H112: SILMA - ACABAMENTO | I112: 45792 | J112: 45792 | K112: 45843 | L112: 45847 | M112: PIX ITAU ALV | N112: 136.8 | O112: 136.8 | P112: B | Q112: 18 | R112: 02.01.01 | S112: Acabamento Externo | T112: DESPESAS FONECEDORES | V112: ITAU ALV | W112: Sem Origem | X112: Pagamento de Ordens de Serviço:949, | Y112: =IF(L112="",K112,L112) -> 45847 | Z112: =TEXT(Y112,"MMMM") -> julho
A113: 1154 | B113: 1154 | C113: 2240 | D113: 1 | E113: 2T-OP274_x000D_ -1/1 | F113: 1965 | H113: SILMA - ACABAMENTO | I113: 45783 | J113: 45783 | K113: 45843 | L113: 45847 | M113: PIX ITAU ALV | N113: 468 | O113: 468 | P113: B | Q113: 18 | R113: 02.01.01 | S113: Acabamento Externo | T113: DESPESAS FONECEDORES | V113: ITAU ALV | W113: Sem Origem | X113: Pagamento de Ordens de Serviço:905, | Y113: =IF(L113="",K113,L113) -> 45847 | Z113: =TEXT(Y113,"MMMM") -> julho
A114: 1154 | B114: 1154 | C114: 2416 | D114: 1 | E114: 2T-OP295_x000D_ -1/1 | F114: 1965 | H114: SILMA - ACABAMENTO | I114: 45799 | J114: 45799 | K114: 45843 | L114: 45847 | M114: PIX ITAU ALV | N114: 436.8 | O114: 436.8 | P114: B | Q114: 18 | R114: 02.01.01 | S114: Acabamento Externo | T114: DESPESAS FONECEDORES | V114: ITAU ALV | W114: Sem Origem | X114: Pagamento de Ordens de Serviço:972, | Y114: =IF(L114="",K114,L114) -> 45847 | Z114: =TEXT(Y114,"MMMM") -> julho
A115: 1154 | B115: 1154 | C115: 2436 | D115: 1 | E115: 2T-OP296_x000D_ -1/1 | F115: 1965 | H115: SILMA - ACABAMENTO | I115: 45799 | J115: 45799 | K115: 45843 | L115: 45847 | M115: PIX ITAU ALV | N115: 489.6 | O115: 489.6 | P115: B | Q115: 18 | R115: 02.01.01 | S115: Acabamento Externo | T115: DESPESAS FONECEDORES | V115: ITAU ALV | W115: Sem Origem | X115: Pagamento de Ordens de Serviço:974, | Y115: =IF(L115="",K115,L115) -> 45847 | Z115: =TEXT(Y115,"MMMM") -> julho
...

Sheet CONTAS A PAGAR
A1: EMP. CADASTRO | B1: EMP.REFERENTE | C1: ID | D1: ID.ITEM | E1: DOCUMENTO | F1: COD. PESSOA | G1: CNPJ | H1: PESSOA | I1: DT. CAD. | J1: DT. EMISSÃO | K1: DT. VENC. | L1: DT. BAIXA | M1: FORMA PAGTO. | N1: VALOR | O1: VALOR PAGO | P1: SIT | Q1: ID.PL.CONTAS | R1: COD. PL CONTAS | S1: PLANO DE CONTAS | T1: CENTRO DE CUSTO | U1: COD.CONTA | V1: CONTA | W1: ORIGEM CAD.PESSOAS | X1: OBS.: | Y1: MÊS | Z1: MÊS TEXTO
A2: 1154 | B2: 1154 | C2: 582 | D2: 3 | E2: 00037384_x000D_ 7-3/3 | F2: 1976 | G2: 61.520.607/0018-35 | H2: SANTISTA TEXTIL | I2: 45565 | J2: 45565 | K2: 45658 | L2: 45656 | M2: BOLETO BANCÁRIO | N2: 3154.33 | O2: 3154.33 | P2: B | Q2: 26 | R2: 02.01.09 | S2: Tecidos | T2: CODI.COM JEANS | V2: ITAU ALV | W2: Sem Origem
A3: 1154 | B3: 1154 | C3: 1095 | D3: 1 | E3: 45658 | F3: 1984 | H3: SHEILA ETIQUETAS | I3: 45637 | J3: 45637 | K3: 45658 | L3: 45656 | M3: BOLETO BANCÁRIO | N3: 430 | O3: 430 | P3: B | Q3: 23 | R3: 02.01.06 | S3: Aviamento | T3: CODI.COM JEANS | V3: ITAU ALV | W3: Sem Origem
A4: 1154 | B4: 1154 | C4: 797 | D4: 1 | E4: OP109-1/_x000D_ 1 | F4: 1957 | H4: ROGERIO - TRAVETE | I4: 45594 | J4: 45594 | K4: 45662 | L4: 45665 | M4: PIX ITAU ALV | N4: 157 | O4: 157 | P4: B | Q4: 27 | R4: 02.01.10 | S4: Travete | T4: DESPESAS FONECEDORES | V4: ITAU ALV | W4: Sem Origem
A5: 1154 | B5: 1154 | C5: 798 | D5: 1 | E5: OP109-1/_x000D_ 1 | F5: 1965 | H5: SILMA - ACABAMENTO | I5: 45594 | J5: 45594 | K5: 45662 | L5: 45649 | M5: PIX ITAU ALV | N5: 345.4 | O5: 345.4 | P5: B | Q5: 18 | R5: 02.01.01 | S5: Acabamento Externo | T5: DESPESAS FONECEDORES | V5: ITAU ALV | W5: Sem Origem
A6: 1154 | B6: 1154 | C6: 807 | D6: 1 | E6: OP112-1/_x000D_ 1 | F6: 1957 | H6: ROGERIO - TRAVETE | I6: 45594 | J6: 45594 | K6: 45662 | L6: 45637 | M6: PIX ITAU ALV | N6: 147 | O6: 147 | P6: B | Q6: 27 | R6: 02.01.10 | S6: Travete | T6: DESPESAS FONECEDORES | V6: ITAU ALV | W6: Sem Origem | X6: compras mês
A7: 1154 | B7: 1154 | C7: 808 | D7: 1 | E7: OP112-1/_x000D_ 1 | F7: 1965 | H7: SILMA - ACABAMENTO | I7: 45594 | J7: 45594 | K7: 45662 | L7: 45649 | M7: PIX ITAU ALV | N7: 323.4 | O7: 323.4 | P7: B | Q7: 18 | R7: 02.01.01 | S7: Acabamento Externo | T7: DESPESAS FONECEDORES | V7: ITAU ALV | W7: Sem Origem
A8: 1154 | B8: 1154 | C8: 897 | D8: 1 | E8: OP125-1/_x000D_ 1 | F8: 1957 | H8: ROGERIO - TRAVETE | I8: 45602 | J8: 45602 | K8: 45662 | L8: 45665 | M8: PIX ITAU ALV | N8: 700 | O8: 700 | P8: B | Q8: 27 | R8: 02.01.10 | S8: Travete | T8: DESPESAS FONECEDORES | V8: ITAU ALV | W8: Sem Origem | X8: Pagamento de Ordens de Serviço:420,
A9: 1154 | B9: 1154 | C9: 898 | D9: 1 | E9: OP125-1/_x000D_ 1 | F9: 1965 | H9: SILMA - ACABAMENTO | I9: 45602 | J9: 45602 | K9: 45662 | L9: 45649 | M9: PIX ITAU ALV | N9: 1540 | O9: 1540 | P9: B | Q9: 18 | R9: 02.01.01 | S9: Acabamento Externo | T9: DESPESAS FONECEDORES | V9: ITAU ALV | W9: Sem Origem | X9: Pagamento de Ordens de Serviço:475,
A10: 1154 | B10: 1154 | C10: 929 | D10: 1 | E10: OP126-1/_x000D_ 1 | F10: 1957 | H10: ROGERIO - TRAVETE | I10: 45607 | J10: 45607 | K10: 45662 | L10: 45665 | M10: PIX ITAU ALV | N10: 120 | O10: 120 | P10: B | Q10: 27 | R10: 02.01.10 | S10: Travete | T10: DESPESAS FONECEDORES | V10: ITAU ALV | W10: Sem Origem | X10: Pagamento de Ordens de Serviço:478,
A11: 1154 | B11: 1154 | C11: 930 | D11: 1 | E11: OP126-1/_x000D_ 1 | F11: 1965 | H11: SILMA - ACABAMENTO | I11: 45607 | J11: 45607 | K11: 45662 | L11: 45649 | M11: PIX ITAU ALV | N11: 264 | O11: 264 | P11: B | Q11: 18 | R11: 02.01.01 | S11: Acabamento Externo | T11: DESPESAS FONECEDORES | V11: ITAU ALV | W11: Sem Origem
A12: 1154 | B12: 1154 | C12: 935 | D12: 1 | E12: OP128-1/_x000D_ 1 | F12: 1957 | H12: ROGERIO - TRAVETE | I12: 45608 | J12: 45608 | K12: 45662 | L12: 45665 | M12: PIX ITAU ALV | N12: 423 | O12: 423 | P12: B | Q12: 27 | R12: 02.01.10 | S12: Travete | T12: DESPESAS FONECEDORES | V12: ITAU ALV | W12: Sem Origem
A13: 1154 | B13: 1154 | C13: 945 | D13: 1 | E13: OP131-1/_x000D_ 1 | F13: 1957 | H13: ROGERIO - TRAVETE | I13: 45608 | J13: 45608 | K13: 45662 | L13: 45665 | M13: PIX ITAU ALV | N13: 77 | O13: 77 | P13: B | Q13: 27 | R13: 02.01.10 | S13: Travete | T13: DESPESAS FONECEDORES | V13: ITAU ALV | W13: Sem Origem
A14: 1154 | B14: 1154 | C14: 946 | D14: 1 | E14: OP131-1/_x000D_ 1 | F14: 1965 | H14: SILMA - ACABAMENTO | I14: 45608 | J14: 45608 | K14: 45662 | L14: 45638 | M14: PIX ITAU ALV | N14: 169.4 | O14: 169.4 | P14: B | Q14: 18 | R14: 02.01.01 | S14: Acabamento Externo | T14: DESPESAS FONECEDORES | V14: ITAU ALV | W14: Sem Origem
A15: 1154 | B15: 1154 | C15: 949 | D15: 1 | E15: OP132-1/_x000D_ 1 | F15: 1957 | H15: ROGERIO - TRAVETE | I15: 45608 | J15: 45608 | K15: 45662 | L15: 45665 | M15: PIX ITAU ALV | N15: 300 | O15: 300 | P15: B | Q15: 27 | R15: 02.01.10 | S15: Travete | T15: DESPESAS FONECEDORES | V15: ITAU ALV | W15: Sem Origem
A16: 1154 | B16: 1154 | C16: 954 | D16: 1 | E16: OP133-1/_x000D_ 1 | F16: 1957 | H16: ROGERIO - TRAVETE | I16: 45608 | J16: 45608 | K16: 45662 | L16: 45665 | M16: PIX ITAU ALV | N16: 40 | O16: 40 | P16: B | Q16: 27 | R16: 02.01.10 | S16: Travete | T16: DESPESAS FONECEDORES | V16: ITAU ALV | W16: Sem Origem
A17: 1154 | B17: 1154 | C17: 973 | D17: 1 | E17: OP134-1/_x000D_ 1 | F17: 1957 | H17: ROGERIO - TRAVETE | I17: 45614 | J17: 45614 | K17: 45662 | L17: 45665 | M17: PIX ITAU ALV | N17: 434 | O17: 434 | P17: B | Q17: 27 | R17: 02.01.10 | S17: Travete | T17: DESPESAS FONECEDORES | V17: ITAU ALV | W17: Sem Origem
A18: 1154 | B18: 1154 | C18: 976 | D18: 1 | E18: OP135-1/_x000D_ 1 | F18: 1957 | H18: ROGERIO - TRAVETE | I18: 45614 | J18: 45614 | K18: 45662 | L18: 45637 | M18: PIX ITAU ALV | N18: 45 | O18: 45 | P18: B | Q18: 27 | R18: 02.01.10 | S18: Travete | T18: DESPESAS FONECEDORES | V18: ITAU ALV | W18: Sem Origem
A19: 1154 | B19: 1154 | C19: 977 | D19: 1 | E19: OP135-1/_x000D_ 1 | F19: 1965 | H19: SILMA - ACABAMENTO | I19: 45614 | J19: 45614 | K19: 45662 | L19: 45649 | M19: PIX ITAU ALV | N19: 99 | O19: 99 | P19: B | Q19: 18 | R19: 02.01.01 | S19: Acabamento Externo | T19: DESPESAS FONECEDORES | V19: ITAU ALV | W19: Sem Origem
A20: 1154 | B20: 1154 | C20: 992 | D20: 1 | E20: OP136-1/_x000D_ 1 | F20: 1957 | H20: ROGERIO - TRAVETE | I20: 45618 | J20: 45618 | K20: 45662 | L20: 45630 | M20: PIX ITAU ALV | N20: 430 | O20: 430 | P20: B | Q20: 27 | R20: 02.01.10 | S20: Travete | T20: DESPESAS FONECEDORES | V20: ITAU ALV | W20: Sem Origem
A21: 1154 | B21: 1154 | C21: 993 | D21: 1 | E21: OP136-1/_x000D_ 1 | F21: 1965 | H21: SILMA - ACABAMENTO | I21: 45618 | J21: 45618 | K21: 45662 | L21: 45649 | M21: PIX ITAU ALV | N21: 946 | O21: 946 | P21: B | Q21: 18 | R21: 02.01.01 | S21: Acabamento Externo | T21: DESPESAS FONECEDORES | V21: ITAU ALV | W21: Sem Origem
A22: 1154 | B22: 1154 | C22: 995 | D22: 1 | E22: OP137-1/_x000D_ 1 | F22: 1957 | H22: ROGERIO - TRAVETE | I22: 45618 | J22: 45618 | K22: 45662 | L22: 45665 | M22: PIX ITAU ALV | N22: 140 | O22: 140 | P22: B | Q22: 27 | R22: 02.01.10 | S22: Travete | T22: DESPESAS FONECEDORES | V22: ITAU ALV | W22: Sem Origem
... A29: 1154 | B29: 1154 | C29: 869 | D29: 1 | E29: OP120-1/_x000D_ 1 | F29: 1957 | H29: ROGERIO - TRAVETE | I29: 45600 | J29: 45600 | K29: 45662 | L29: 45665 | M29: PIX ITAU ALV | N29: 247 | O29: 247 | P29: B | Q29: 27 | R29: 02.01.10 | S29: Travete | T29: DESPESAS FONECEDORES | V29: ITAU ALV | W29: Sem Origem
A30: 1154 | B30: 1154 | C30: 772 | D30: 3 | E30: 45780 | F30: 2152 | H30: LUCAS/ CONTADOR | I30: 45587 | J30: 45587 | K30: 45662 | L30: 45688 | M30: PIX ITAU ALV | N30: 920 | O30: 920 | P30: B | Q30: 39 | R30: 02.02.09 | S30: Advogados - Honorários | T30: DESPESAS MENSAIS | V30: ITAU ALV | W30: Sem Origem
A31: 1154 | B31: 1154 | C31: 759 | D31: 3 | E31: 45780 | F31: 2110 | H31: BORGES ESTOQUE | I31: 45587 | J31: 45587 | K31: 45663 | L31: 45664 | M31: PIX ITAU ALV | N31: 2100 | O31: 2100 | P31: B | Q31: 83 | R31: 02.03.13 | S31: Salário e Ordenados | T31: DESPESA COLABORADORES | V31: ITAU ALV | W31: Sem Origem | X31: ERREJOTA
A32: 1154 | B32: 1154 | C32: 761 | D32: 3 | E32: 45780 | F32: 2060 | H32: AILTON CORTADOR | I32: 45587 | J32: 45587 | K32: 45663 | L32: 45664 | M32: PIX ITAU ALV | N32: 2274 | O32: 2274 | P32: B | Q32: 83 | R32: 02.03.13 | S32: Salário e Ordenados | T32: DESPESA COLABORADORES | V32: ITAU ALV | W32: Sem Origem | X32: Pagamento de Ordens de Serviço:369,
A33: 1154 | B33: 1154 | C33: 762 | D33: 3 | E33: 45780 | F33: 2186 | H33: JOSÉ HAMILTON CORTADOR | I33: 45587 | J33: 45587 | K33: 45663 | L33: 45664 | M33: PIX ITAU ALV | N33: 1400 | O33: 1400 | P33: B | Q33: 83 | R33: 02.03.13 | S33: Salário e Ordenados | T33: DESPESA COLABORADORES | V33: ITAU ALV | W33: Sem Origem | X33: Pagamento de Ordens de Serviço:395,
A34: 1154 | B34: 1154 | C34: 763 | D34: 3 | E34: 45780 | F34: 2063 | H34: DELVA GERENTE DO ESTOQUE | I34: 45587 | J34: 45587 | K34: 45663 | L34: 45664 | M34: PIX ITAU ALV | N34: 1700 | O34: 1700 | P34: B | Q34: 83 | R34: 02.03.13 | S34: Salário e Ordenados | T34: DESPESA COLABORADORES | V34: ITAU ALV | W34: Sem Origem | X34: Pagamento de Ordens de Serviço:401,
A35: 1154 | B35: 1154 | C35: 764 | D35: 3 | E35: 45780 | F35: 2064 | H35: WENDER WALLAN | I35: 45587 | J35: 45587 | K35: 45663 | L35: 45664 | M35: PIX ITAU ALV | N35: 2600 | O35: 2600 | P35: B | Q35: 83 | R35: 02.03.13 | S35: Salário e Ordenados | T35: DESPESA COLABORADORES | V35: ITAU ALV | W35: Sem Origem | X35: Pagamento de Ordens de Serviço:410,
A36: 1154 | B36: 1154 | C36: 766 | D36: 2 | E36: 45749 | F36: 828 | H36: PAULO ESTOQUE ENTREGAS | I36: 45587 | J36: 45587 | K36: 45663 | L36: =K36 -> 45663 | M36: PIX ITAU ALV | N36: 1800 | P36: S | Q36: 83 | R36: 02.03.13 | S36: Salário e Ordenados | T36: DESPESA COLABORADORES | V36: ITAU ALV | W36: Sem Origem | X36: Pagamento de Ordens de Serviço:413,
A37: 1154 | B37: 1154 | C37: 767 | D37: 3 | E37: 45780 | F37: 2120 | H37: GABY VENDAS LOJA | I37: 45587 | J37: 45587 | K37: 45663 | L37: =K37 -> 45663 | M37: PIX ITAU ALV | N37: 1412 | P37: S | Q37: 83 | R37: 02.03.13 | S37: Salário e Ordenados | T37: DESPESA COLABORADORES | V37: ITAU ALV | W37: Sem Origem | X37: Pagamento de Ordens de Serviço:415,
A38: 1154 | B38: 1154 | C38: 769 | D38: 3 | E38: 45780 | F38: 2180 | H38: ADRIANA VENDAS FÁBRICA | I38: 45587 | J38: 45587 | K38: 45663 | L38: =K38 -> 45663 | M38: PIX ITAU ALV | N38: 1412 | P38: S | Q38: 83 | R38: 02.03.13 | S38: Salário e Ordenados | T38: DESPESA COLABORADORES | V38: ITAU ALV | W38: Sem Origem | X38: Pagamento de Ordens de Serviço:418,
A39: 1154 | B39: 1154 | C39: 770 | D39: 3 | E39: 45780 | F39: 2112 | H39: MARIA EDUARDA VENDAS FÁBRICA | I39: 45587 | J39: 45587 | K39: 45663 | L39: =K39 -> 45663 | M39: PIX ITAU ALV | N39: 1412 | P39: S | Q39: 83 | R39: 02.03.13 | S39: Salário e Ordenados | T39: DESPESA COLABORADORES | V39: ITAU ALV | W39: Sem Origem | X39: Pagamento de Ordens de Serviço:427,
A40: 1154 | B40: 1154 | C40: 773 | D40: 3 | E40: 45780 | F40: 2071 | H40: DANIEL ENNOS | I40: 45587 | J40: 45587 | K40: 45663 | L40: =K40 -> 45663 | M40: PIX ITAU ALV | N40: 4500 | P40: S | Q40: 83 | R40: 02.03.13 | S40: Salário e Ordenados | T40: DESPESA COLABORADORES | V40: ITAU ALV | W40: Sem Origem | X40: Pagamento de Ordens de Serviço:430,
A41: 1154 | B41: 1154 | C41: 774 | D41: 3 | E41: 45780 | F41: 2070 | H41: LUCAS KOJIMA | I41: 45587 | J41: 45587 | K41: 45663 | L41: 45664 | M41: PIX ITAU ALV | N41: 1500 | O41: 1500 | P41: B | Q41: 83 | R41: 02.03.13 | S41: Salário e Ordenados | T41: DESPESA COLABORADORES | V41: ITAU ALV | W41: Sem Origem | X41: Pagamento de Ordens de Serviço:433,
A42: 1154 | B42: 1154 | C42: 902 | D42: 2 | E42: 45718 | F42: 2260 | H42: THAIS VENDAS FABRICA | I42: 45603 | J42: 45603 | K42: 45663 | L42: =K42 -> 45663 | M42: PIX ITAU ALV | N42: 1412 | P42: S | Q42: 83 | R42: 02.03.13 | S42: Salário e Ordenados | T42: DESPESA COLABORADORES | V42: ITAU ALV | W42: Sem Origem | X42: Pagamento de Ordens de Serviço:436,
A43: 1154 | B43: 1154 | C43: 1020 | D43: 1 | E43: OP139QS_x000D_ -1/1 | F43: 1953 | H43: CIDA - FACÇÃO | I43: 45625 | J43: 45625 | K43: 45663 | L43: 45636 | M43: PIX ITAU ALV | N43: 517.5 | O43: 517.5 | P43: B | Q43: 21 | R43: 02.01.04 | S43: Facção | T43: DESPESAS FONECEDORES | V43: ITAU ALV | W43: Sem Origem | X43: Pagamento de Ordens de Serviço:439,
A44: 1154 | B44: 1154 | C44: 1045 | D44: 1 | E44: OP108-1/_x000D_ 1 | F44: 1957 | H44: ROGERIO - TRAVETE | I44: 45635 | J44: 45635 | K44: 45663 | L44: 45665 | M44: PIX ITAU ALV | N44: 260 | O44: 260 | P44: B | Q44: 27 | R44: 02.01.10 | S44: Travete | T44: DESPESAS FONECEDORES | V44: ITAU ALV | W44: Sem Origem | X44: Pagamento de Ordens de Serviço:450,
A45: 1154 | B45: 1154 | C45: 1048 | D45: 1 | E45: OP111-1/_x000D_ 1 | F45: 1957 | H45: ROGERIO - TRAVETE | I45: 45635 | J45: 45635 | K45: 45663 | L45: 45665 | M45: PIX ITAU ALV | N45: 325 | O45: 325 | P45: B | Q45: 27 | R45: 02.01.10 | S45: Travete | T45: DESPESAS FONECEDORES | V45: ITAU ALV | W45: Sem Origem | X45: Pagamento de Ordens de Serviço:453,
A46: 1154 | B46: 1154 | C46: 1049 | D46: 1 | E46: OP114-1/_x000D_ 1 | F46: 1957 | H46: ROGERIO - TRAVETE | I46: 45635 | J46: 45635 | K46: 45663 | L46: 45665 | M46: PIX ITAU ALV | N46: 40 | O46: 40 | P46: B | Q46: 27 | R46: 02.01.10 | S46: Travete | T46: DESPESAS FONECEDORES | V46: ITAU ALV | W46: Sem Origem | X46: Pagamento de Ordens de Serviço:454,
A47: 1154 | B47: 1154 | C47: 1050 | D47: 1 | E47: OP118-1/_x000D_ 1 | F47: 1957 | H47: ROGERIO - TRAVETE | I47: 45635 | J47: 45635 | K47: 45663 | L47: 45665 | M47: PIX ITAU ALV | N47: 403 | O47: 403 | P47: B | Q47: 27 | R47: 02.01.10 | S47: Travete | T47: DESPESAS FONECEDORES | V47: ITAU ALV | W47: Sem Origem | X47: Pagamento de Ordens de Serviço:457,
A48: 1154 | B48: 1154 | C48: 1051 | D48: 1 | E48: OP123-1/_x000D_ 1 | F48: 1957 | H48: ROGERIO - TRAVETE | I48: 45635 | J48: 45635 | K48: 45663 | L48: 45665 | M48: PIX ITAU ALV | N48: 308 | O48: 308 | P48: B | Q48: 27 | R48: 02.01.10 | S48: Travete | T48: DESPESAS FONECEDORES | V48: ITAU ALV | W48: Sem Origem | X48: Pagamento de Ordens de Serviço:458,
A49: 1154 | B49: 1154 | C49: 1056 | D49: 1 | E49: OP101-1/_x000D_ 1 | F49: 1965 | H49: SILMA - ACABAMENTO | I49: 45635 | J49: 45635 | K49: 45663 | L49: 45649 | M49: PIX ITAU ALV | N49: 1601.6 | O49: 1601.6 | P49: B | Q49: 18 | R49: 02.01.01 | S49: Acabamento Externo | T49: DESPESAS FONECEDORES | V49: ITAU ALV | W49: Sem Origem | X49: Pagamento de Ordens de Serviço:354,
A50: 1154 | B50: 1154 | C50: 1058 | D50: 1 | E50: OP108-1/_x000D_ 1 | F50: 1965 | H50: SILMA - ACABAMENTO | I50: 45635 | J50: 45635 | K50: 45663 | L50: 45649 | M50: PIX ITAU ALV | N50: 572 | O50: 572 | P50: B | Q50: 18 | R50: 02.01.01 | S50: Acabamento Externo | T50: DESPESAS FONECEDORES | V50: ITAU ALV | W50: Sem Origem | X50: Pagamento de Ordens de Serviço:310,
A51: 1154 | B51: 1154 | C51: 1059 | D51: 1 | E51: OP111-1/_x000D_ 1 | F51: 1965 | H51: SILMA - ACABAMENTO | I51: 45635 | J51: 45635 | K51: 45663 | L51: 45649 | M51: PIX ITAU ALV | N51: 715 | O51: 715 | P51: B | Q51: 18 | R51: 02.01.01 | S51: Acabamento Externo | T51: DESPESAS FONECEDORES | V51: ITAU ALV | W51: Sem Origem | X51: Pagamento de Ordens de Serviço:482,
A52: 1154 | B52: 1154 | C52: 1060 | D52: 1 | E52: OP114-1/_x000D_ 1 | F52: 1965 | H52: SILMA - ACABAMENTO | I52: 45635 | J52: 45635 | K52: 45663 | L52: 45649 | M52: PIX ITAU ALV | N52: 88 | O52: 88 | P52: B | Q52: 18 | R52: 02.01.01 | S52: Acabamento Externo | T52: DESPESAS FONECEDORES | V52: ITAU ALV | W52: Sem Origem | X52: Pagamento de Ordens de Serviço:485,
A53: 1154 | B53: 1154 | C53: 1061 | D53: 1 | E53: OP115-1/_x000D_ 1 | F53: 1965 | H53: SILMA - ACABAMENTO | I53: 45635 | J53: 45635 | K53: 45663 | L53: 45649 | M53: PIX ITAU ALV | N53: 598.4 | O53: 598.4 | P53: B | Q53: 18 | R53: 02.01.01 | S53: Acabamento Externo | T53: DESPESAS FONECEDORES | V53: ITAU ALV | W53: Sem Origem | X53: Pagamento de Ordens de Serviço:488,
A54: 1154 | B54: 1154 | C54: 1062 | D54: 1 | E54: OP117-1/_x000D_ 1 | F54: 1965 | H54: SILMA - ACABAMENTO | I54: 45635 | J54: 45635 | K54: 45663 | L54: 45649 | M54: PIX ITAU ALV | N54: 686.4 | O54: 686.4 | P54: B | Q54: 18 | R54: 02.01.01 | S54: Acabamento Externo | T54: DESPESAS FONECEDORES | V54: ITAU ALV | W54: Sem Origem | X54: Pagamento de Ordens de Serviço:490,
... A56: 1154 | B56: 1154 | C56: 1065 | D56: 1 | E56: OP121-1/_x000D_ 1 | F56: 1965 | H56: SILMA - ACABAMENTO | I56: 45635 | J56: 45635 | K56: 45663 | L56: 45649 | M56: PIX ITAU ALV | N56: 543.4 | O56: 543.4 | P56: B | Q56: 18 | R56: 02.01.01 | S56: Acabamento Externo | T56: DESPESAS FONECEDORES | V56: ITAU ALV | W56: Sem Origem | X56: ACERTO + 258,61 DO FGTS
A57: 1154 | B57: 1154 | C57: 1066 | D57: 1 | E57: OP122-1/_x000D_ 1 | F57: 1965 | H57: SILMA - ACABAMENTO | I57: 45635 | J57: 45635 | K57: 45663 | L57: 45649 | M57: PIX ITAU ALV | N57: 176 | O57: 176 | P57: B | Q57: 18 | R57: 02.01.01 | S57: Acabamento Externo | T57: DESPESAS FONECEDORES | V57: ITAU ALV | W57: Sem Origem
A58: 1154 | B58: 1154 | C58: 1067 | D58: 1 | E58: OP123-1/_x000D_ 1 | F58: 1965 | H58: SILMA - ACABAMENTO | I58: 45635 | J58: 45635 | K58: 45663 | L58: 45649 | M58: PIX ITAU ALV | N58: 677.6 | O58: 677.6 | P58: B | Q58: 18 | R58: 02.01.01 | S58: Acabamento Externo | T58: DESPESAS FONECEDORES | V58: ITAU ALV | W58: Sem Origem
A59: 1154 | B59: 1154 | C59: 1078 | D59: 1 | E59: OP144-1/_x000D_ 1 | F59: 1957 | H59: ROGERIO - TRAVETE | I59: 45636 | J59: 45636 | K59: 45663 | L59: 45665 | M59: PIX ITAU ALV | N59: 44 | O59: 44 | P59: B | Q59: 27 | R59: 02.01.10 | S59: Travete | T59: DESPESAS FONECEDORES | V59: ITAU ALV | W59: Sem Origem
A60: 1154 | B60: 1154 | C60: 1079 | D60: 1 | E60: OP144-1/_x000D_ 1 | F60: 1965 | H60: SILMA - ACABAMENTO | I60: 45636 | J60: 45636 | K60: 45663 | L60: 45649 | M60: PIX ITAU ALV | N60: 96.8 | O60: 96.8 | P60: B | Q60: 18 | R60: 02.01.01 | S60: Acabamento Externo | T60: DESPESAS FONECEDORES | V60: ITAU ALV | W60: Sem Origem | X60: Pagamento de Ordens de Serviço:535,
A61: 1154 | B61: 1154 | C61: 1081 | D61: 1 | E61: OP145-1/_x000D_ 1 | F61: 1957 | H61: ROGERIO - TRAVETE | I61: 45636 | J61: 45636 | K61: 45663 | L61: 45665 | M61: PIX ITAU ALV | N61: 44 | O61: 44 | P61: B | Q61: 27 | R61: 02.01.10 | S61: Travete | T61: DESPESAS FONECEDORES | V61: ITAU ALV | W61: Sem Origem
A62: 1154 | B62: 1154 | C62: 1082 | D62: 1 | E62: OP145-1/_x000D_ 1 | F62: 1965 | H62: SILMA - ACABAMENTO | I62: 45636 | J62: 45636 | K62: 45663 | L62: 45649 | M62: PIX ITAU ALV | N62: 96.8 | O62: 96.8 | P62: B | Q62: 18 | R62: 02.01.01 | S62: Acabamento Externo | T62: DESPESAS FONECEDORES | V62: ITAU ALV | W62: Sem Origem
A63: 1154 | B63: 1154 | C63: 1084 | D63: 1 | E63: OP146-1/_x000D_ 1 | F63: 1957 | H63: ROGERIO - TRAVETE | I63: 45636 | J63: 45636 | K63: 45663 | L63: 45665 | M63: PIX ITAU ALV | N63: 44 | O63: 44 | P63: B | Q63: 27 | R63: 02.01.10 | S63: Travete | T63: DESPESAS FONECEDORES | V63: ITAU ALV | W63: Sem Origem
A64: 1154 | B64: 1154 | C64: 1085 | D64: 1 | E64: OP146-1/_x000D_ 1 | F64: 1965 | H64: SILMA - ACABAMENTO | I64: 45636 | J64: 45636 | K64: 45663 | L64: 45649 | M64: PIX ITAU ALV | N64: 96.8 | O64: 96.8 | P64: B | Q64: 18 | R64: 02.01.01 | S64: Acabamento Externo | T64: DESPESAS FONECEDORES | V64: ITAU ALV | W64: Sem Origem
A65: 1154 | B65: 1154 | C65: 1094 | D65: 1 | E65: OP147-1/_x000D_ 1 | F65: 1954 | H65: HERON - FACÇÃO | I65: 45637 | J65: 45637 | K65: 45663 | L65: 45665 | M65: PIX ITAU ALV | N65: 2432 | O65: 2432 | P65: B | Q65: 21 | R65: 02.01.04 | S65: Facção | T65: DESPESAS FONECEDORES | V65: ITAU ALV | W65: Sem Origem
A66: 1154 | B66: 1154 | C66: 1100 | D66: 1 | E66: OP132-1/_x000D_ 1 | F66: 1966 | H66: JANE - ACABAMENTO | I66: 45637 | J66: 45637 | K66: 45663 | L66: 45653 | M66: PIX ITAU ALV | N66: 660 | O66: 660 | P66: B | Q66: 18 | R66: 02.01.01 | S66: Acabamento Externo | T66: DESPESAS FONECEDORES | V66: ITAU ALV | W66: Sem Origem
A67: 1154 | B67: 1154 | C67: 1101 | D67: 1 | E67: OP133-1/_x000D_ 1 | F67: 1966 | H67: JANE - ACABAMENTO | I67: 45637 | J67: 45637 | K67: 45663 | L67: 45653 | M67: PIX ITAU ALV | N67: 88 | O67: 88 | P67: B | Q67: 18 | R67: 02.01.01 | S67: Acabamento Externo | T67: DESPESAS FONECEDORES | V67: ITAU ALV | W67: Sem Origem
A68: 1154 | B68: 1154 | C68: 1017 | D68: 1 | E68: OP138-1/_x000D_ 1 | F68: 1953 | H68: CIDA - FACÇÃO | I68: 45625 | J68: 45625 | K68: 45663 | L68: 45636 | M68: PIX ITAU ALV | N68: 517.5 | O68: 517.5 | P68: B | Q68: 21 | R68: 02.01.04 | S68: Facção | T68: DESPESAS FONECEDORES | V68: ITAU ALV | W68: Sem Origem
A69: 1154 | B69: 1154 | C69: 1201 | D69: 1 | E69: 45658 | F69: 828 | H69: PAULO ESTOQUE ENTREGAS | I69: 45664 | J69: 45664 | K69: 45664 | L69: 45664 | M69: PIX ITAU ALV | N69: 1100 | O69: 1100 | P69: B | Q69: 83 | R69: 02.03.13 | S69: Salário e Ordenados | T69: DESPESA COLABORADORES | V69: ITAU ALV | W69: Sem Origem
A70: 1154 | B70: 1154 | C70: 1203 | D70: 1 | E70: 45658 | F70: 2260 | H70: THAIS VENDAS FABRICA | I70: 45664 | J70: 45664 | K70: 45664 | L70: 45664 | M70: PIX ITAU ALV | N70: 1248.95 | O70: 1248.95 | P70: B | Q70: 83 | R70: 02.03.13 | S70: Salário e Ordenados | T70: DESPESA COLABORADORES | V70: ITAU ALV | W70: Sem Origem
A71: 1154 | B71: 1154 | C71: 1204 | D71: 1 | E71: 45658 | F71: 2180 | H71: ADRIANA VENDAS FÁBRICA | I71: 45664 | J71: 45664 | K71: 45664 | L71: 45664 | M71: PIX ITAU ALV | N71: 3736 | O71: 3736 | P71: B | Q71: 83 | R71: 02.03.13 | S71: Salário e Ordenados | T71: DESPESA COLABORADORES | V71: ITAU ALV | W71: Sem Origem
A72: 1154 | B72: 1154 | C72: 1205 | D72: 1 | E72: 45658 | F72: 2112 | H72: MARIA EDUARDA VENDAS FÁBRICA | I72: 45664 | J72: 45664 | K72: 45664 | L72: 45664 | M72: PIX ITAU ALV | N72: 2080.62 | O72: 2080.62 | P72: B | Q72: 83 | R72: 02.03.13 | S72: Salário e Ordenados | T72: DESPESA COLABORADORES | V72: ITAU ALV | W72: Sem Origem
A73: 1154 | B73: 1154 | C73: 1206 | D73: 1 | E73: 45658 | F73: 2120 | H73: GABY VENDAS LOJA | I73: 45664 | J73: 45664 | K73: 45664 | L73: 45664 | M73: PIX ITAU ALV | N73: 3735.51 | O73: 3735.51 | P73: B | Q73: 83 | R73: 02.03.13 | S73: Salário e Ordenados | T73: DESPESA COLABORADORES | V73: ITAU ALV | W73: Sem Origem
A74: 1154 | B74: 1154 | C74: 1207 | D74: 1 | E74: 45658 | F74: 2071 | H74: DANIEL ENNOS | I74: 45664 | J74: 45664 | K74: 45664 | L74: 45664 | M74: PIX ITAU ALV | N74: 6867 | O74: 6867 | P74: B | Q74: 83 | R74: 02.03.13 | S74: Salário e Ordenados | T74: DESPESA COLABORADORES | V74: ITAU ALV | W74: Sem Origem
A75: 1154 | B75: 1154 | C75: 1208 | D75: 1 | E75: 45658 | F75: 2120 | H75: GABY VENDAS LOJA | I75: 45664 | J75: 45664 | K75: 45664 | L75: 45664 | M75: PIX ITAU ALV | N75: 4133.17 | O75: 4133.17 | P75: B | Q75: 76 | R75: 02.03.07 | S75: Férias | T75: DESPESA COLABORADORES | V75: ITAU ALV | W75: Sem Origem
A76: 1154 | B76: 1154 | C76: 1209 | D76: 1 | E76: 45658 | F76: 2064 | H76: WENDER WALLAN | I76: 45664 | J76: 45664 | K76: 45664 | L76: 45664 | M76: PIX ITAU ALV | N76: 3340.4 | O76: 3340.4 | P76: B | Q76: 76 | R76: 02.03.07 | S76: Férias | T76: DESPESA COLABORADORES | V76: ITAU ALV | W76: Sem Origem
A77: 1154 | B77: 1154 | C77: 1211 | D77: 1 | E77: 45658 | F77: 2136 | H77: EDIMAR GERENTE DE PRODUÇÃO | I77: 45664 | J77: 45664 | K77: 45664 | L77: 45664 | M77: PIX ITAU ALV | N77: 5000 | O77: 5000 | P77: B | Q77: 83 | R77: 02.03.13 | S77: Salário e Ordenados | T77: DESPESA COLABORADORES | V77: ITAU ALV | W77: Sem Origem
A78: 1154 | B78: 1154 | C78: 756 | D78: 10 | E78: 44470 | F78: 2114 | H78: NALVA - DIARISTA | I78: 45587 | J78: 45587 | K78: 45664 | L78: 45666 | M78: PIX ITAU ALV | N78: 140 | O78: 140 | P78: B | Q78: 83 | R78: 02.03.13 | S78: Salário e Ordenados | T78: DESPESA COLABORADORES | V78: ITAU ALV | W78: Sem Origem
A79: 1154 | B79: 1154 | C79: 1214 | D79: 1 | E79: 45658 | F79: 468 | H79: LOJA MEGA MODA PARK 215-216 | I79: 45664 | J79: 45664 | K79: 45664 | L79: 45664 | M79: BOLETO BANCÁRIO | N79: 3762 | O79: 3762 | P79: B | Q79: 32 | R79: 02.02.02 | S79: Aluguéis e Condomínios | T79: CODI.COM JEANS | V79: ITAU ALV | W79: Sem Origem | X79: Pagamento de Ordens de Serviço:546,
A80: 1154 | B80: 1154 | C80: 1213 | D80: 1 | E80: 45658 | F80: 1991 | H80: DESPESAS ESCRITORIO | I80: 45664 | J80: 45664 | K80: 45664 | L80: 45660 | M80: PIX ITAU ALV | N80: 383 | O80: 383 | P80: B | Q80: 44 | R80: 02.02.14 | S80: Material de Limpeza e Higiene | T80: DESPESAS MENSAIS | V80: ITAU ALV | W80: Sem Origem | X80: Pagamento de Ordens de Serviço:538,
A81: 1154 | B81: 1154 | C81: 1218 | D81: 1 | E81: 45658 | F81: 1982 | H81: FRETES GERAIS | I81: 45666 | J81: 45666 | K81: 45665 | L81: 45665 | M81: PIX ITAU ALV | N81: 296 | O81: 296 | P81: B | Q81: 38 | R81: 02.02.08 | S81: Frete e Transporte de Mercadorias | T81: DESPESAS MENSAIS | V81: ITAU ALV | W81: Sem Origem | X81: Pagamento de Ordens de Serviço:541,
A82: 1154 | B82: 1154 | C82: 1111 | D82: 1 | E82: 45658 | F82: 1984 | H82: SHEILA ETIQUETAS | I82: 45643 | J82: 45643 | K82: 45666 | L82: 45663 | M82: BOLETO BANCÁRIO | N82: 162.55 | O82: 162.55 | P82: B | Q82: 23 | R82: 02.01.06 | S82: Aviamento | T82: CODI.COM JEANS | V82: ITAU ALV | W82: Sem Origem | X82: Pagamento de Ordens de Serviço:552,
A83: 1154 | B83: 1154 | C83: 1221 | D83: 1 | E83: 45658 | F83: 828 | H83: PAULO ESTOQUE ENTREGAS | I83: 45666 | J83: 45666 | K83: 45666 | L83: 45666 | M83: PIX ITAU ALV | N83: 760.38 | O83: 760.38 | P83: B | Q83: 71 | R83: 02.03.02 | S83: Acertos e Recisões | T83: DESPESA COLABORADORES | V83: ITAU ALV | W83: Sem Origem | X83: Pagamento de Ordens de Serviço:566,
A84: 1154 | B84: 1154 | C84: 14 | D84: 8 | E84: 45877 | F84: 1974 | H84: CARTÃO DE CRÉDITO ITAU | I84: 45430 | J84: 45430 | K84: 45666 | L84: 45680 | M84: TRANSFERÊNCIA | N84: 9854 | O84: 9854 | P84: B | Q84: 55 | R84: 02.02.25 | S84: Empréstimos | T84: DESPESA COLABORADORES | V84: ITAU ALV | W84: Sem Origem | X84: Pagamento de Ordens de Serviço:532,
A85: 1154 | B85: 1154 | C85: 5 | D85: 8 | E85: 43678 | F85: 1969 | H85: CAPITAL GIRO ITAU PF CLEITON | I85: 45429 | J85: 45429 | K85: 45667 | L85: 45680 | M85: TRANSFERÊNCIA | N85: 12680 | O85: 12680 | P85: B | Q85: 55 | R85: 02.02.25 | S85: Empréstimos | T85: DESPESA COLABORADORES | V85: ITAU ALV | W85: Sem Origem | X85: Pagamento de Ordens de Serviço:512,
A86: 1154 | B86: 1154 | C86: 1 | D86: 6 | E86: 45997 | F86: 1947 | H86: WIKI SISTEMAS | I86: 45425 | J86: 45425 | K86: 45667 | L86: 45663 | M86: BOLETO BANCÁRIO | N86: 890 | O86: 890 | P86: B | Q86: 60 | R86: 02.02.31 | S86: Web Site e Sistema ERP | T86: DESPESA COLABORADORES | V86: ITAU ALV | W86: Sem Origem | X86: Pagamento de Ordens de Serviço:515,
A87: 1154 | B87: 1154 | C87: 1215 | D87: 1 | E87: 45658 | F87: 468 | H87: LOJA MEGA MODA PARK 215-216 | I87: 45664 | J87: 45664 | K87: 45667 | L87: 45667 | M87: BOLETO BANCÁRIO | N87: 1501 | O87: 1501 | P87: B | Q87: 32 | R87: 02.02.02 | S87: Aluguéis e Condomínios | T87: CODI.COM JEANS | V87: ITAU ALV | W87: Sem Origem | X87: Pagamento de Ordens de Serviço:518,
A88: 1154 | B88: 1154 | C88: 1239 | D88: 1 | E88: 45658 | F88: 1985 | H88: LÍDER TECIDOS | I88: 45667 | J88: 45667 | K88: 45667 | L88: 45667 | M88: PIX ITAU ALV | N88: 4890 | O88: 4890 | P88: B | Q88: 26 | R88: 02.01.09 | S88: Tecidos | T88: CODI.COM JEANS | V88: ITAU ALV | W88: Sem Origem | X88: Pagamento de Ordens de Serviço:509,
A89: 1154 | B89: 1154 | C89: 691 | D89: 2 | E89: 002763-2/_x000D_ 4 | F89: 1958 | H89: ROMERONDES - LAVANDERIA | I89: 45576 | J89: 45576 | K89: 45667 | L89: 45670 | M89: CHEQUE - EMPRESA | N89: 4000 | O89: 4000 | P89: B | Q89: 28 | R89: 02.01.11 | S89: Lavanderia | T89: DESPESAS FONECEDORES | V89: ITAU ALV | W89: Sem Origem | X89: Pagamento de Ordens de Serviço:503,
A90: 1154 | B90: 1154 | C90: 851 | D90: 1 | E90: 0002581-1_x000D_ /6 | F90: 1980 | H90: JOAO - CAPITAL DE GIRO | I90: 45595 | J90: 45595 | K90: 45669 | L90: 45678 | M90: CHEQUE - EMPRESA | N90: 4670 | O90: 4670 | P90: B | Q90: 26 | R90: 02.01.09 | S90: Empréstimos | T90: DESPESAS FONECEDORES | V90: ITAU ALV | W90: Sem Origem
A91: 1154 | B91: 1154 | C91: 856 | D91: 1 | E91: 0002551-1_x000D_ /6 | F91: 1980 | H91: JOAO - CAPITAL DE GIRO | I91: 45596 | J91: 45596 | K91: 45669 | L91: 45678 | M91: CHEQUE - EMPRESA | N91: 4500 | O91: 4500 | P91: B | Q91: 26 | R91: 02.01.09 | S91: Empréstimos | T91: DESPESAS FONECEDORES | V91: ITAU ALV | W91: Sem Origem
A92: 1154 | B92: 1154 | C92: 963 | D92: 3 | E92: 00085467_x000D_ 2-3/3 | F92: 1949 | H92: CEDRO TEXTIL | I92: 45609 | J92: 45609 | K92: 45670 | L92: 45670 | M92: BOLETO BANCÁRIO | N92: 6822.28 | O92: 6822.28 | P92: B | Q92: 26 | R92: 02.01.09 | S92: Suspenso | T92: CODI.COM JEANS | V92: ITAU ALV | W92: Sem Origem
A93: 1154 | B93: 1154 | C93: 964 | D93: 3 | E93: 00085553_x000D_ 3-3/3 | F93: 1949 | H93: CEDRO TEXTIL | I93: 45609 | J93: 45609 | K93: 45670 | L93: 45670 | M93: BOLETO BANCÁRIO | N93: 5889.21 | O93: 5889.21 | P93: B | Q93: 26 | R93: 02.01.09 | S93: Suspenso | T93: CODI.COM JEANS | V93: ITAU ALV | W93: Sem Origem
A94: 1154 | B94: 1154 | C94: 572 | D94: 3 | E94: 00085360_x000D_ 0-3/3 | F94: 1949 | H94: CEDRO TEXTIL | I94: 45559 | J94: 45559 | K94: 45670 | L94: 45670 | M94: BOLETO BANCÁRIO | N94: 10064.39 | O94: 10064.39 | P94: B | Q94: 26 | R94: 02.01.09 | S94: Suspenso | T94: CODI.COM JEANS | V94: ITAU ALV | W94: Sem Origem
A95: 1154 | B95: 1154 | C95: 1068 | D95: 1 | E95: OP142-1/_x000D_ 1 | F95: 1956 | H95: EMERSON - FACÇÃO | I95: 45635 | J95: 45635 | K95: 45670 | L95: 45663 | M95: PIX ITAU ALV | N95: 1500 | O95: 1500 | P95: B | Q95: 21 | R95: 02.01.04 | S95: Facção | T95: DESPESAS FONECEDORES | V95: ITAU ALV | W95: Sem Origem
A96: 1154 | B96: 1154 | C96: 1142 | D96: 1 | E96: OP154-1/_x000D_ 1 | F96: 1956 | H96: EMERSON - FACÇÃO | I96: 45646 | J96: 45646 | K96: 45670 | L96: 45677 | M96: PIX ITAU ALV | N96: 1976 | O96: 1976 | P96: B | Q96: 21 | R96: 02.01.04 | S96: Facção | T96: DESPESAS FONECEDORES | V96: ITAU ALV | W96: Sem Origem
A97: 1154 | B97: 1154 | C97: 1225 | D97: 1 | E97: OP160-1/_x000D_ 1 | F97: 1953 | H97: CIDA - FACÇÃO | I97: 45667 | J97: 45667 | K97: 45670 | L97: 45667 | M97: PIX ITAU ALV | N97: 1976 | O97: 1976 | P97: B | Q97: 21 | R97: 02.01.04 | S97: Facção | T97: DESPESAS FONECEDORES | V97: ITAU ALV | W97: Sem Origem
A98: 1154 | B98: 1154 | C98: 702 | D98: 3 | E98: 00085037_x000D_ 3-3/3 | F98: 1949 | H98: CEDRO TEXTIL | I98: 45579 | J98: 45579 | K98: 45670 | L98: 45670 | M98: BOLETO BANCÁRIO | N98: 2901 | O98: 2901 | P98: B | Q98: 26 | R98: 02.01.09 | S98: Suspenso | T98: DESPESAS FONECEDORES | V98: ITAU ALV | W98: Sem Origem
A99: 1154 | B99: 1154 | C99: 1220 | D99: 1 | E99: 45658 | F99: 1986 | H99: JADLOG | I99: 45666 | J99: 45666 | K99: 45670 | L99: 45680 | M99: PIX ITAU ALV | N99: 1027.78 | O99: 1027.78 | P99: B | Q99: 38 | R99: 02.02.08 | S99: Frete e Transporte de Mercadorias | T99: DESPESAS MENSAIS | V99: ITAU ALV | W99: Sem Origem
A100: 1154 | B100: 1154 | C100: 756 | D100: 11 | E100: 44501 | F100: 2114 | H100: NALVA - DIARISTA | I100: 45587 | J100: 45587 | K100: 45671 | L100: 45680 | M100: PIX ITAU ALV | N100: 140 | O100: 140 | P100: B | Q100: 83 | R100: 02.03.13 | S100: Salário e Ordenados | T100: DESPESA COLABORADORES | V100: ITAU ALV | W100: Sem Origem | X100: semana 585 / concero celular 150,00 / impressora 563,00 semana de 13 a 18/01
A101: 1154 | B101: 1154 | C101: 1522 | D101: 1 | E101: 45658 | F101: 2374 | H101: CRISLANDIA ESTOQUE FABRICA | I101: 45716 | J101: 45671 | K101: 45671 | L101: 45716 | M101: PIX ITAU ALV | N101: 20 | O101: 20 | P101: B | Q101: 75 | R101: 02.03.06 | S101: Exame Adminissional/Demissional | T101: DESPESA COLABORADORES | V101: ITAU ALV | W101: Sem Origem | X101: CAPITAL GIRO ITAU PF
A102: 1154 | B102: 1154 | C102: 893 | D102: 1 | E102: 00086082_x000D_ 7-1/3 | F102: 1949 | H102: CEDRO TEXTIL | I102: 45602 | J102: 45602 | K102: 45671 | L102: 45677 | M102: BOLETO BANCÁRIO | N102: 3408.05 | O102: 3408.05 | P102: B | Q102: 26 | R102: 02.01.09 | S102: Suspenso | T102: DESPESAS FONECEDORES | V102: ITAU ALV | W102: Sem Origem
A103: 1154 | B103: 1154 | C103: 901 | D103: 3 | E103: 45719 | F103: 2260 | H103: THAIS VENDAS FABRICA | I103: 45603 | J103: 45603 | K103: 45672 | L103: 45681 | M103: PIX ITAU ALV | N103: 700 | O103: 700 | P103: B | Q103: 88 | R103: 02.03.18 | S103: Vales e Adiantamentos | T103: DESPESA COLABORADORES | V103: ITAU ALV | W103: Sem Origem | X103: BETO - CARRO
A104: 1154 | B104: 1154 | C104: 641 | D104: 4 | E104: 45995 | F104: 2063 | H104: DELVA GERENTE DO ESTOQUE | I104: 45574 | J104: 45574 | K104: 45672 | L104: 45681 | M104: PIX ITAU ALV | N104: 300 | O104: 300 | P104: B | Q104: 88 | R104: 02.03.18 | S104: Vales e Adiantamentos | T104: DESPESA COLABORADORES | V104: ITAU ALV | W104: Sem Origem
A105: 1154 | B105: 1154 | C105: 499 | D105: 4 | E105: 45995 | F105: 2186 | H105: JOSÉ HAMILTON CORTADOR | I105: 45553 | J105: 45553 | K105: 45672 | L105: 45681 | M105: PIX ITAU ALV | N105: 500 | O105: 500 | P105: B | Q105: 88 | R105: 02.03.18 | S105: Vales e Adiantamentos | T105: DESPESA COLABORADORES | V105: ITAU ALV | W105: Sem Origem
A106: 1154 | B106: 1154 | C106: 507 | D106: 4 | E106: 45995 | F106: 389 | H106: ADRIANA CARDOSO | I106: 45553 | J106: 45553 | K106: 45672 | L106: 45681 | M106: PIX ITAU ALV | N106: 200 | O106: 200 | P106: B | Q106: 88 | R106: 02.03.18 | S106: Vales e Adiantamentos | T106: DESPESA COLABORADORES | V106: ITAU ALV | W106: Sem Origem
A107: 1154 | B107: 1154 | C107: 508 | D107: 4 | E107: 45995 | F107: 1946 | H107: MARIA EDUARDA | I107: 45553 | J107: 45553 | K107: 45672 | L107: 45681 | M107: PIX ITAU ALV | N107: 200 | O107: 200 | P107: B | Q107: 88 | R107: 02.03.18 | S107: Vales e Adiantamentos | T107: DESPESA COLABORADORES | V107: ITAU ALV | W107: Sem Origem
...

Sheet CONTAS A RECEBER
A1: DOCUMENTO | B1: CNPJ | C1: PESSOA | D1: DT.CAD. | E1: DT. VENC. | F1: DT. BAIXA | G1: FORMA PGTO. | H1: VALOR | I1: VALOR _x000D_ RECEBIDO | J1: REC. | K1: ID PL.CONTAS | L1: COD.PL.CONTAS | M1: PLANO DE CONTAS | N1: SIT | O1: PORTADOR | P1: COD.CONTA | Q1: CONTA | R1: OBS.: | S1: Nº NF-E | T1: INF. FATURA NF-E | U1: Nº NSU | V1: MÊS
A2: P1436/1 | C2: PATRICIA MARQUES | D2: 45646 | E2: 45676 | F2: 45659 | G2: LINK REDE | H2: 5625 | I2: 5625 | J2: 1201 | K2: 3 | L2: 01.01.01 | M2: Vendas | N2: B | P2: 2 | Q2: ITAU ALV | V2: =TEXT(F2,"MMMM") -> janeiro
A3: P1435/1 | B3: 27.715.843/0001-20 | C3: ADNA JULIA PINTO GOIS | D3: 45649 | E3: 45649 | F3: 45659 | G3: PIX CODI BANCO BRASIL | H3: 2450 | I3: 2450 | J3: 1213 | K3: 3 | L3: 01.01.01 | M3: Vendas | N3: B | P3: 2 | Q3: ITAU ALV | V3: =TEXT(F3,"MMMM") -> janeiro
A4: P1484/1 | B4: 48.095.856/0001-14 | C4: ESITON BARROSO | D4: 45653 | E4: 45653 | F4: 45659 | G4: PIX ITAU ALV | H4: 815 | I4: 815 | J4: 1231 | K4: 3 | L4: 01.01.01 | M4: Vendas | N4: B | P4: 2 | Q4: ITAU ALV | V4: =TEXT(F4,"MMMM") -> janeiro
A5: P1146/1 | B5: 23.728.778/0001-17 | C5: ERREJOTA OUTLET-DOUGLAS OLIVEIRA DOS SANTOS 14516832780 | D5: 45656 | E5: 45686 | F5: 45659 | G5: BOLETO BANCÁRIO | H5: 8745 | I5: 8745 | J5: 1232 | K5: 3 | L5: 01.01.01 | M5: Vendas | N5: B | P5: 2 | Q5: ITAU ALV | V5: =TEXT(F5,"MMMM") -> janeiro
A6: P1352/1 | B6: 23.728.778/0001-17 | C6: ERREJOTA OUTLET-DOUGLAS OLIVEIRA DOS SANTOS 14516832780 | D6: 45656 | E6: 45686 | F6: 45659 | G6: BOLETO BANCÁRIO | H6: 5355 | I6: 5355 | J6: 1233 | K6: 3 | L6: 01.01.01 | M6: Vendas | N6: B | P6: 2 | Q6: ITAU ALV | V6: =TEXT(F6,"MMMM") -> janeiro
A7: P966/1 | C7: GENIVALDO | D7: 45653 | E7: 45653 | F7: 45659 | G7: PIX ITAU ALV | H7: 80 | I7: 80 | J7: 863 | K7: 3 | L7: 01.01.01 | M7: Vendas | N7: B | P7: 2 | Q7: ITAU ALV | V7: =TEXT(F7,"MMMM") -> janeiro
A8: P954/1 | C8: ALEX AIRES | D8: 45654 | E8: 45654 | F8: 45659 | G8: PIX ITAU ALV | H8: 40 | I8: 40 | J8: 864 | K8: 3 | L8: 01.01.01 | M8: Vendas | N8: B | P8: 2 | Q8: ITAU ALV | V8: =TEXT(F8,"MMMM") -> janeiro
A9: P963/1 | C9: ALEX AIRES | D9: 45654 | E9: 45654 | F9: 45659 | G9: PIX ITAU ALV | H9: 100 | I9: 100 | J9: 865 | K9: 3 | L9: 01.01.01 | M9: Vendas | N9: B | P9: 2 | Q9: ITAU ALV | V9: =TEXT(F9,"MMMM") -> janeiro
A10: P968/1 | C10: GENIVALDO | D10: 45654 | E10: 45654 | F10: 45659 | G10: PIX ITAU ALV | H10: 85 | I10: 85 | J10: 866 | K10: 3 | L10: 01.01.01 | M10: Vendas | N10: B | P10: 2 | Q10: ITAU ALV | V10: =TEXT(F10,"MMMM") -> janeiro
A11: P969/1 | C11: NOME DO CLIENTE É OBRIGATÓRIO | D11: 45654 | E11: 45684 | F11: 45659 | G11: CARTÃO CRÉDITO | H11: 160 | I11: 155.38 | J11: 867 | K11: 3 | L11: 01.01.01 | M11: Vendas | N11: B | P11: 2 | Q11: ITAU ALV | V11: =TEXT(F11,"MMMM") -> janeiro
A12: P970/1 | C12: NOME DO CLIENTE É OBRIGATÓRIO | D12: 45654 | E12: 45654 | F12: 45659 | G12: CARTÃO CRÉDITO | H12: 99 | I12: 96.14 | J12: 868 | K12: 3 | L12: 01.01.01 | M12: Vendas | N12: B | P12: 2 | Q12: ITAU ALV | V12: =TEXT(F12,"MMMM") -> janeiro
A13: P972/1 | C13: NOME DO CLIENTE É OBRIGATÓRIO | D13: 45654 | E13: 45654 | F13: 45659 | G13: CARTÃO DÉBITO | H13: 140 | I13: 138.68 | J13: 869 | K13: 3 | L13: 01.01.01 | M13: Vendas | N13: B | P13: 2 | Q13: ITAU ALV | V13: =TEXT(F13,"MMMM") -> janeiro
A14: P974/ | C14: NOME DO CLIENTE É OBRIGATÓRIO | D14: 45654 | E14: 45654 | F14: 45659 | G14: CARTÃO CRÉDITO | H14: 800 | I14: 754.08 | J14: 870 | K14: 3 | L14: 01.01.01 | M14: Vendas | N14: B | P14: 2 | Q14: ITAU ALV | V14: =TEXT(F14,"MMMM") -> janeiro
A15: P963/1 | C15: ALEX AIRES | D15: 45654 | E15: 45654 | F15: 45659 | G15: PIX ITAU ALV | H15: 290 | I15: 290 | J15: 871 | K15: 3 | L15: 01.01.01 | M15: Vendas | N15: B | P15: 2 | Q15: ITAU ALV | V15: =TEXT(F15,"MMMM") -> janeiro
A16: P976/1 | C16: NOME DO CLIENTE É OBRIGATÓRIO | D16: 45656 | E16: 45656 | F16: 45659 | G16: CARTÃO CRÉDITO | H16: 170 | I16: 165.09 | J16: 872 | K16: 3 | L16: 01.01.01 | M16: Vendas | N16: B | P16: 2 | Q16: ITAU ALV | V16: =TEXT(F16,"MMMM") -> janeiro
A17: P977/1 | C17: NOME DO CLIENTE É OBRIGATÓRIO | D17: 45656 | E17: 45656 | F17: 45659 | G17: PIX ITAU ALV | H17: 20 | I17: 20 | J17: 873 | K17: 3 | L17: 01.01.01 | M17: Vendas | N17: B | P17: 2 | Q17: ITAU ALV | V17: =TEXT(F17,"MMMM") -> janeiro
A18: P978/1 | C18: GENIVALDO | D18: 45656 | E18: 45656 | F18: 45659 | G18: PIX ITAU ALV | H18: 80 | I18: 80 | J18: 874 | K18: 3 | L18: 01.01.01 | M18: Vendas | N18: B | P18: 2 | Q18: ITAU ALV | V18: =TEXT(F18,"MMMM") -> janeiro
... A21: P982/1 | C21: NOME DO CLIENTE É OBRIGATÓRIO | D21: 45656 | E21: 45656 | F21: 45659 | G21: CARTÃO DÉBITO | H21: 170 | I21: 168.4 | J21: 877 | K21: 3 | L21: 01.01.01 | M21: Vendas | N21: B | P21: 2 | Q21: ITAU ALV | V21: =TEXT(F21,"MMMM") -> janeiro
A22: P983/1 | B22: 082.693.791-82 | C22: PAULO AUGUSTO DIONIZIO CAMELÔ | D22: 45656 | E22: 45656 | F22: 45659 | G22: PIX ITAU ALV | H22: 810 | I22: 810 | J22: 878 | K22: 3 | L22: 01.01.01 | M22: Vendas | N22: B | P22: 2 | Q22: ITAU ALV | V22: =TEXT(F22,"MMMM") -> janeiro
A23: P984/1 | C23: NOME DO CLIENTE É OBRIGATÓRIO | D23: 45657 | E23: 45657 | F23: 45659 | G23: CARTÃO CRÉDITO | H23: 160 | I23: 155.38 | J23: 879 | K23: 3 | L23: 01.01.01 | M23: Vendas | N23: B | P23: 2 | Q23: ITAU ALV | V23: =TEXT(F23,"MMMM") -> janeiro
A24: P963/1 | C24: ALEX AIRES | D24: 45657 | E24: 45657 | F24: 45659 | G24: PIX ITAU ALV | H24: 50 | I24: 50 | J24: 880 | K24: 3 | L24: 01.01.01 | M24: Vendas | N24: B | P24: 2 | Q24: ITAU ALV | V24: =TEXT(F24,"MMMM") -> janeiro
A25: P988/1 | C25: NOME DO CLIENTE É OBRIGATÓRIO | D25: 45657 | E25: 45657 | F25: 45659 | G25: PIX ITAU ALV | H25: 297 | I25: 297 | J25: 882 | K25: 3 | L25: 01.01.01 | M25: Vendas | N25: B | P25: 2 | Q25: ITAU ALV | V25: =TEXT(F25,"MMMM") -> janeiro
A26: P989/1 | C26: NOME DO CLIENTE É OBRIGATÓRIO | D26: 45657 | E26: 45657 | F26: 45659 | G26: CARTÃO DÉBITO | H26: 99 | I26: 98.07 | J26: 883 | K26: 3 | L26: 01.01.01 | M26: Vendas | N26: B | P26: 2 | Q26: ITAU ALV | V26: =TEXT(F26,"MMMM") -> janeiro
A27: P986/1 | C27: GENIVALDO | D27: 45657 | E27: 45657 | F27: 45659 | G27: PIX ITAU ALV | H27: 85 | I27: 85 | J27: 884 | K27: 3 | L27: 01.01.01 | M27: Vendas | N27: B | P27: 2 | Q27: ITAU ALV | V27: =TEXT(F27,"MMMM") -> janeiro
A28: P991/1 | C28: NOME DO CLIENTE É OBRIGATÓRIO | D28: 45659 | E28: 45659 | F28: 45659 | G28: DINHEIRO | H28: 170 | I28: 170 | J28: 886 | K28: 3 | L28: 01.01.01 | M28: Vendas | N28: B | P28: 1156 | Q28: CODI.COM - LOJA BASIC 2 | V28: =TEXT(F28,"MMMM") -> janeiro
A29: P993/1 | C29: NOME DO CLIENTE É OBRIGATÓRIO | D29: 45661 | E29: 45661 | F29: 45661 | G29: DINHEIRO | H29: 705 | I29: 705 | J29: 889 | K29: 3 | L29: 01.01.01 | M29: Vendas | N29: B | P29: 1156 | Q29: CODI.COM - LOJA BASIC 2 | V29: =TEXT(F29,"MMMM") -> janeiro
A30: P1492/1 | C30: ALEX AIRES | D30: 45665 | E30: 45665 | F30: 45665 | G30: PIX ITAU ALV | H30: 5165 | I30: 5165 | J30: 1245 | K30: 3 | L30: 01.01.01 | M30: Vendas | N30: B | P30: 2 | Q30: ITAU ALV | V30: =TEXT(F30,"MMMM") -> janeiro
A31: P1499/1 | B31: 538.458.112-34 | C31: FRANCISCO PEDROSA TIMOTEO | D31: 45666 | E31: 45666 | F31: 45666 | G31: BOLETO BANCÁRIO | H31: 810 | I31: 810 | J31: 1246 | K31: 3 | L31: 01.01.01 | M31: Vendas | N31: B | P31: 2 | Q31: ITAU ALV | V31: =TEXT(F31,"MMMM") -> janeiro
A32: P1493/1 | B32: 52.736.496/0001-60 | C32: CARLOS EDUARDO BORGES | D32: 45666 | E32: 45666 | F32: 45666 | G32: PIX ITAU ALV | H32: 3290 | I32: 3290 | J32: 1247 | K32: 3 | L32: 01.01.01 | M32: Vendas | N32: B | P32: 2 | Q32: ITAU ALV | V32: =TEXT(F32,"MMMM") -> janeiro
A33: P1504/1 | B33: 35.318.134/0001-30 | C33: MLW STORE VESTUARIO E ACESSORIOS LTDA | D33: 45666 | E33: 45696 | F33: 45666 | G33: BOLETO BANCÁRIO | H33: 2240 | I33: 2240 | J33: 1248 | K33: 3 | L33: 01.01.01 | M33: Vendas | N33: B | P33: 2 | Q33: ITAU ALV | V33: =TEXT(F33,"MMMM") -> janeiro
A34: P1490/1 | B34: 52.978.259/0001-05 | C34: VINICIUS ALVES DOS SANTOS | D34: 45663 | E34: 45663 | F34: 45666 | G34: PIX ITAU ALV | H34: 4160 | I34: 4160 | J34: 1234 | K34: 3 | L34: 01.01.01 | M34: Vendas | N34: B | P34: 2 | Q34: ITAU ALV | V34: =TEXT(F34,"MMMM") -> janeiro
A35: P1488/1 | C35: WENDER CODIJEANS | D35: 45664 | E35: 45664 | F35: 45666 | G35: PIX ITAU ALV | H35: 310 | I35: 310 | J35: 1235 | K35: 3 | L35: 01.01.01 | M35: Vendas | N35: B | P35: 2 | Q35: ITAU ALV | V35: =TEXT(F35,"MMMM") -> janeiro
A36: P1323/1 | C36: WENDER CODIJEANS | D36: 45664 | E36: 45664 | F36: 45666 | G36: PIX ITAU ALV | H36: 55 | I36: 55 | J36: 1236 | K36: 3 | L36: 01.01.01 | M36: Vendas | N36: B | P36: 2 | Q36: ITAU ALV | V36: =TEXT(F36,"MMMM") -> janeiro
A37: P1358/1 | C37: AILTON | D37: 45664 | E37: 45664 | F37: 45666 | G37: PIX ITAU ALV | H37: 50 | I37: 50 | J37: 1237 | K37: 3 | L37: 01.01.01 | M37: Vendas | N37: B | P37: 2 | Q37: ITAU ALV | V37: =TEXT(F37,"MMMM") -> janeiro
A38: P1421/1 | C38: WENDER CODIJEANS | D38: 45664 | E38: 45664 | F38: 45666 | G38: PIX ITAU ALV | H38: 50 | I38: 50 | J38: 1238 | K38: 3 | L38: 01.01.01 | M38: Vendas | N38: B | P38: 2 | Q38: ITAU ALV | V38: =TEXT(F38,"MMMM") -> janeiro
A39: P1427/1 | C39: BORGES CODI JEANS | D39: 45664 | E39: 45664 | F39: 45666 | G39: PIX ITAU ALV | H39: 55 | I39: 55 | J39: 1239 | K39: 3 | L39: 01.01.01 | M39: Vendas | N39: B | P39: 2 | Q39: ITAU ALV | V39: =TEXT(F39,"MMMM") -> janeiro
A40: P1459/1 | C40: DELVA CODI | D40: 45664 | E40: 45664 | F40: 45666 | G40: PIX ITAU ALV | H40: 85 | I40: 85 | J40: 1240 | K40: 3 | L40: 01.01.01 | M40: Vendas | N40: B | P40: 2 | Q40: ITAU ALV | V40: =TEXT(F40,"MMMM") -> janeiro
A41: P1497/1 | B41: 23.728.778/0001-17 | C41: ERREJOTA OUTLET-DOUGLAS OLIVEIRA DOS SANTOS 14516832780 | D41: 45665 | E41: 45695 | F41: 45666 | G41: BOLETO BANCÁRIO | H41: 9195 | I41: 9195 | J41: 1241 | K41: 3 | L41: 01.01.01 | M41: Vendas | N41: B | P41: 2 | Q41: ITAU ALV | V41: =TEXT(F41,"MMMM") -> janeiro
A42: P1498/1 | B42: 54.186.406/0001-30 | C42: GABRIEL BENTO DE SOUZA | D42: 45665 | E42: 45665 | F42: 45666 | G42: PIX ITAU ALV | H42: 940 | I42: 940 | J42: 1242 | K42: 3 | L42: 01.01.01 | M42: Vendas | N42: B | P42: 2 | Q42: ITAU ALV | V42: =TEXT(F42,"MMMM") -> janeiro
A43: P1496/ | B43: 609.659.591-04 | C43: JOSE WILSON DOS SANTOS | D43: 45665 | E43: 45665 | F43: 45666 | G43: BOLETO BANCÁRIO | H43: 2000 | I43: 2000 | J43: 1243 | K43: 3 | L43: 01.01.01 | M43: Vendas | N43: B | P43: 2 | Q43: ITAU ALV | V43: =TEXT(F43,"MMMM") -> janeiro
A44: P1496/ | B44: 609.659.591-04 | C44: JOSE WILSON DOS SANTOS | D44: 45665 | E44: 45665 | F44: 45666 | G44: PIX ITAU ALV | H44: 210 | I44: 210 | J44: 1243 | K44: 3 | L44: 01.01.01 | M44: Vendas | N44: B | P44: 2 | Q44: ITAU ALV | V44: =TEXT(F44,"MMMM") -> janeiro
A45: P1495/1 | B45: 39.260.360/0001-68 | C45: JESSICA AGUIAR DA SILVA | D45: 45665 | E45: 45695 | F45: 45666 | G45: BOLETO BANCÁRIO | H45: 646.67 | I45: 646.67 | J45: 1244 | K45: 3 | L45: 01.01.01 | M45: Vendas | N45: B | P45: 2 | Q45: ITAU ALV | V45: =TEXT(F45,"MMMM") -> janeiro
A46: P1495/2 | B46: 39.260.360/0001-68 | C46: JESSICA AGUIAR DA SILVA | D46: 45665 | E46: 45725 | F46: 45666 | G46: BOLETO BANCÁRIO | H46: 646.67 | I46: 646.67 | J46: 1244 | K46: 3 | L46: 01.01.01 | M46: Vendas | N46: B | P46: 2 | Q46: ITAU ALV | V46: =TEXT(F46,"MMMM") -> janeiro
A47: P1495/3 | B47: 39.260.360/0001-68 | C47: JESSICA AGUIAR DA SILVA | D47: 45665 | E47: 45755 | F47: 45666 | G47: BOLETO BANCÁRIO | H47: 646.66 | I47: 646.66 | J47: 1244 | K47: 3 | L47: 01.01.01 | M47: Vendas | N47: B | P47: 2 | Q47: ITAU ALV | V47: =TEXT(F47,"MMMM") -> janeiro
A48: P995/1 | C48: NOME DO CLIENTE É OBRIGATÓRIO | D48: 45664 | E48: 45664 | F48: 45666 | G48: PIX ITAU ALV | H48: 465 | I48: 465 | J48: 890 | K48: 3 | L48: 01.01.01 | M48: Vendas | N48: B | P48: 2 | Q48: ITAU ALV | V48: =TEXT(F48,"MMMM") -> janeiro
A49: P996/1 | C49: GENIVALDO | D49: 45664 | E49: 45664 | F49: 45666 | G49: PIX ITAU ALV | H49: 160 | I49: 160 | J49: 891 | K49: 3 | L49: 01.01.01 | M49: Vendas | N49: B | P49: 2 | Q49: ITAU ALV | V49: =TEXT(F49,"MMMM") -> janeiro
A50: P997/1 | C50: EMERSON JAMES RODRIGUES SOARES | D50: 45664 | E50: 45664 | F50: 45666 | G50: PIX ITAU ALV | H50: 910 | I50: 910 | J50: 892 | K50: 3 | L50: 01.01.01 | M50: Vendas | N50: B | P50: 2 | Q50: ITAU ALV | V50: =TEXT(F50,"MMMM") -> janeiro
A51: P827/1 | C51: FUNCIONARIOS | D51: 45664 | E51: 45664 | F51: 45666 | G51: PIX ITAU ALV | H51: 125 | I51: 125 | J51: 893 | K51: 3 | L51: 01.01.01 | M51: Vendas | N51: B | P51: 2 | Q51: ITAU ALV | V51: =TEXT(F51,"MMMM") -> janeiro
A52: P967/1 | C52: FUNCIONARIOS | D52: 45664 | E52: 45664 | F52: 45666 | G52: PIX ITAU ALV | H52: 55 | I52: 55 | J52: 894 | K52: 3 | L52: 01.01.01 | M52: Vendas | N52: B | P52: 2 | Q52: ITAU ALV | V52: =TEXT(F52,"MMMM") -> janeiro
A53: P999/1 | C53: NOME DO CLIENTE É OBRIGATÓRIO | D53: 45666 | E53: 45666 | F53: 45666 | G53: PIX ITAU ALV | H53: 320 | I53: 320 | J53: 895 | K53: 3 | L53: 01.01.01 | M53: Vendas | N53: B | P53: 2 | Q53: ITAU ALV | V53: =TEXT(F53,"MMMM") -> janeiro
A54: P992/1 | C54: NOME DO CLIENTE É OBRIGATÓRIO | D54: 45659 | E54: 45689 | F54: 45666 | G54: CARTÃO CRÉDITO | H54: 960 | I54: 912.58 | J54: 887 | K54: 3 | L54: 01.01.01 | M54: Vendas | N54: B | P54: 2 | Q54: ITAU ALV | V54: =TEXT(F54,"MMMM") -> janeiro
A55: P994/ | C55: NOME DO CLIENTE É OBRIGATÓRIO | D55: 45661 | E55: 45661 | F55: 45666 | G55: PIX ITAU ALV | H55: 160 | I55: 160 | J55: 888 | K55: 3 | L55: 01.01.01 | M55: Vendas | N55: B | P55: 2 | Q55: ITAU ALV | V55: =TEXT(F55,"MMMM") -> janeiro
A56: P994/ | C56: NOME DO CLIENTE É OBRIGATÓRIO | D56: 45661 | E56: 45661 | F56: 45666 | G56: CARTÃO CRÉDITO | H56: 160 | I56: 153.22 | J56: 888 | K56: 3 | L56: 01.01.01 | M56: Vendas | N56: B | P56: 2 | Q56: ITAU ALV | V56: =TEXT(F56,"MMMM") -> janeiro
A57: P990/1 | C57: NOME DO CLIENTE É OBRIGATÓRIO | D57: 45659 | E57: 45659 | F57: 45666 | G57: CARTÃO DÉBITO | H57: 259 | I57: 256.57 | J57: 885 | K57: 3 | L57: 01.01.01 | M57: Vendas | N57: B | P57: 2 | Q57: ITAU ALV | V57: =TEXT(F57,"MMMM") -> janeiro
A58: P1010/1 | C58: NOME DO CLIENTE É OBRIGATÓRIO | D58: 45674 | E58: 45674 | F58: 45674 | G58: DINHEIRO | H58: 360 | I58: 360 | J58: 907 | K58: 3 | L58: 01.01.01 | M58: Vendas | N58: B | P58: 1156 | Q58: CODI.COM - LOJA BASIC 2 | V58: =TEXT(F58,"MMMM") -> janeiro
A59: P1011/1 | C59: NOME DO CLIENTE É OBRIGATÓRIO | D59: 45675 | E59: 45675 | F59: 45675 | G59: DINHEIRO | H59: 280 | I59: 280 | J59: 909 | K59: 3 | L59: 01.01.01 | M59: Vendas | N59: B | P59: 1156 | Q59: CODI.COM - LOJA BASIC 2 | V59: =TEXT(F59,"MMMM") -> janeiro
A60: P1505/1 | B60: 42.131.039/0001-98 | C60: SIR JACK COMERCIO DE ARTIGOS DO VESTUARIO LTDA | D60: 45666 | E60: 45666 | F60: 45678 | G60: PIX ITAU ALV | H60: 2640 | I60: 2640 | J60: 1250 | K60: 3 | L60: 01.01.01 | M60: Vendas | N60: B | P60: 2 | Q60: ITAU ALV | V60: =TEXT(F60,"MMMM") -> janeiro
A61: P1503/1 | B61: 38.119.487/0001-07 | C61: LUANA D PAULA SILVA MOREIRA 06029743139 | D61: 45667 | E61: 45667 | F61: 45678 | G61: PIX ITAU ALV | H61: 600 | I61: 600 | J61: 1251 | K61: 3 | L61: 01.01.01 | M61: Vendas | N61: B | P61: 2 | Q61: ITAU ALV | V61: =TEXT(F61,"MMMM") -> janeiro
A62: P1506/1 | B62: 42.132.463/0001-57 | C62: ALEXANDRE DE OLIVEIRA BATISTA 01460967542 | D62: 45667 | E62: 45667 | F62: 45678 | G62: PIX ITAU ALV | H62: 1110 | I62: 1110 | J62: 1252 | K62: 3 | L62: 01.01.01 | M62: Vendas | N62: B | P62: 2 | Q62: ITAU ALV | V62: =TEXT(F62,"MMMM") -> janeiro
A63: P1501/1 | B63: 47.442.972/0001-08 | C63: ROSINALDO DE ARAUJO BRAZ | D63: 45667 | E63: 45667 | F63: 45678 | G63: PIX ITAU ALV | H63: 1320 | I63: 1320 | J63: 1253 | K63: 3 | L63: 01.01.01 | M63: Vendas | N63: B | P63: 2 | Q63: ITAU ALV | V63: =TEXT(F63,"MMMM") -> janeiro
A64: P1500/1 | B64: 428.643.748-54 | C64: LUCAS IDALGO CHIEREGATO | D64: 45667 | E64: 45667 | F64: 45678 | G64: PIX ITAU ALV | H64: 5270 | I64: 5270 | J64: 1254 | K64: 3 | L64: 01.01.01 | M64: Vendas | N64: B | P64: 2 | Q64: ITAU ALV | V64: =TEXT(F64,"MMMM") -> janeiro
A65: P1507/1 | B65: 19.191.570/0001-34 | C65: CLEUSA MARINI GAMBA | D65: 45667 | E65: 45667 | F65: 45678 | G65: TRANSFERÊNCIA | H65: 1455 | I65: 1455 | J65: 1255 | K65: 3 | L65: 01.01.01 | M65: Vendas | N65: B | P65: 2 | Q65: ITAU ALV | R65: FRETE JADLOG | V65: =TEXT(F65,"MMMM") -> janeiro
A66: P1509/1 | B66: 44.138.173/0001-46 | C66: GUILHERME HENRIQUE OLIVEIRA MAGALHAES | D66: 45667 | E66: 45667 | F66: 45678 | G66: PIX ITAU ALV | H66: 1095 | I66: 1095 | J66: 1256 | K66: 3 | L66: 01.01.01 | M66: Vendas | N66: B | P66: 2 | Q66: ITAU ALV | V66: =TEXT(F66,"MMMM") -> janeiro
A67: P1508/1 | B67: 31.963.913/0001-37 | C67: INVICTA CAMISARIA LTDA | D67: 45670 | E67: 45670 | F67: 45678 | G67: PIX ITAU ALV | H67: 3000 | I67: 3000 | J67: 1258 | K67: 3 | L67: 01.01.01 | M67: Vendas | N67: B | P67: 2 | Q67: ITAU ALV | V67: =TEXT(F67,"MMMM") -> janeiro
A68: P1513/1 | B68: 42.554.243/0001-11 | C68: CLAUDIR JOSE BACKES JUNIOR 02043336010 | D68: 45670 | E68: 45670 | F68: 45678 | G68: PIX ITAU ALV | H68: 1235 | I68: 1235 | J68: 1259 | K68: 3 | L68: 01.01.01 | M68: Vendas | N68: B | P68: 2 | Q68: ITAU ALV | V68: =TEXT(F68,"MMMM") -> janeiro
A69: P1512/ | B69: 42.176.954/0001-08 | C69: JOSE AIRTON DE OLIVEIRA | D69: 45670 | E69: 45670 | F69: 45678 | G69: PIX ITAU ALV | H69: 105 | I69: 105 | J69: 1260 | K69: 3 | L69: 01.01.01 | M69: Vendas | N69: B | P69: 2 | Q69: ITAU ALV | V69: =TEXT(F69,"MMMM") -> janeiro
A70: P1512/1 | B70: 42.176.954/0001-08 | C70: JOSE AIRTON DE OLIVEIRA | D70: 45670 | E70: 45670 | F70: 45678 | G70: LINK REDE | H70: 459 | I70: 459 | J70: 1260 | K70: 3 | L70: 01.01.01 | M70: Vendas | N70: B | P70: 2 | Q70: ITAU ALV | V70: =TEXT(F70,"MMMM") -> janeiro
A71: P1512/2 | B71: 42.176.954/0001-08 | C71: JOSE AIRTON DE OLIVEIRA | D71: 45670 | E71: 45700 | F71: 45678 | G71: LINK REDE | H71: 459 | I71: 459 | J71: 1260 | K71: 3 | L71: 01.01.01 | M71: Vendas | N71: B | P71: 2 | Q71: ITAU ALV | V71: =TEXT(F71,"MMMM") -> janeiro
A72: P1512/3 | B72: 42.176.954/0001-08 | C72: JOSE AIRTON DE OLIVEIRA | D72: 45670 | E72: 45730 | F72: 45678 | G72: LINK REDE | H72: 459 | I72: 459 | J72: 1260 | K72: 3 | L72: 01.01.01 | M72: Vendas | N72: B | P72: 2 | Q72: ITAU ALV | V72: =TEXT(F72,"MMMM") -> janeiro
A73: P1512/4 | B73: 42.176.954/0001-08 | C73: JOSE AIRTON DE OLIVEIRA | D73: 45670 | E73: 45760 | F73: 45678 | G73: LINK REDE | H73: 459 | I73: 459 | J73: 1260 | K73: 3 | L73: 01.01.01 | M73: Vendas | N73: B | P73: 2 | Q73: ITAU ALV | V73: =TEXT(F73,"MMMM") -> janeiro
A74: P1512/5 | B74: 42.176.954/0001-08 | C74: JOSE AIRTON DE OLIVEIRA | D74: 45670 | E74: 45790 | F74: 45678 | G74: LINK REDE | H74: 459 | I74: 459 | J74: 1260 | K74: 3 | L74: 01.01.01 | M74: Vendas | N74: B | P74: 2 | Q74: ITAU ALV | V74: =TEXT(F74,"MMMM") -> janeiro
A75: P1514/1 | B75: 09.372.678/0001-70 | C75: JOEL VIVEIRO DE ABREU | D75: 45671 | E75: 45671 | F75: 45678 | G75: PIX ITAU ALV | H75: 1585 | I75: 1585 | J75: 1261 | K75: 3 | L75: 01.01.01 | M75: Vendas | N75: B | P75: 2 | Q75: ITAU ALV | V75: =TEXT(F75,"MMMM") -> janeiro
A76: P1515/ | B76: 37.269.994/0001-56 | C76: FRANCIELI APARECIDA DUTRA | D76: 45671 | E76: 45671 | F76: 45678 | G76: PIX ITAU ALV | H76: 100 | I76: 100 | J76: 1262 | K76: 3 | L76: 01.01.01 | M76: Vendas | N76: B | P76: 2 | Q76: ITAU ALV | V76: =TEXT(F76,"MMMM") -> janeiro
A77: P1517/ | B77: 28.423.209/0001-87 | C77: LUCILENE ANTUNES DE SOUZA 03481767919 | D77: 45672 | E77: 45672 | F77: 45678 | G77: PIX ITAU ALV | H77: 80 | I77: 80 | J77: 1264 | K77: 3 | L77: 01.01.01 | M77: Vendas | N77: B | P77: 2 | Q77: ITAU ALV | V77: =TEXT(F77,"MMMM") -> janeiro
... A88: P1115/2 | B88: 28.444.314/0001-00 | C88: JOÃO CARLOS RODRIGUES | D88: 45615 | E88: 45675 | F88: 45678 | G88: BOLETO BANCÁRIO | H88: 1295 | I88: 1295 | J88: 907 | K88: 3 | L88: 01.01.01 | M88: Vendas | N88: B | P88: 2 | Q88: ITAU ALV | V88: =TEXT(F88,"MMMM") -> janeiro
A89: P1519/1 | C89: GRINGO GRIFFES | D89: 45674 | E89: 45674 | F89: 45678 | G89: PIX ITAU ALV | H89: 1160 | I89: 1160 | J89: 1273 | K89: 3 | L89: 01.01.01 | M89: Vendas | N89: B | P89: 2 | Q89: ITAU ALV | V89: =TEXT(F89,"MMMM") -> janeiro
A90: P1532/1 | B90: 073.979.141-95 | C90: GABRIEL ROCHA DANGONI | D90: 45677 | E90: 45677 | F90: 45678 | G90: PIX ITAU ALV | H90: 935 | I90: 935 | J90: 1274 | K90: 3 | L90: 01.01.01 | M90: Vendas | N90: B | P90: 2 | Q90: ITAU ALV | V90: =TEXT(F90,"MMMM") -> janeiro
A91: P1533/1 | B91: 37.876.261/0001-80 | C91: CARLOS ALBERTO COSTA JUNIOR | D91: 45678 | E91: 45678 | F91: 45678 | G91: PIX ITAU ALV | H91: 1285 | I91: 1285 | J91: 1276 | K91: 3 | L91: 01.01.01 | M91: Vendas | N91: B | P91: 2 | Q91: ITAU ALV | V91: =TEXT(F91,"MMMM") -> janeiro
A92: P1009/1 | B92: 038.181.475-07 | C92: JOSELANIA CONCEICAO NOVAIS | D92: 45678 | E92: 45678 | F92: 45678 | G92: PIX ITAU ALV | H92: 1220 | I92: 1220 | J92: 910 | K92: 3 | L92: 01.01.01 | M92: Vendas | N92: B | P92: 2 | Q92: ITAU ALV | R92: 1157 e 1159 (brindes referente a ação de completar 10 vendas em cada cartão)LIBERADO PELA ADRIANA | V92: =TEXT(F92,"MMMM") -> janeiro
A93: P1013/1 | B93: 28.137.293/0001-72 | C93: ROSIBERTO DOS SANTOS FERREIRA 88756947291 | D93: 45675 | E93: 45675 | F93: 45678 | G93: PIX ITAU ALV | H93: 640 | I93: 640 | J93: 908 | K93: 3 | L93: 01.01.01 | M93: Vendas | N93: B | P93: 2 | Q93: ITAU ALV | V93: =TEXT(F93,"MMMM") -> janeiro
A94: P1002/1 | C94: SENYN | D94: 45666 | E94: 45666 | F94: 45678 | G94: PIX ITAU ALV | H94: 80 | I94: 80 | J94: 896 | K94: 3 | L94: 01.01.01 | M94: Vendas | N94: B | P94: 2 | Q94: ITAU ALV | V94: =TEXT(F94,"MMMM") -> janeiro
A95: P1001/1 | C95: NOME DO CLIENTE É OBRIGATÓRIO | D95: 45666 | E95: 45666 | F95: 45678 | G95: PIX ITAU ALV | H95: 160 | I95: 160 | J95: 897 | K95: 3 | L95: 01.01.01 | M95: Vendas | N95: B | P95: 2 | Q95: ITAU ALV | V95: =TEXT(F95,"MMMM") -> janeiro
A96: P1005/1 | C96: NOME DO CLIENTE É OBRIGATÓRIO | D96: 45667 | E96: 45697 | F96: 45678 | G96: CARTÃO CRÉDITO | H96: 280 | I96: 271.91 | J96: 898 | K96: 3 | L96: 01.01.01 | M96: Vendas | N96: B | P96: 2 | Q96: ITAU ALV | V96: =TEXT(F96,"MMMM") -> janeiro
A97: P1004/1 | C97: NOME DO CLIENTE É OBRIGATÓRIO | D97: 45667 | E97: 45667 | F97: 45678 | G97: PIX ITAU ALV | H97: 310 | I97: 310 | J97: 899 | K97: 3 | L97: 01.01.01 | M97: Vendas | N97: B | P97: 2 | Q97: ITAU ALV | V97: =TEXT(F97,"MMMM") -> janeiro
A98: P1003/1 | C98: NOME DO CLIENTE É OBRIGATÓRIO | D98: 45667 | E98: 45697 | F98: 45678 | G98: CARTÃO CRÉDITO | H98: 160 | I98: 155.38 | J98: 900 | K98: 3 | L98: 01.01.01 | M98: Vendas | N98: B | P98: 2 | Q98: ITAU ALV | V98: =TEXT(F98,"MMMM") -> janeiro
A99: P1006/1 | C99: NOME DO CLIENTE É OBRIGATÓRIO | D99: 45668 | E99: 45668 | F99: 45678 | G99: CARTÃO CRÉDITO | H99: 160 | I99: 155.38 | J99: 901 | K99: 3 | L99: 01.01.01 | M99: Vendas | N99: B | P99: 2 | Q99: ITAU ALV | V99: =TEXT(F99,"MMMM") -> janeiro
A100: P963/1 | C100: ALEX AIRES | D100: 45671 | E100: 45671 | F100: 45678 | G100: PIX ITAU ALV | H100: 120 | I100: 120 | J100: 902 | K100: 3 | L100: 01.01.01 | M100: Vendas | N100: B | P100: 2 | Q100: ITAU ALV | V100: =TEXT(F100,"MMMM") -> janeiro
A101: P971/1 | C101: ALEX AIRES | D101: 45671 | E101: 45671 | F101: 45678 | G101: PIX ITAU ALV | H101: 85 | I101: 85 | J101: 903 | K101: 3 | L101: 01.01.01 | M101: Vendas | N101: B | P101: 2 | Q101: ITAU ALV | V101: =TEXT(F101,"MMMM") -> janeiro
A102: P1000/1 | C102: ALEX AIRES | D102: 45671 | E102: 45671 | F102: 45678 | G102: PIX ITAU ALV | H102: 85 | I102: 85 | J102: 904 | K102: 3 | L102: 01.01.01 | M102: Vendas | N102: B | P102: 2 | Q102: ITAU ALV | V102: =TEXT(F102,"MMMM") -> janeiro
A103: P987/1 | C103: ALEX AIRES | D103: 45671 | E103: 45671 | F103: 45678 | G103: PIX ITAU ALV | H103: 10 | I103: 10 | J103: 905 | K103: 3 | L103: 01.01.01 | M103: Vendas | N103: B | P103: 2 | Q103: ITAU ALV | V103: =TEXT(F103,"MMMM") -> janeiro
A104: P1537/1 | C104: THIAGO/CLEITON | D104: 45678 | E104: 45678 | F104: 45680 | G104: PIX ITAU ALV | H104: 165 | I104: 165 | J104: 1277 | K104: 3 | L104: 01.01.01 | M104: Vendas | N104: B | P104: 2 | Q104: ITAU ALV | V104: =TEXT(F104,"MMMM") -> janeiro
A105: P1536/1 | B105: 109.932.207-38 | C105: SITE FRANCIELLO BOLSONI | D105: 45678 | E105: 45678 | F105: 45680 | G105: LINK REDE | H105: 450 | I105: 430.92 | J105: 1278 | K105: 3 | L105: 01.01.01 | M105: Vendas | N105: B | P105: 2 | Q105: ITAU ALV | R105: DESCONTO DEVIDO Á PROMOÇÃO DO SITE valor autorizado por daniel | V105: =TEXT(F105,"MMMM") -> janeiro
A106: P1535/1 | B106: 57.725.548/0001-16 | C106: ALCINDO FERREIRA SOARES | D106: 45680 | E106: 45680 | F106: 45680 | G106: PIX ITAU ALV | H106: 1330 | I106: 1330 | J106: 1279 | K106: 3 | L106: 01.01.01 | M106: Vendas | N106: B | P106: 2 | Q106: ITAU ALV | V106: =TEXT(F106,"MMMM") -> janeiro
A107: P1545/1 | B107: 48.095.856/0001-14 | C107: ESITON BARROSO | D107: 45680 | E107: 45680 | F107: 45680 | G107: PIX ITAU ALV | H107: 840 | I107: 840 | J107: 1280 | K107: 3 | L107: 01.01.01 | M107: Vendas | N107: B | P107: 2 | Q107: ITAU ALV | V107: =TEXT(F107,"MMMM") -> janeiro
A108: P1543/1 | B108: 30.451.616/0001-40 | C108: R T DO NASCIMENTO | D108: 45680 | E108: 45680 | F108: 45680 | G108: PIX ITAU ALV | H108: 1200 | I108: 1200 | J108: 1281 | K108: 3 | L108: 01.01.01 | M108: Vendas | N108: B | P108: 2 | Q108: ITAU ALV | V108: =TEXT(F108,"MMMM") -> janeiro
A109: P1530/1 | B109: 37.017.526/0001-94 | C109: LUXO URBANO ARAUCARIA PR LTDA | D109: 45677 | E109: 45707 | F109: 45680 | G109: BOLETO BANCÁRIO | H109: 1760 | I109: 1760 | J109: 1275 | K109: 3 | L109: 01.01.01 | M109: Vendas | N109: B | P109: 2 | Q109: ITAU ALV | V109: =TEXT(F109,"MMMM") -> janeiro
A110: P1530/2 | B110: 37.017.526/0001-94 | C110: LUXO URBANO ARAUCARIA PR LTDA | D110: 45677 | E110: 45737 | F110: 45680 | G110: BOLETO BANCÁRIO | H110: 1760 | I110: 1760 | J110: 1275 | K110: 3 | L110: 01.01.01 | M110: Vendas | N110: B | P110: 2 | Q110: ITAU ALV | V110: =TEXT(F110,"MMMM") -> janeiro
A111: P1530/3 | B111: 37.017.526/0001-94 | C111: LUXO URBANO ARAUCARIA PR LTDA | D111: 45677 | E111: 45767 | F111: 45680 | G111: BOLETO BANCÁRIO | H111: 1760 | I111: 1760 | J111: 1275 | K111: 3 | L111: 01.01.01 | M111: Vendas | N111: B | P111: 2 | Q111: ITAU ALV | V111: =TEXT(F111,"MMMM") -> janeiro
A112: P1529/1 | B112: 45.947.332/0001-16 | C112: TINDICO GRIFF LTDA | D112: 45674 | E112: 45674 | F112: 45680 | G112: PIX ITAU ALV | H112: 3440 | I112: 3440 | J112: 1272 | K112: 3 | L112: 01.01.01 | M112: Vendas | N112: B | P112: 2 | Q112: ITAU ALV | V112: =TEXT(F112,"MMMM") -> janeiro
...

Sheet Planilha3

Sheet DFC
A1: TIPO | B1: PLANO | C1: JULHO | D1: AGOSTO | E1: SETEMBRO | F1: OUTUBRO | G1: NOVEMBRO | H1: DEZEMBRO
A2: RECEITA | B2: RECEITA | C2: =SUMIFS('CONTAS A RECEBER'!$I:$I,'CONTAS A RECEBER'!$V:$V,DFC!C$1) -> 0 | D2: =SUMIFS('CONTAS A RECEBER'!$I:$I,'CONTAS A RECEBER'!$V:$V,DFC!D$1) -> 0 | E2: =SUMIFS('CONTAS A RECEBER'!$I:$I,'CONTAS A RECEBER'!$V:$V,DFC!E$1) -> 0 | F2: =SUMIFS('CONTAS A RECEBER'!$I:$I,'CONTAS A RECEBER'!$V:$V,DFC!F$1) -> 0 | G2: =SUMIFS('CONTAS A RECEBER'!$I:$I,'CONTAS A RECEBER'!$V:$V,DFC!G$1) -> 0 | H2: =SUMIFS('CONTAS A RECEBER'!$I:$I,'CONTAS A RECEBER'!$V:$V,DFC!H$1) -> 0
A3: DESPESAS | B3: Tecidos | C3: =SUMIFS('CONTAS A PAGAR'!$N:$N,'CONTAS A PAGAR'!$S:$S,$B3,'CONTAS A PAGAR'!$Z:$Z,DFC!C$1) -> 0 | D3: =SUMIFS('CONTAS A PAGAR'!$N:$N,'CONTAS A PAGAR'!$S:$S,$B3,'CONTAS A PAGAR'!$Z:$Z,DFC!D$1) -> 0 | E3: =SUMIFS('CONTAS A PAGAR'!$N:$N,'CONTAS A PAGAR'!$S:$S,$B3,'CONTAS A PAGAR'!$Z:$Z,DFC!E$1) -> 0 | F3: =SUMIFS('CONTAS A PAGAR'!$N:$N,'CONTAS A PAGAR'!$S:$S,$B3,'CONTAS A PAGAR'!$Z:$Z,DFC!F$1) -> 0 | G3: =SUMIFS('CONTAS A PAGAR'!$N:$N,'CONTAS A PAGAR'!$S:$S,$B3,'CONTAS A PAGAR'!$Z:$Z,DFC!G$1) -> 0 | H3: =SUMIFS('CONTAS A PAGAR'!$N:$N,'CONTAS A PAGAR'!$S:$S,$B3,'CONTAS A PAGAR'!$Z:$Z,DFC!H$1) -> 0
A4: DESPESAS | B4: Lavanderia | C4: =SUMIFS('CONTAS A PAGAR'!$N:$N,'CONTAS A PAGAR'!$S:$S,$B4,'CONTAS A PAGAR'!$Z:$Z,DFC!C$1) -> 0 | D4: =SUMIFS('CONTAS A PAGAR'!$N:$N,'CONTAS A PAGAR'!$S:$S,$B4,'CONTAS A PAGAR'!$Z:$Z,DFC!D$1) -> 0 | E4: =SUMIFS('CONTAS A PAGAR'!$N:$N,'CONTAS A PAGAR'!$S:$S,$B4,'CONTAS A PAGAR'!$Z:$Z,DFC!E$1) -> 0 | F4: =SUMIFS('CONTAS A PAGAR'!$N:$N,'CONTAS A PAGAR'!$S:$S,$B4,'CONTAS A PAGAR'!$Z:$Z,DFC!F$1) -> 0 | G4: =SUMIFS('CONTAS A PAGAR'!$N:$N,'CONTAS A PAGAR'!$S:$S,$B4,'CONTAS A PAGAR'!$Z:$Z,DFC!G$1) -> 0 | H4: =SUMIFS('CONTAS A PAGAR'!$N:$N,'CONTAS A PAGAR'!$S:$S,$B4,'CONTAS A PAGAR'!$Z:$Z,DFC!H$1) -> 0
A5: DESPESAS | B5: Travete | C5: =SUMIFS('CONTAS A PAGAR'!$N:$N,'CONTAS A PAGAR'!$S:$S,$B5,'CONTAS A PAGAR'!$Z:$Z,DFC!C$1) -> 0 | D5: =SUMIFS('CONTAS A PAGAR'!$N:$N,'CONTAS A PAGAR'!$S:$S,$B5,'CONTAS A PAGAR'!$Z:$Z,DFC!D$1) -> 0 | E5: =SUMIFS('CONTAS A PAGAR'!$N:$N,'CONTAS A PAGAR'!$S:$S,$B5,'CONTAS A PAGAR'!$Z:$Z,DFC!E$1) -> 0 | F5: =SUMIFS('CONTAS A PAGAR'!$N:$N,'CONTAS A PAGAR'!$S:$S,$B5,'CONTAS A PAGAR'!$Z:$Z,DFC!F$1) -> 0 | G5: =SUMIFS('CONTAS A PAGAR'!$N:$N,'CONTAS A PAGAR'!$S:$S,$B5,'CONTAS A PAGAR'!$Z:$Z,DFC!G$1) -> 0 | H5: =SUMIFS('CONTAS A PAGAR'!$N:$N,'CONTAS A PAGAR'!$S:$S,$B5,'CONTAS A PAGAR'!$Z:$Z,DFC!H$1) -> 0
A6: DESPESAS | B6: Facção | C6: =SUMIFS('CONTAS A PAGAR'!$N:$N,'CONTAS A PAGAR'!$S:$S,$B6,'CONTAS A PAGAR'!$Z:$Z,DFC!C$1) -> 0 | D6: =SUMIFS('CONTAS A PAGAR'!$N:$N,'CONTAS A PAGAR'!$S:$S,$B6,'CONTAS A PAGAR'!$Z:$Z,DFC!D$1) -> 0 | E6: =SUMIFS('CONTAS A PAGAR'!$N:$N,'CONTAS A PAGAR'!$S:$S,$B6,'CONTAS A PAGAR'!$Z:$Z,DFC!E$1) -> 0 | F6: =SUMIFS('CONTAS A PAGAR'!$N:$N,'CONTAS A PAGAR'!$S:$S,$B6,'CONTAS A PAGAR'!$Z:$Z,DFC!F$1) -> 0 | G6: =SUMIFS('CONTAS A PAGAR'!$N:$N,'CONTAS A PAGAR'!$S:$S,$B6,'CONTAS A PAGAR'!$Z:$Z,DFC!G$1) -> 0 | H6: =SUMIFS('CONTAS A PAGAR'!$N:$N,'CONTAS A PAGAR'!$S:$S,$B6,'CONTAS A PAGAR'!$Z:$Z,DFC!H$1) -> 0
A7: DESPESAS | B7: Acabamento Externo | C7: =SUMIFS('CONTAS A PAGAR'!$N:$N,'CONTAS A PAGAR'!$S:$S,$B7,'CONTAS A PAGAR'!$Z:$Z,DFC!C$1) -> 0 | D7: =SUMIFS('CONTAS A PAGAR'!$N:$N,'CONTAS A PAGAR'!$S:$S,$B7,'CONTAS A PAGAR'!$Z:$Z,DFC!D$1) -> 0 | E7: =SUMIFS('CONTAS A PAGAR'!$N:$N,'CONTAS A PAGAR'!$S:$S,$B7,'CONTAS A PAGAR'!$Z:$Z,DFC!E$1) -> 0 | F7: =SUMIFS('CONTAS A PAGAR'!$N:$N,'CONTAS A PAGAR'!$S:$S,$B7,'CONTAS A PAGAR'!$Z:$Z,DFC!F$1) -> 0 | G7: =SUMIFS('CONTAS A PAGAR'!$N:$N,'CONTAS A PAGAR'!$S:$S,$B7,'CONTAS A PAGAR'!$Z:$Z,DFC!G$1) -> 0 | H7: =SUMIFS('CONTAS A PAGAR'!$N:$N,'CONTAS A PAGAR'!$S:$S,$B7,'CONTAS A PAGAR'!$Z:$Z,DFC!H$1) -> 0
A8: DESPESAS | B8: Aviamento | C8: =SUMIFS('CONTAS A PAGAR'!$N:$N,'CONTAS A PAGAR'!$S:$S,$B8,'CONTAS A PAGAR'!$Z:$Z,DFC!C$1) -> 0 | D8: =SUMIFS('CONTAS A PAGAR'!$N:$N,'CONTAS A PAGAR'!$S:$S,$B8,'CONTAS A PAGAR'!$Z:$Z,DFC!D$1) -> 0 | E8: =SUMIFS('CONTAS A PAGAR'!$N:$N,'CONTAS A PAGAR'!$S:$S,$B8,'CONTAS A PAGAR'!$Z:$Z,DFC!E$1) -> 0 | F8: =SUMIFS('CONTAS A PAGAR'!$N:$N,'CONTAS A PAGAR'!$S:$S,$B8,'CONTAS A PAGAR'!$Z:$Z,DFC!F$1) -> 0 | G8: =SUMIFS('CONTAS A PAGAR'!$N:$N,'CONTAS A PAGAR'!$S:$S,$B8,'CONTAS A PAGAR'!$Z:$Z,DFC!G$1) -> 0 | H8: =SUMIFS('CONTAS A PAGAR'!$N:$N,'CONTAS A PAGAR'!$S:$S,$B8,'CONTAS A PAGAR'!$Z:$Z,DFC!H$1) -> 0
A9: DESPESAS | B9: Etiquetas | C9: =SUMIFS('CONTAS A PAGAR'!$N:$N,'CONTAS A PAGAR'!$S:$S,$B9,'CONTAS A PAGAR'!$Z:$Z,DFC!C$1) -> 0 | D9: =SUMIFS('CONTAS A PAGAR'!$N:$N,'CONTAS A PAGAR'!$S:$S,$B9,'CONTAS A PAGAR'!$Z:$Z,DFC!D$1) -> 0 | E9: =SUMIFS('CONTAS A PAGAR'!$N:$N,'CONTAS A PAGAR'!$S:$S,$B9,'CONTAS A PAGAR'!$Z:$Z,DFC!E$1) -> 0 | F9: =SUMIFS('CONTAS A PAGAR'!$N:$N,'CONTAS A PAGAR'!$S:$S,$B9,'CONTAS A PAGAR'!$Z:$Z,DFC!F$1) -> 0 | G9: =SUMIFS('CONTAS A PAGAR'!$N:$N,'CONTAS A PAGAR'!$S:$S,$B9,'CONTAS A PAGAR'!$Z:$Z,DFC!G$1) -> 0 | H9: =SUMIFS('CONTAS A PAGAR'!$N:$N,'CONTAS A PAGAR'!$S:$S,$B9,'CONTAS A PAGAR'!$Z:$Z,DFC!H$1) -> 0
A10: DESPESAS | B10: Bordado Industrial | C10: =SUMIFS('CONTAS A PAGAR'!$N:$N,'CONTAS A PAGAR'!$S:$S,$B10,'CONTAS A PAGAR'!$Z:$Z,DFC!C$1) -> 0 | D10: =SUMIFS('CONTAS A PAGAR'!$N:$N,'CONTAS A PAGAR'!$S:$S,$B10,'CONTAS A PAGAR'!$Z:$Z,DFC!D$1) -> 0 | E10: =SUMIFS('CONTAS A PAGAR'!$N:$N,'CONTAS A PAGAR'!$S:$S,$B10,'CONTAS A PAGAR'!$Z:$Z,DFC!E$1) -> 0 | F10: =SUMIFS('CONTAS A PAGAR'!$N:$N,'CONTAS A PAGAR'!$S:$S,$B10,'CONTAS A PAGAR'!$Z:$Z,DFC!F$1) -> 0 | G10: =SUMIFS('CONTAS A PAGAR'!$N:$N,'CONTAS A PAGAR'!$S:$S,$B10,'CONTAS A PAGAR'!$Z:$Z,DFC!G$1) -> 0 | H10: =SUMIFS('CONTAS A PAGAR'!$N:$N,'CONTAS A PAGAR'!$S:$S,$B10,'CONTAS A PAGAR'!$Z:$Z,DFC!H$1) -> 0
A11: DESPESAS | B11: Embalagens | C11: =SUMIFS('CONTAS A PAGAR'!$N:$N,'CONTAS A PAGAR'!$S:$S,$B11,'CONTAS A PAGAR'!$Z:$Z,DFC!C$1) -> 0 | D11: =SUMIFS('CONTAS A PAGAR'!$N:$N,'CONTAS A PAGAR'!$S:$S,$B11,'CONTAS A PAGAR'!$Z:$Z,DFC!D$1) -> 0 | E11: =SUMIFS('CONTAS A PAGAR'!$N:$N,'CONTAS A PAGAR'!$S:$S,$B11,'CONTAS A PAGAR'!$Z:$Z,DFC!E$1) -> 0 | F11: =SUMIFS('CONTAS A PAGAR'!$N:$N,'CONTAS A PAGAR'!$S:$S,$B11,'CONTAS A PAGAR'!$Z:$Z,DFC!F$1) -> 0 | G11: =SUMIFS('CONTAS A PAGAR'!$N:$N,'CONTAS A PAGAR'!$S:$S,$B11,'CONTAS A PAGAR'!$Z:$Z,DFC!G$1) -> 0 | H11: =SUMIFS('CONTAS A PAGAR'!$N:$N,'CONTAS A PAGAR'!$S:$S,$B11,'CONTAS A PAGAR'!$Z:$Z,DFC!H$1) -> 0
A12: DESPESAS | B12: Criação de Modelos | C12: =SUMIFS('CONTAS A PAGAR'!$N:$N,'CONTAS A PAGAR'!$S:$S,$B12,'CONTAS A PAGAR'!$Z:$Z,DFC!C$1) -> 0 | D12: =SUMIFS('CONTAS A PAGAR'!$N:$N,'CONTAS A PAGAR'!$S:$S,$B12,'CONTAS A PAGAR'!$Z:$Z,DFC!D$1) -> 0 | E12: =SUMIFS('CONTAS A PAGAR'!$N:$N,'CONTAS A PAGAR'!$S:$S,$B12,'CONTAS A PAGAR'!$Z:$Z,DFC!E$1) -> 0 | F12: =SUMIFS('CONTAS A PAGAR'!$N:$N,'CONTAS A PAGAR'!$S:$S,$B12,'CONTAS A PAGAR'!$Z:$Z,DFC!F$1) -> 0 | G12: =SUMIFS('CONTAS A PAGAR'!$N:$N,'CONTAS A PAGAR'!$S:$S,$B12,'CONTAS A PAGAR'!$Z:$Z,DFC!G$1) -> 0 | H12: =SUMIFS('CONTAS A PAGAR'!$N:$N,'CONTAS A PAGAR'!$S:$S,$B12,'CONTAS A PAGAR'!$Z:$Z,DFC!H$1) -> 0
A13: DESPESAS | B13: Salário e Ordenados | C13: =SUMIFS('CONTAS A PAGAR'!$N:$N,'CONTAS A PAGAR'!$S:$S,$B13,'CONTAS A PAGAR'!$Z:$Z,DFC!C$1) -> 0 | D13: =SUMIFS('CONTAS A PAGAR'!$N:$N,'CONTAS A PAGAR'!$S:$S,$B13,'CONTAS A PAGAR'!$Z:$Z,DFC!D$1) -> 0 | E13: =SUMIFS('CONTAS A PAGAR'!$N:$N,'CONTAS A PAGAR'!$S:$S,$B13,'CONTAS A PAGAR'!$Z:$Z,DFC!E$1) -> 0 | F13: =SUMIFS('CONTAS A PAGAR'!$N:$N,'CONTAS A PAGAR'!$S:$S,$B13,'CONTAS A PAGAR'!$Z:$Z,DFC!F$1) -> 0 | G13: =SUMIFS('CONTAS A PAGAR'!$N:$N,'CONTAS A PAGAR'!$S:$S,$B13,'CONTAS A PAGAR'!$Z:$Z,DFC!G$1) -> 0 | H13: =SUMIFS('CONTAS A PAGAR'!$N:$N,'CONTAS A PAGAR'!$S:$S,$B13,'CONTAS A PAGAR'!$Z:$Z,DFC!H$1) -> 0
A14: DESPESAS | B14: Vale Transporte | C14: =SUMIFS('CONTAS A PAGAR'!$N:$N,'CONTAS A PAGAR'!$S:$S,$B14,'CONTAS A PAGAR'!$Z:$Z,DFC!C$1) -> 0 | D14: =SUMIFS('CONTAS A PAGAR'!$N:$N,'CONTAS A PAGAR'!$S:$S,$B14,'CONTAS A PAGAR'!$Z:$Z,DFC!D$1) -> 0 | E14: =SUMIFS('CONTAS A PAGAR'!$N:$N,'CONTAS A PAGAR'!$S:$S,$B14,'CONTAS A PAGAR'!$Z:$Z,DFC!E$1) -> 0 | F14: =SUMIFS('CONTAS A PAGAR'!$N:$N,'CONTAS A PAGAR'!$S:$S,$B14,'CONTAS A PAGAR'!$Z:$Z,DFC!F$1) -> 0 | G14: =SUMIFS('CONTAS A PAGAR'!$N:$N,'CONTAS A PAGAR'!$S:$S,$B14,'CONTAS A PAGAR'!$Z:$Z,DFC!G$1) -> 0 | H14: =SUMIFS('CONTAS A PAGAR'!$N:$N,'CONTAS A PAGAR'!$S:$S,$B14,'CONTAS A PAGAR'!$Z:$Z,DFC!H$1) -> 0
... A64: DESPESAS | B64: Fgts, Gps e Pis | C64: =SUMIFS('CONTAS A PAGAR'!$N:$N,'CONTAS A PAGAR'!$S:$S,$B64,'CONTAS A PAGAR'!$Z:$Z,DFC!C$1) -> 0 | D64: =SUMIFS('CONTAS A PAGAR'!$N:$N,'CONTAS A PAGAR'!$S:$S,$B64,'CONTAS A PAGAR'!$Z:$Z,DFC!D$1) -> 0 | E64: =SUMIFS('CONTAS A PAGAR'!$N:$N,'CONTAS A PAGAR'!$S:$S,$B64,'CONTAS A PAGAR'!$Z:$Z,DFC!E$1) -> 0 | F64: =SUMIFS('CONTAS A PAGAR'!$N:$N,'CONTAS A PAGAR'!$S:$S,$B64,'CONTAS A PAGAR'!$Z:$Z,DFC!F$1) -> 0 | G64: =SUMIFS('CONTAS A PAGAR'!$N:$N,'CONTAS A PAGAR'!$S:$S,$B64,'CONTAS A PAGAR'!$Z:$Z,DFC!G$1) -> 0 | H64: =SUMIFS('CONTAS A PAGAR'!$N:$N,'CONTAS A PAGAR'!$S:$S,$B64,'CONTAS A PAGAR'!$Z:$Z,DFC!H$1) -> 0
A65: DESPESAS | B65: TOTAL | C65: =SUM(C3:C64) -> 0 | D65: =SUM(D3:D64) -> 0 | E65: =SUM(E3:E64) -> 0 | F65: =SUM(F3:F64) -> 0 | G65: =SUM(G3:G64) -> 0 | H65: =SUM(H3:H64) -> 0
A66: DESPESAS | B66: TOTAL | C66: =C2-C65 -> 0 | D66: =D2-D65 -> 0 | E66: =E2-E65 -> 0 | F66: =F2-F65 -> 0 | G66: =G2-G65 -> 0 | H66: =H2-H65 -> 0

Sheet NCG
B3: TITULOS A PAGAR | C3: =SUM(DFC!F66:H66) -> 0
B4: PREVISAO DE RECEITA | C4: =SUM('ANALISE RECEITA'!Q8:Q9) -> 1304401.4
B5: NCG | C5: =SUM(C3:C4) -> 1304401.4

Sheet DIÁRIO
C2: =SUM(C4:C65) -> 1099.88 | D2: =SUM(D4:D65) -> 26353.15 | E2: =SUM(E4:E65) -> 1977 | F2: =SUM(F4:F65) -> 9966.94 | G2: =SUM(G4:G65) -> 9840 | H2: =SUM(H4:H65) -> 29142.04 | I2: =SUM(I4:I65) -> 93710.02 | J2: =SUM(J4:J65) -> 72057.06 | ... T2: =SUM(T4:T65) -> 104415 | U2: =SUM(C2:T2) -> 555298.52
C3: 45944 | D3: 45945 | E3: 45946 | F3: 45947 | G3: 45948 | H3: 45949 | I3: 45950 | J3: 45951 | K3: 45952 | L3: 45953 | M3: 45954 | N3: 45955 | O3: 45956 | P3: 45957 | Q3: 45958 | R3: 45959 | S3: 45960 | T3: 45961 | U3: TOTAL
B4: Tecidos | C4: =SUMIFS('CONTAS A PAGAR'!$N:$N,'CONTAS A PAGAR'!$K:$K,DIÁRIO!C$3,'CONTAS A PAGAR'!$S:$S,DIÁRIO!$B4) -> 0 | D4: =SUMIFS('CONTAS A PAGAR'!$N:$N,'CONTAS A PAGAR'!$K:$K,DIÁRIO!D$3,'CONTAS A PAGAR'!$S:$S,DIÁRIO!$B4) -> 9840 | E4: =SUMIFS('CONTAS A PAGAR'!$N:$N,'CONTAS A PAGAR'!$K:$K,DIÁRIO!E$3,'CONTAS A PAGAR'!$S:$S,DIÁRIO!$B4) -> 0 | F4: =SUMIFS('CONTAS A PAGAR'!$N:$N,'CONTAS A PAGAR'!$K:$K,DIÁRIO!F$3,'CONTAS A PAGAR'!$S:$S,DIÁRIO!$B4) -> 0 | G4: =SUMIFS('CONTAS A PAGAR'!$N:$N,'CONTAS A PAGAR'!$K:$K,DIÁRIO!G$3,'CONTAS A PAGAR'!$S:$S,DIÁRIO!$B4) -> 9840 | H4: =SUMIFS('CONTAS A PAGAR'!$N:$N,'CONTAS A PAGAR'!$K:$K,DIÁRIO!H$3,'CONTAS A PAGAR'!$S:$S,DIÁRIO!$B4) -> 0 | I4: =SUMIFS('CONTAS A PAGAR'!$N:$N,'CONTAS A PAGAR'!$K:$K,DIÁRIO!I$3,'CONTAS A PAGAR'!$S:$S,DIÁRIO!$B4) -> 22248.8 | J4: =SUMIFS('CONTAS A PAGAR'!$N:$N,'CONTAS A PAGAR'!$K:$K,DIÁRIO!J$3,'CONTAS A PAGAR'!$S:$S,DIÁRIO!$B4) -> 9840 | ... T4: =SUMIFS('CONTAS A PAGAR'!$N:$N,'CONTAS A PAGAR'!$K:$K,DIÁRIO!T$3,'CONTAS A PAGAR'!$S:$S,DIÁRIO!$B4) -> 0 | U4: =SUM(C4:T4) -> 95516.31
B5: Lavanderia | C5: =SUMIFS('CONTAS A PAGAR'!$N:$N,'CONTAS A PAGAR'!$K:$K,DIÁRIO!C$3,'CONTAS A PAGAR'!$S:$S,DIÁRIO!$B5) -> 0 | D5: =SUMIFS('CONTAS A PAGAR'!$N:$N,'CONTAS A PAGAR'!$K:$K,DIÁRIO!D$3,'CONTAS A PAGAR'!$S:$S,DIÁRIO!$B5) -> 8710 | E5: =SUMIFS('CONTAS A PAGAR'!$N:$N,'CONTAS A PAGAR'!$K:$K,DIÁRIO!E$3,'CONTAS A PAGAR'!$S:$S,DIÁRIO!$B5) -> 0 | F5: =SUMIFS('CONTAS A PAGAR'!$N:$N,'CONTAS A PAGAR'!$K:$K,DIÁRIO!F$3,'CONTAS A PAGAR'!$S:$S,DIÁRIO!$B5) -> 0 | G5: =SUMIFS('CONTAS A PAGAR'!$N:$N,'CONTAS A PAGAR'!$K:$K,DIÁRIO!G$3,'CONTAS A PAGAR'!$S:$S,DIÁRIO!$B5) -> 0 | H5: =SUMIFS('CONTAS A PAGAR'!$N:$N,'CONTAS A PAGAR'!$K:$K,DIÁRIO!H$3,'CONTAS A PAGAR'!$S:$S,DIÁRIO!$B5) -> 0 | I5: =SUMIFS('CONTAS A PAGAR'!$N:$N,'CONTAS A PAGAR'!$K:$K,DIÁRIO!I$3,'CONTAS A PAGAR'!$S:$S,DIÁRIO!$B5) -> 3620.5 | J5: =SUMIFS('CONTAS A PAGAR'!$N:$N,'CONTAS A PAGAR'!$K:$K,DIÁRIO!J$3,'CONTAS A PAGAR'!$S:$S,DIÁRIO!$B5) -> 0 | ... T5: =SUMIFS('CONTAS A PAGAR'!$N:$N,'CONTAS A PAGAR'!$K:$K,DIÁRIO!T$3,'CONTAS A PAGAR'!$S:$S,DIÁRIO!$B5) -> 0 | U5: =SUM(C5:T5) -> 18760.5
B6: Travete | C6: =SUMIFS('CONTAS A PAGAR'!$N:$N,'CONTAS A PAGAR'!$K:$K,DIÁRIO!C$3,'CONTAS A PAGAR'!$S:$S,DIÁRIO!$B6) -> 0 | D6: =SUMIFS('CONTAS A PAGAR'!$N:$N,'CONTAS A PAGAR'!$K:$K,DIÁRIO!D$3,'CONTAS A PAGAR'!$S:$S,DIÁRIO!$B6) -> 0 | E6: =SUMIFS('CONTAS A PAGAR'!$N:$N,'CONTAS A PAGAR'!$K:$K,DIÁRIO!E$3,'CONTAS A PAGAR'!$S:$S,DIÁRIO!$B6) -> 0 | F6: =SUMIFS('CONTAS A PAGAR'!$N:$N,'CONTAS A PAGAR'!$K:$K,DIÁRIO!F$3,'CONTAS A PAGAR'!$S:$S,DIÁRIO!$B6) -> 0 | G6: =SUMIFS('CONTAS A PAGAR'!$N:$N,'CONTAS A PAGAR'!$K:$K,DIÁRIO!G$3,'CONTAS A PAGAR'!$S:$S,DIÁRIO!$B6) -> 0 | H6: =SUMIFS('CONTAS A PAGAR'!$N:$N,'CONTAS A PAGAR'!$K:$K,DIÁRIO!H$3,'CONTAS A PAGAR'!$S:$S,DIÁRIO!$B6) -> 0 | I6: =SUMIFS('CONTAS A PAGAR'!$N:$N,'CONTAS A PAGAR'!$K:$K,DIÁRIO!I$3,'CONTAS A PAGAR'!$S:$S,DIÁRIO!$B6) -> 881 | J6: =SUMIFS('CONTAS A PAGAR'!$N:$N,'CONTAS A PAGAR'!$K:$K,DIÁRIO!J$3,'CONTAS A PAGAR'!$S:$S,DIÁRIO!$B6) -> 0 | ... T6: =SUMIFS('CONTAS A PAGAR'!$N:$N,'CONTAS A PAGAR'!$K:$K,DIÁRIO!T$3,'CONTAS A PAGAR'!$S:$S,DIÁRIO!$B6) -> 0 | U6: =SUM(C6:T6) -> 881
B7: Facção | C7: =SUMIFS('CONTAS A PAGAR'!$N:$N,'CONTAS A PAGAR'!$K:$K,DIÁRIO!C$3,'CONTAS A PAGAR'!$S:$S,DIÁRIO!$B7) -> 0 | D7: =SUMIFS('CONTAS A PAGAR'!$N:$N,'CONTAS A PAGAR'!$K:$K,DIÁRIO!D$3,'CONTAS A PAGAR'!$S:$S,DIÁRIO!$B7) -> 0 | E7: =SUMIFS('CONTAS A PAGAR'!$N:$N,'CONTAS A PAGAR'!$K:$K,DIÁRIO!E$3,'CONTAS A PAGAR'!$S:$S,DIÁRIO!$B7) -> 0 | F7: =SUMIFS('CONTAS A PAGAR'!$N:$N,'CONTAS A PAGAR'!$K:$K,DIÁRIO!F$3,'CONTAS A PAGAR'!$S:$S,DIÁRIO!$B7) -> 0 | G7: =SUMIFS('CONTAS A PAGAR'!$N:$N,'CONTAS A PAGAR'!$K:$K,DIÁRIO!G$3,'CONTAS A PAGAR'!$S:$S,DIÁRIO!$B7) -> 0 | H7: =SUMIFS('CONTAS A PAGAR'!$N:$N,'CONTAS A PAGAR'!$K:$K,DIÁRIO!H$3,'CONTAS A PAGAR'!$S:$S,DIÁRIO!$B7) -> 0 | I7: =SUMIFS('CONTAS A PAGAR'!$N:$N,'CONTAS A PAGAR'!$K:$K,DIÁRIO!I$3,'CONTAS A PAGAR'!$S:$S,DIÁRIO!$B7) -> 34977.5 | J7: =SUMIFS('CONTAS A PAGAR'!$N:$N,'CONTAS A PAGAR'!$K:$K,DIÁRIO!J$3,'CONTAS A PAGAR'!$S:$S,DIÁRIO!$B7) -> 0 | ... T7: =SUMIFS('CONTAS A PAGAR'!$N:$N,'CONTAS A PAGAR'!$K:$K,DIÁRIO!T$3,'CONTAS A PAGAR'!$S:$S,DIÁRIO!$B7) -> 0 | U7: =SUM(C7:T7) -> 55472
B8: Acabamento Externo | C8: =SUMIFS('CONTAS A PAGAR'!$N:$N,'CONTAS A PAGAR'!$K:$K,DIÁRIO!C$3,'CONTAS A PAGAR'!$S:$S,DIÁRIO!$B8) -> 467.8 | D8: =SUMIFS('CONTAS A PAGAR'!$N:$N,'CONTAS A PAGAR'!$K:$K,DIÁRIO!D$3,'CONTAS A PAGAR'!$S:$S,DIÁRIO!$B8) -> 0 | E8: =SUMIFS('CONTAS A PAGAR'!$N:$N,'CONTAS A PAGAR'!$K:$K,DIÁRIO!E$3,'CONTAS A PAGAR'!$S:$S,DIÁRIO!$B8) -> 0 | F8: =SUMIFS('CONTAS A PAGAR'!$N:$N,'CONTAS A PAGAR'!$K:$K,DIÁRIO!F$3,'CONTAS A PAGAR'!$S:$S,DIÁRIO!$B8) -> 0 | G8: =SUMIFS('CONTAS A PAGAR'!$N:$N,'CONTAS A PAGAR'!$K:$K,DIÁRIO!G$3,'CONTAS A PAGAR'!$S:$S,DIÁRIO!$B8) -> 0 | H8: =SUMIFS('CONTAS A PAGAR'!$N:$N,'CONTAS A PAGAR'!$K:$K,DIÁRIO!H$3,'CONTAS A PAGAR'!$S:$S,DIÁRIO!$B8) -> 0 | I8: =SUMIFS('CONTAS A PAGAR'!$N:$N,'CONTAS A PAGAR'!$K:$K,DIÁRIO!I$3,'CONTAS A PAGAR'!$S:$S,DIÁRIO!$B8) -> 0 | J8: =SUMIFS('CONTAS A PAGAR'!$N:$N,'CONTAS A PAGAR'!$K:$K,DIÁRIO!J$3,'CONTAS A PAGAR'!$S:$S,DIÁRIO!$B8) -> 0 | ... T8: =SUMIFS('CONTAS A PAGAR'!$N:$N,'CONTAS A PAGAR'!$K:$K,DIÁRIO!T$3,'CONTAS A PAGAR'!$S:$S,DIÁRIO!$B8) -> 0 | U8: =SUM(C8:T8) -> 467.8
B9: Aviamento | C9: =SUMIFS('CONTAS A PAGAR'!$N:$N,'CONTAS A PAGAR'!$K:$K,DIÁRIO!C$3,'CONTAS A PAGAR'!$S:$S,DIÁRIO!$B9) -> 0 | D9: =SUMIFS('CONTAS A PAGAR'!$N:$N,'CONTAS A PAGAR'!$K:$K,DIÁRIO!D$3,'CONTAS A PAGAR'!$S:$S,DIÁRIO!$B9) -> 2182.6 | E9: =SUMIFS('CONTAS A PAGAR'!$N:$N,'CONTAS A PAGAR'!$K:$K,DIÁRIO!E$3,'CONTAS A PAGAR'!$S:$S,DIÁRIO!$B9) -> 0 | F9: =SUMIFS('CONTAS A PAGAR'!$N:$N,'CONTAS A PAGAR'!$K:$K,DIÁRIO!F$3,'CONTAS A PAGAR'!$S:$S,DIÁRIO!$B9) -> 0 | G9: =SUMIFS('CONTAS A PAGAR'!$N:$N,'CONTAS A PAGAR'!$K:$K,DIÁRIO!G$3,'CONTAS A PAGAR'!$S:$S,DIÁRIO!$B9) -> 0 | H9: =SUMIFS('CONTAS A PAGAR'!$N:$N,'CONTAS A PAGAR'!$K:$K,DIÁRIO!H$3,'CONTAS A PAGAR'!$S:$S,DIÁRIO!$B9) -> 0 | I9: =SUMIFS('CONTAS A PAGAR'!$N:$N,'CONTAS A PAGAR'!$K:$K,DIÁRIO!I$3,'CONTAS A PAGAR'!$S:$S,DIÁRIO!$B9) -> 0 | J9: =SUMIFS('CONTAS A PAGAR'!$N:$N,'CONTAS A PAGAR'!$K:$K,DIÁRIO!J$3,'CONTAS A PAGAR'!$S:$S,DIÁRIO!$B9) -> 2000 | ... T9: =SUMIFS('CONTAS A PAGAR'!$N:$N,'CONTAS A PAGAR'!$K:$K,DIÁRIO!T$3,'CONTAS A PAGAR'!$S:$S,DIÁRIO!$B9) -> 0 | U9: =SUM(C9:T9) -> 10509.63
B10: Etiquetas | C10: =SUMIFS('CONTAS A PAGAR'!$N:$N,'CONTAS A PAGAR'!$K:$K,DIÁRIO!C$3,'CONTAS A PAGAR'!$S:$S,DIÁRIO!$B10) -> 0 | D10: =SUMIFS('CONTAS A PAGAR'!$N:$N,'CONTAS A PAGAR'!$K:$K,DIÁRIO!D$3,'CONTAS A PAGAR'!$S:$S,DIÁRIO!$B10) -> 0 | E10: =SUMIFS('CONTAS A PAGAR'!$N:$N,'CONTAS A PAGAR'!$K:$K,DIÁRIO!E$3,'CONTAS A PAGAR'!$S:$S,DIÁRIO!$B10) -> 0 | F10: =SUMIFS('CONTAS A PAGAR'!$N:$N,'CONTAS A PAGAR'!$K:$K,DIÁRIO!F$3,'CONTAS A PAGAR'!$S:$S,DIÁRIO!$B10) -> 0 | G10: =SUMIFS('CONTAS A PAGAR'!$N:$N,'CONTAS A PAGAR'!$K:$K,DIÁRIO!G$3,'CONTAS A PAGAR'!$S:$S,DIÁRIO!$B10) -> 0 | H10: =SUMIFS('CONTAS A PAGAR'!$N:$N,'CONTAS A PAGAR'!$K:$K,DIÁRIO!H$3,'CONTAS A PAGAR'!$S:$S,DIÁRIO!$B10) -> 0 | I10: =SUMIFS('CONTAS A PAGAR'!$N:$N,'CONTAS A PAGAR'!$K:$K,DIÁRIO!I$3,'CONTAS A PAGAR'!$S:$S,DIÁRIO!$B10) -> 0 | J10: =SUMIFS('CONTAS A PAGAR'!$N:$N,'CONTAS A PAGAR'!$K:$K,DIÁRIO!J$3,'CONTAS A PAGAR'!$S:$S,DIÁRIO!$B10) -> 89 | ... T10: =SUMIFS('CONTAS A PAGAR'!$N:$N,'CONTAS A PAGAR'!$K:$K,DIÁRIO!T$3,'CONTAS A PAGAR'!$S:$S,DIÁRIO!$B10) -> 0 | U10: =SUM(C10:T10) -> 5383
B11: Bordado Industrial | C11: =SUMIFS('CONTAS A PAGAR'!$N:$N,'CONTAS A PAGAR'!$K:$K,DIÁRIO!C$3,'CONTAS A PAGAR'!$S:$S,DIÁRIO!$B11) -> 0 | D11: =SUMIFS('CONTAS A PAGAR'!$N:$N,'CONTAS A PAGAR'!$K:$K,DIÁRIO!D$3,'CONTAS A PAGAR'!$S:$S,DIÁRIO!$B11) -> 1125 | E11: =SUMIFS('CONTAS A PAGAR'!$N:$N,'CONTAS A PAGAR'!$K:$K,DIÁRIO!E$3,'CONTAS A PAGAR'!$S:$S,DIÁRIO!$B11) -> 0 | F11: =SUMIFS('CONTAS A PAGAR'!$N:$N,'CONTAS A PAGAR'!$K:$K,DIÁRIO!F$3,'CONTAS A PAGAR'!$S:$S,DIÁRIO!$B11) -> 0 | G11: =SUMIFS('CONTAS A PAGAR'!$N:$N,'CONTAS A PAGAR'!$K:$K,DIÁRIO!G$3,'CONTAS A PAGAR'!$S:$S,DIÁRIO!$B11) -> 0 | H11: =SUMIFS('CONTAS A PAGAR'!$N:$N,'CONTAS A PAGAR'!$K:$K,DIÁRIO!H$3,'CONTAS A PAGAR'!$S:$S,DIÁRIO!$B11) -> 0 | I11: =SUMIFS('CONTAS A PAGAR'!$N:$N,'CONTAS A PAGAR'!$K:$K,DIÁRIO!I$3,'CONTAS A PAGAR'!$S:$S,DIÁRIO!$B11) -> 0 | J11: =SUMIFS('CONTAS A PAGAR'!$N:$N,'CONTAS A PAGAR'!$K:$K,DIÁRIO!J$3,'CONTAS A PAGAR'!$S:$S,DIÁRIO!$B11) -> 0 | ... T11: =SUMIFS('CONTAS A PAGAR'!$N:$N,'CONTAS A PAGAR'!$K:$K,DIÁRIO!T$3,'CONTAS A PAGAR'!$S:$S,DIÁRIO!$B11) -> 0 | U11: =SUM(C11:T11) -> 1125
B12: Embalagens | C12: =SUMIFS('CONTAS A PAGAR'!$N:$N,'CONTAS A PAGAR'!$K:$K,DIÁRIO!C$3,'CONTAS A PAGAR'!$S:$S,DIÁRIO!$B12) -> 0 | D12: =SUMIFS('CONTAS A PAGAR'!$N:$N,'CONTAS A PAGAR'!$K:$K,DIÁRIO!D$3,'CONTAS A PAGAR'!$S:$S,DIÁRIO!$B12) -> 0 | E12: =SUMIFS('CONTAS A PAGAR'!$N:$N,'CONTAS A PAGAR'!$K:$K,DIÁRIO!E$3,'CONTAS A PAGAR'!$S:$S,DIÁRIO!$B12) -> 427 | F12: =SUMIFS('CONTAS A PAGAR'!$N:$N,'CONTAS A PAGAR'!$K:$K,DIÁRIO!F$3,'CONTAS A PAGAR'!$S:$S,DIÁRIO!$B12) -> 0 | G12: =SUMIFS('CONTAS A PAGAR'!$N:$N,'CONTAS A PAGAR'!$K:$K,DIÁRIO!G$3,'CONTAS A PAGAR'!$S:$S,DIÁRIO!$B12) -> 0 | H12: =SUMIFS('CONTAS A PAGAR'!$N:$N,'CONTAS A PAGAR'!$K:$K,DIÁRIO!H$3,'CONTAS A PAGAR'!$S:$S,DIÁRIO!$B12) -> 0 | I12: =SUMIFS('CONTAS A PAGAR'!$N:$N,'CONTAS A PAGAR'!$K:$K,DIÁRIO!I$3,'CONTAS A PAGAR'!$S:$S,DIÁRIO!$B12) -> 0 | J12: =SUMIFS('CONTAS A PAGAR'!$N:$N,'CONTAS A PAGAR'!$K:$K,DIÁRIO!J$3,'CONTAS A PAGAR'!$S:$S,DIÁRIO!$B12) -> 0 | ... T12: =SUMIFS('CONTAS A PAGAR'!$N:$N,'CONTAS A PAGAR'!$K:$K,DIÁRIO!T$3,'CONTAS A PAGAR'!$S:$S,DIÁRIO!$B12) -> 0 | U12: =SUM(C12:T12) -> 427
B13: Criação de Modelos | C13: =SUMIFS('CONTAS A PAGAR'!$N:$N,'CONTAS A PAGAR'!$K:$K,DIÁRIO!C$3,'CONTAS A PAGAR'!$S:$S,DIÁRIO!$B13) -> 0 | D13: =SUMIFS('CONTAS A PAGAR'!$N:$N,'CONTAS A PAGAR'!$K:$K,DIÁRIO!D$3,'CONTAS A PAGAR'!$S:$S,DIÁRIO!$B13) -> 0 | E13: =SUMIFS('CONTAS A PAGAR'!$N:$N,'CONTAS A PAGAR'!$K:$K,DIÁRIO!E$3,'CONTAS A PAGAR'!$S:$S,DIÁRIO!$B13) -> 1550 | F13: =SUMIFS('CONTAS A PAGAR'!$N:$N,'CONTAS A PAGAR'!$K:$K,DIÁRIO!F$3,'CONTAS A PAGAR'!$S:$S,DIÁRIO!$B13) -> 0 | G13: =SUMIFS('CONTAS A PAGAR'!$N:$N,'CONTAS A PAGAR'!$K:$K,DIÁRIO!G$3,'CONTAS A PAGAR'!$S:$S,DIÁRIO!$B13) -> 0 | H13: =SUMIFS('CONTAS A PAGAR'!$N:$N,'CONTAS A PAGAR'!$K:$K,DIÁRIO!H$3,'CONTAS A PAGAR'!$S:$S,DIÁRIO!$B13) -> 0 | I13: =SUMIFS('CONTAS A PAGAR'!$N:$N,'CONTAS A PAGAR'!$K:$K,DIÁRIO!I$3,'CONTAS A PAGAR'!$S:$S,DIÁRIO!$B13) -> 1500 | J13: =SUMIFS('CONTAS A PAGAR'!$N:$N,'CONTAS A PAGAR'!$K:$K,DIÁRIO!J$3,'CONTAS A PAGAR'!$S:$S,DIÁRIO!$B13) -> 0 | ... T13: =SUMIFS('CONTAS A PAGAR'!$N:$N,'CONTAS A PAGAR'!$K:$K,DIÁRIO!T$3,'CONTAS A PAGAR'!$S:$S,DIÁRIO!$B13) -> 0 | U13: =SUM(C13:T13) -> 3050
B14: Salário e Ordenados | C14: =SUMIFS('CONTAS A PAGAR'!$N:$N,'CONTAS A PAGAR'!$K:$K,DIÁRIO!C$3,'CONTAS A PAGAR'!$S:$S,DIÁRIO!$B14) -> 0 | D14: =SUMIFS('CONTAS A PAGAR'!$N:$N,'CONTAS A PAGAR'!$K:$K,DIÁRIO!D$3,'CONTAS A PAGAR'!$S:$S,DIÁRIO!$B14) -> 0 | E14: =SUMIFS('CONTAS A PAGAR'!$N:$N,'CONTAS A PAGAR'!$K:$K,DIÁRIO!E$3,'CONTAS A PAGAR'!$S:$S,DIÁRIO!$B14) -> 0 | F14: =SUMIFS('CONTAS A PAGAR'!$N:$N,'CONTAS A PAGAR'!$K:$K,DIÁRIO!F$3,'CONTAS A PAGAR'!$S:$S,DIÁRIO!$B14) -> 0 | G14: =SUMIFS('CONTAS A PAGAR'!$N:$N,'CONTAS A PAGAR'!$K:$K,DIÁRIO!G$3,'CONTAS A PAGAR'!$S:$S,DIÁRIO!$B14) -> 0 | H14: =SUMIFS('CONTAS A PAGAR'!$N:$N,'CONTAS A PAGAR'!$K:$K,DIÁRIO!H$3,'CONTAS A PAGAR'!$S:$S,DIÁRIO!$B14) -> 0 | I14: =SUMIFS('CONTAS A PAGAR'!$N:$N,'CONTAS A PAGAR'!$K:$K,DIÁRIO!I$3,'CONTAS A PAGAR'!$S:$S,DIÁRIO!$B14) -> 170 | J14: =SUMIFS('CONTAS A PAGAR'!$N:$N,'CONTAS A PAGAR'!$K:$K,DIÁRIO!J$3,'CONTAS A PAGAR'!$S:$S,DIÁRIO!$B14) -> 0 | ... T14: =SUMIFS('CONTAS A PAGAR'!$N:$N,'CONTAS A PAGAR'!$K:$K,DIÁRIO!T$3,'CONTAS A PAGAR'!$S:$S,DIÁRIO!$B14) -> 0 | U14: =SUM(C14:T14) -> 340
B15: Vale Transporte | C15: =SUMIFS('CONTAS A PAGAR'!$N:$N,'CONTAS A PAGAR'!$K:$K,DIÁRIO!C$3,'CONTAS A PAGAR'!$S:$S,DIÁRIO!$B15) -> 0 | D15: =SUMIFS('CONTAS A PAGAR'!$N:$N,'CONTAS A PAGAR'!$K:$K,DIÁRIO!D$3,'CONTAS A PAGAR'!$S:$S,DIÁRIO!$B15) -> 0 | E15: =SUMIFS('CONTAS A PAGAR'!$N:$N,'CONTAS A PAGAR'!$K:$K,DIÁRIO!E$3,'CONTAS A PAGAR'!$S:$S,DIÁRIO!$B15) -> 0 | F15: =SUMIFS('CONTAS A PAGAR'!$N:$N,'CONTAS A PAGAR'!$K:$K,DIÁRIO!F$3,'CONTAS A PAGAR'!$S:$S,DIÁRIO!$B15) -> 0 | G15: =SUMIFS('CONTAS A PAGAR'!$N:$N,'CONTAS A PAGAR'!$K:$K,DIÁRIO!G$3,'CONTAS A PAGAR'!$S:$S,DIÁRIO!$B15) -> 0 | H15: =SUMIFS('CONTAS A PAGAR'!$N:$N,'CONTAS A PAGAR'!$K:$K,DIÁRIO!H$3,'CONTAS A PAGAR'!$S:$S,DIÁRIO!$B15) -> 0 | I15: =SUMIFS('CONTAS A PAGAR'!$N:$N,'CONTAS A PAGAR'!$K:$K,DIÁRIO!I$3,'CONTAS A PAGAR'!$S:$S,DIÁRIO!$B15) -> 0 | J15: =SUMIFS('CONTAS A PAGAR'!$N:$N,'CONTAS A PAGAR'!$K:$K,DIÁRIO!J$3,'CONTAS A PAGAR'!$S:$S,DIÁRIO!$B15) -> 0 | ... T15: =SUMIFS('CONTAS A PAGAR'!$N:$N,'CONTAS A PAGAR'!$K:$K,DIÁRIO!T$3,'CONTAS A PAGAR'!$S:$S,DIÁRIO!$B15) -> 0 | U15: =SUM(C15:T15) -> 0
... B65: Fgts, Gps e Pis | C65: =SUMIFS('CONTAS A PAGAR'!$N:$N,'CONTAS A PAGAR'!$K:$K,DIÁRIO!C$3,'CONTAS A PAGAR'!$S:$S,DIÁRIO!$B65) -> 0 | D65: =SUMIFS('CONTAS A PAGAR'!$N:$N,'CONTAS A PAGAR'!$K:$K,DIÁRIO!D$3,'CONTAS A PAGAR'!$S:$S,DIÁRIO!$B65) -> 0 | E65: =SUMIFS('CONTAS A PAGAR'!$N:$N,'CONTAS A PAGAR'!$K:$K,DIÁRIO!E$3,'CONTAS A PAGAR'!$S:$S,DIÁRIO!$B65) -> 0 | F65: =SUMIFS('CONTAS A PAGAR'!$N:$N,'CONTAS A PAGAR'!$K:$K,DIÁRIO!F$3,'CONTAS A PAGAR'!$S:$S,DIÁRIO!$B65) -> 0 | G65: =SUMIFS('CONTAS A PAGAR'!$N:$N,'CONTAS A PAGAR'!$K:$K,DIÁRIO!G$3,'CONTAS A PAGAR'!$S:$S,DIÁRIO!$B65) -> 0 | H65: =SUMIFS('CONTAS A PAGAR'!$N:$N,'CONTAS A PAGAR'!$K:$K,DIÁRIO!H$3,'CONTAS A PAGAR'!$S:$S,DIÁRIO!$B65) -> 0 | I65: =SUMIFS('CONTAS A PAGAR'!$N:$N,'CONTAS A PAGAR'!$K:$K,DIÁRIO!I$3,'CONTAS A PAGAR'!$S:$S,DIÁRIO!$B65) -> 3989.34 | J65: =SUMIFS('CONTAS A PAGAR'!$N:$N,'CONTAS A PAGAR'!$K:$K,DIÁRIO!J$3,'CONTAS A PAGAR'!$S:$S,DIÁRIO!$B65) -> 0 | ... T65: =SUMIFS('CONTAS A PAGAR'!$N:$N,'CONTAS A PAGAR'!$K:$K,DIÁRIO!T$3,'CONTAS A PAGAR'!$S:$S,DIÁRIO!$B65) -> 0 | U65: =SUM(C65:T65) -> 3989.34

Sheet BASE VD 2024
A1: EMPRESA | B1: DATA | C1: DIA - SEMANA | D1: QTD. VENDAS | E1: QTD.ITENS | F1: VALOR LÍQUIDO | G1: MÊS
A2: CODI.COM - LOJA BASIC 2 | B2: 45453 | C2: Segunda-feira | D2: 2 | E2: 4 | F2: 340 | G2: =TEXT(B2,"MMMM") -> junho
A3: CODI.COM - LOJA BASIC 1 | B3: 45456 | C3: Quinta-feira | D3: 1 | E3: 3 | F3: 593.7 | G3: =TEXT(B3,"MMMM") -> junho
A4: CODI.COM - LOJA BASIC 1 | B4: 45457 | C4: Sexta-feira | D4: 1 | E4: 12 | F4: 960 | G4: =TEXT(B4,"MMMM") -> junho
A5: CODI.COM - LOJA BASIC 1 | B5: 45460 | C5: Segunda-feira | D5: 6 | E5: 204 | F5: 16625 | G5: =TEXT(B5,"MMMM") -> junho
A6: CODI.COM - LOJA BASIC 1 | B6: 45461 | C6: Terça-feira | D6: 13 | E6: 436 | F6: 35320 | G6: =TEXT(B6,"MMMM") -> junho
A7: CODI.COM - LOJA BASIC 2 | B7: 45461 | C7: Terça-feira | D7: 3 | E7: 4 | F7: 330 | G7: =TEXT(B7,"MMMM") -> junho
A8: CODI.COM - LOJA BASIC 1 | B8: 45462 | C8: Quarta-feira | D8: 6 | E8: 99 | F8: 8218.72 | G8: =TEXT(B8,"MMMM") -> junho
A9: CODI.COM - LOJA BASIC 2 | B9: 45462 | C9: Quarta-feira | D9: 8 | E9: 40 | F9: 3125 | G9: =TEXT(B9,"MMMM") -> junho
A10: CODI.COM - LOJA BASIC 1 | B10: 45463 | C10: Quinta-feira | D10: 10 | E10: 306 | F10: 25781.62 | G10: =TEXT(B10,"MMMM") -> junho
A11: CODI.COM - LOJA BASIC 2 | B11: 45463 | C11: Quinta-feira | D11: 12 | E11: 56 | F11: 4760 | G11: =TEXT(B11,"MMMM") -> junho
A12: CODI.COM - LOJA BASIC 1 | B12: 45464 | C12: Sexta-feira | D12: 12 | E12: 290 | F12: 24149.9 | G12: =TEXT(B12,"MMMM") -> junho
A13: CODI.COM - LOJA BASIC 2 | B13: 45464 | C13: Sexta-feira | D13: 5 | E13: 27 | F13: 2685 | G13: =TEXT(B13,"MMMM") -> junho
... A169: CODI.COM - LOJA BASIC 1 | B169: 45567 | C169: Quarta-feira | D169: 6 | E169: 263 | F169: 19929 | G169: =TEXT(B169,"MMMM") -> outubro
A170: CODI.COM - LOJA BASIC 2 | B170: 45567 | C170: Quarta-feira | D170: 4 | E170: 58 | F170: 4700 | G170: =TEXT(B170,"MMMM") -> outubro | J170: =SUM(F168:F189) -> 306591.5
A171: CODI.COM - LOJA BASIC 1 | B171: 45568 | C171: Quinta-feira | D171: 7 | E171: 119 | F171: 9240 | G171: =TEXT(B171,"MMMM") -> outubro | J171: =SUM(F191:F216) -> 296350.24
A172: CODI.COM - LOJA BASIC 2 | B172: 45568 | C172: Quinta-feira | D172: 2 | E172: 3 | F172: 245 | G172: =TEXT(B172,"MMMM") -> outubro
A173: CODI.COM - LOJA BASIC 1 | B173: 45569 | C173: Sexta-feira | D173: 10 | E173: 593 | F173: 46135 | G173: =TEXT(B173,"MMMM") -> outubro
A174: CODI.COM - LOJA BASIC 2 | B174: 45569 | C174: Sexta-feira | D174: 2 | E174: 6 | F174: 720 | G174: =TEXT(B174,"MMMM") -> outubro
A175: CODI.COM - LOJA BASIC 2 | B175: 45570 | C175: Sábado | D175: 5 | E175: 14 | F175: 1150 | G175: =TEXT(B175,"MMMM") -> outubro
A176: CODI.COM - LOJA BASIC 1 | B176: 45572 | C176: Segunda-feira | D176: 4 | E176: 75 | F176: 5250 | G176: =TEXT(B176,"MMMM") -> outubro
A177: CODI.COM - LOJA BASIC 2 | B177: 45572 | C177: Segunda-feira | D177: 6 | E177: 24 | F177: 1770 | G177: =TEXT(B177,"MMMM") -> outubro
A178: CODI.COM - LOJA BASIC 1 | B178: 45573 | C178: Terça-feira | D178: 9 | E178: 223 | F178: 16765 | G178: =TEXT(B178,"MMMM") -> outubro
A179: CODI.COM - LOJA BASIC 2 | B179: 45573 | C179: Terça-feira | D179: 3 | E179: 15 | F179: 1145 | G179: =TEXT(B179,"MMMM") -> outubro
A180: CODI.COM - LOJA BASIC 1 | B180: 45574 | C180: Quarta-feira | D180: 6 | E180: 402 | F180: 31780 | G180: =TEXT(B180,"MMMM") -> outubro
A181: CODI.COM - LOJA BASIC 2 | B181: 45574 | C181: Quarta-feira | D181: 5 | E181: 7 | F181: 835 | G181: =TEXT(B181,"MMMM") -> outubro
A182: CODI.COM - LOJA BASIC 1 | B182: 45575 | C182: Quinta-feira | D182: 3 | E182: 103 | F182: 7635 | G182: =TEXT(B182,"MMMM") -> outubro
A183: CODI.COM - LOJA BASIC 2 | B183: 45575 | C183: Quinta-feira | D183: 4 | E183: 40 | F183: 2940 | G183: =TEXT(B183,"MMMM") -> outubro
... A304: CODI.COM - LOJA BASIC 2 | B304: 45657 | C304: Terça-feira | D304: 7 | E304: 11 | F304: 1254 | G304: =TEXT(B304,"MMMM") -> dezembro

Sheet ANALISE RECEITA
A2: 23 | C2: CODI.COM - LOJA BASIC 2 | J2: CODI.COM - LOJA BASIC 1 | O2: TOTAL
A3: 11 | D3: 2024 | E3: 2025 | F3: 25 X 24 | J3: 2024 | K3: 2025 | L3: 25 X 24 | O3: 2024 | Q3: 2025 | R3: 25 X 24
C4: JULHO | D4: =SUMIFS('BASE VD 2024'!F:F,'BASE VD 2024'!G:G,'ANALISE RECEITA'!C4,'BASE VD 2025'!$A:$A,'ANALISE RECEITA'!C$2) -> 305866.44 | E4: =SUMIFS('BASE VD 2025'!F:F,'BASE VD 2025'!G:G,'ANALISE RECEITA'!C4,'BASE VD 2025'!$A:$A,'ANALISE RECEITA'!$C$2) -> 41578 | F4: =E4/D4-1 -> -0.86406485 | G4: =E4*20% -> 8315.6 | I4: JULHO | J4: =SUMIFS('BASE VD 2024'!F:F,'BASE VD 2024'!G:G,'ANALISE RECEITA'!C4,'BASE VD 2025'!$A:$A,J$2) -> 269445.84 | K4: =SUMIFS('BASE VD 2025'!F:F,'BASE VD 2025'!G:G,'ANALISE RECEITA'!C4,'BASE VD 2025'!$A:$A,$J$2) -> 440746.6 | L4: =K4/J4-1 -> 0.63575211 | N4: JULHO | O4: =SUM(D4,J4) -> 575312.28 | P4: =SUM(D4,J4) -> 575312.28 | Q4: =SUM(E4,K4) -> 482324.6 | R4: =Q4/O4-1 -> -0.16162992
C5: AGOSTO | D5: =SUMIFS('BASE VD 2024'!F:F,'BASE VD 2024'!G:G,'ANALISE RECEITA'!C5,'BASE VD 2025'!$A:$A,'ANALISE RECEITA'!C$2) -> 352678.47 | E5: =SUMIFS('BASE VD 2025'!F:F,'BASE VD 2025'!G:G,'ANALISE RECEITA'!C5,'BASE VD 2025'!$A:$A,'ANALISE RECEITA'!$C$2) -> 36825 | F5: =E5/D5-1 -> -0.89558478 | G5: =E5*20% -> 7365 | I5: AGOSTO | J5: =SUMIFS('BASE VD 2024'!F:F,'BASE VD 2024'!G:G,'ANALISE RECEITA'!C5,'BASE VD 2025'!$A:$A,J$2) -> 256418.1 | K5: =SUMIFS('BASE VD 2025'!F:F,'BASE VD 2025'!G:G,'ANALISE RECEITA'!C5,'BASE VD 2025'!$A:$A,$J$2) -> 505022 | L5: =K5/J5-1 -> 0.96952555 | N5: AGOSTO | O5: =SUM(D5,J5) -> 609096.57 | P5: =SUM(D5,J5) -> 609096.57 | Q5: =SUM(E5,K5) -> 541847 | R5: =Q5/O5-1 -> -0.11040872
C6: SETEMBRO | D6: =SUMIFS('BASE VD 2024'!F:F,'BASE VD 2024'!G:G,'ANALISE RECEITA'!C6,'BASE VD 2025'!$A:$A,'ANALISE RECEITA'!C$2) -> 325644.8 | E6: =SUMIFS('BASE VD 2025'!F:F,'BASE VD 2025'!G:G,'ANALISE RECEITA'!C6,'BASE VD 2025'!$A:$A,'ANALISE RECEITA'!$C$2) -> 54755 | F6: =E6/D6-1 -> -0.83185667 | G6: =E6*20% -> 10951 | I6: SETEMBRO | J6: =SUMIFS('BASE VD 2024'!F:F,'BASE VD 2024'!G:G,'ANALISE RECEITA'!C6,'BASE VD 2025'!$A:$A,J$2) -> 135975.7 | K6: =SUMIFS('BASE VD 2025'!F:F,'BASE VD 2025'!G:G,'ANALISE RECEITA'!C6,'BASE VD 2025'!$A:$A,$J$2) -> 425967.15 | L6: =K6/J6-1 -> 2.1326711 | N6: SETEMBRO | O6: =SUM(D6,J6) -> 461620.5 | P6: =SUM(D6,J6) -> 461620.5 | Q6: =SUM(E6,K6) -> 480722.15 | R6: =Q6/O6-1 -> 0.041379553
C7: OUTUBRO | D7: =SUMIFS('BASE VD 2024'!F:F,'BASE VD 2024'!G:G,'ANALISE RECEITA'!C7,'BASE VD 2025'!$A:$A,'ANALISE RECEITA'!C$2) -> 306111.3 | E7: =SUMIFS('BASE VD 2025'!F:F,'BASE VD 2025'!G:G,'ANALISE RECEITA'!C7,'BASE VD 2025'!$A:$A,'ANALISE RECEITA'!$C$2) -> 0 | F7: =E7/D7-1 -> -1 | G7: =E7*20% -> 0 | I7: OUTUBRO | J7: =SUMIFS('BASE VD 2024'!F:F,'BASE VD 2024'!G:G,'ANALISE RECEITA'!C7,'BASE VD 2025'!$A:$A,J$2) -> 298465.44 | K7: =SUMIFS('BASE VD 2025'!F:F,'BASE VD 2025'!G:G,'ANALISE RECEITA'!C7,'BASE VD 2025'!$A:$A,$J$2) -> 204360.6 | L7: =K7/J7-1 -> -0.3152956 | N7: OUTUBRO | O7: =SUM(D7,J7) -> 604576.74 | P7: =SUM(E7,K7) -> 204360.6 | Q7: 522000 | R7: =Q7/O7-1 -> -0.13658604
C8: NOVEMBRO | D8: =SUMIFS('BASE VD 2024'!F:F,'BASE VD 2024'!G:G,'ANALISE RECEITA'!C8,'BASE VD 2025'!$A:$A,'ANALISE RECEITA'!C$2) -> 532950.98 | E8: =SUMIFS('BASE VD 2025'!F:F,'BASE VD 2025'!G:G,'ANALISE RECEITA'!C8,'BASE VD 2025'!$A:$A,'ANALISE RECEITA'!$C$2) -> 0 | F8: =E8/D8-1 -> -1 | G8: =E8*20% -> 0 | I8: NOVEMBRO | J8: =SUMIFS('BASE VD 2024'!F:F,'BASE VD 2024'!G:G,'ANALISE RECEITA'!C8,'BASE VD 2025'!$A:$A,J$2) -> 156393 | K8: =SUMIFS('BASE VD 2025'!F:F,'BASE VD 2025'!G:G,'ANALISE RECEITA'!C8,'BASE VD 2025'!$A:$A,$J$2) -> 0 | L8: =K8/J8-1 -> -1 | N8: NOVEMBRO | O8: =SUM(D8,J8) -> 689343.98 | P8: 620409.58 | Q8: =O8*90% -> 620409.58 | R8: =Q8/O8-1 -> -0.1
C9: DEZEMBRO | D9: =SUMIFS('BASE VD 2024'!F:F,'BASE VD 2024'!G:G,'ANALISE RECEITA'!C9,'BASE VD 2025'!$A:$A,'ANALISE RECEITA'!C$2) -> 174687 | E9: =SUMIFS('BASE VD 2025'!F:F,'BASE VD 2025'!G:G,'ANALISE RECEITA'!C9,'BASE VD 2025'!$A:$A,'ANALISE RECEITA'!$C$2) -> 0 | F9: =E9/D9-1 -> -1 | G9: =E9*20% -> 0 | I9: DEZEMBRO | J9: =SUMIFS('BASE VD 2024'!F:F,'BASE VD 2024'!G:G,'ANALISE RECEITA'!C9,'BASE VD 2025'!$A:$A,J$2) -> 585303.9 | K9: =SUMIFS('BASE VD 2025'!F:F,'BASE VD 2025'!G:G,'ANALISE RECEITA'!C9,'BASE VD 2025'!$A:$A,$J$2) -> 0 | L9: =K9/J9-1 -> -1 | N9: DEZEMBRO | O9: =SUM(D9,J9) -> 759990.9 | P9: 683991.81 | Q9: =O9*90% -> 683991.81 | R9: =Q9/O9-1 -> -0.1
C11: MEDIA DE VENDA POR DIA | D11: 2024 | E11: 2025 | F11: 25 X 24
C12: Segunda-feira | D12: =SUMIFS('BASE VD 2024'!$F:$F,'BASE VD 2024'!$C:$C,'ANALISE RECEITA'!$C12)/COUNTIF('BASE VD 2024'!$C:$C,'ANALISE RECEITA'!$C12) -> 11114.383
C13: Terça-feira | D13: =SUMIFS('BASE VD 2024'!$F:$F,'BASE VD 2024'!$C:$C,'ANALISE RECEITA'!$C13)/COUNTIF('BASE VD 2024'!$C:$C,'ANALISE RECEITA'!$C13) -> 15724.842
C14: Quarta-feira | D14: =SUMIFS('BASE VD 2024'!$F:$F,'BASE VD 2024'!$C:$C,'ANALISE RECEITA'!$C14)/COUNTIF('BASE VD 2024'!$C:$C,'ANALISE RECEITA'!$C14) -> 13708.684
C15: Quinta-feira | D15: =SUMIFS('BASE VD 2024'!$F:$F,'BASE VD 2024'!$C:$C,'ANALISE RECEITA'!$C15)/COUNTIF('BASE VD 2024'!$C:$C,'ANALISE RECEITA'!$C15) -> 15807.649
C16: Sexta-feira | D16: =SUMIFS('BASE VD 2024'!$F:$F,'BASE VD 2024'!$C:$C,'ANALISE RECEITA'!$C16)/COUNTIF('BASE VD 2024'!$C:$C,'ANALISE RECEITA'!$C16) -> 12834.323
C17: Sábado | D17: =SUMIFS('BASE VD 2024'!$F:$F,'BASE VD 2024'!$C:$C,'ANALISE RECEITA'!$C17)/COUNTIF('BASE VD 2024'!$C:$C,'ANALISE RECEITA'!$C17) -> 3687.8148

Sheet BASE VD 2025
A1: EMPRESA | B1: DATA | C1: DIA - SEMANA | D1: QTD. VENDAS | E1: QTD.ITENS | F1: VALOR LÍQUIDO | G1: MÊS
A2: CODI.COM - LOJA BASIC 2 | B2: 45659 | C2: Quinta-feira | D2: 2 | E2: 7 | F2: 1130 | G2: =TEXT(B2,"MMMM") -> janeiro
A3: CODI.COM - LOJA BASIC 2 | B3: 45661 | C3: Sábado | D3: 2 | E3: 11 | F3: 1025 | G3: =TEXT(B3,"MMMM") -> janeiro
A4: CODI.COM - LOJA BASIC 1 | B4: 45663 | C4: Segunda-feira | D4: 1 | E4: 51 | F4: 4160 | G4: =TEXT(B4,"MMMM") -> janeiro
A5: CODI.COM - LOJA BASIC 1 | B5: 45664 | C5: Terça-feira | D5: 3 | E5: 172 | F5: 10285 | G5: =TEXT(B5,"MMMM") -> janeiro
A6: CODI.COM - LOJA BASIC 2 | B6: 45664 | C6: Terça-feira | D6: 4 | E6: 21 | F6: 1615 | G6: =TEXT(B6,"MMMM") -> janeiro
A7: CODI.COM - LOJA BASIC 1 | B7: 45665 | C7: Quarta-feira | D7: 3 | E7: 172 | F7: 12345 | G7: =TEXT(B7,"MMMM") -> janeiro
A8: CODI.COM - LOJA BASIC 1 | B8: 45666 | C8: Quinta-feira | D8: 7 | E8: 199 | F8: 14000 | G8: =TEXT(B8,"MMMM") -> janeiro
A9: CODI.COM - LOJA BASIC 2 | B9: 45666 | C9: Quinta-feira | D9: 4 | E9: 6 | F9: 645 | G9: =TEXT(B9,"MMMM") -> janeiro
A10: CODI.COM - LOJA BASIC 1 | B10: 45667 | C10: Sexta-feira | D10: 4 | E10: 89 | F10: 6525 | G10: =TEXT(B10,"MMMM") -> janeiro
A11: CODI.COM - LOJA BASIC 2 | B11: 45667 | C11: Sexta-feira | D11: 3 | E11: 8 | F11: 750 | G11: =TEXT(B11,"MMMM") -> janeiro
A12: CODI.COM - LOJA BASIC 2 | B12: 45668 | C12: Sábado | D12: 1 | E12: 1 | F12: 160 | G12: =TEXT(B12,"MMMM") -> janeiro
A13: CODI.COM - LOJA BASIC 1 | B13: 45670 | C13: Segunda-feira | D13: 3 | E13: 69 | F13: 5075 | G13: =TEXT(B13,"MMMM") -> janeiro
... A380: CODI.COM - LOJA BASIC 2 | B380: 45930 | C380: Terça-feira | D380: 4 | E380: 18 | F380: 1570 | G380: =TEXT(B380,"MMMM") -> setembro
A381: CODI.COM - LOJA BASIC 1 | B381: 45931 | C381: Quarta-feira | D381: 3 | E381: 38 | G381: =TEXT(B381,"MMMM") -> outubro
A382: CODI.COM - LOJA BASIC 1 | B382: 45932 | C382: Quinta-feira | D382: 5 | E382: 122 | G382: =TEXT(B382,"MMMM") -> outubro
A383: CODI.COM - LOJA BASIC 2 | B383: 45932 | C383: Quinta-feira | D383: 3 | E383: 11 | G383: =TEXT(B383,"MMMM") -> outubro
A384: CODI.COM - LOJA BASIC 1 | B384: 45933 | C384: Sexta-feira | D384: 8 | E384: 198 | G384: =TEXT(B384,"MMMM") -> outubro
A385: CODI.COM - LOJA BASIC 2 | B385: 45933 | C385: Sexta-feira | D385: 4 | E385: 15 | G385: =TEXT(B385,"MMMM") -> outubro
A386: CODI.COM - LOJA BASIC 2 | B386: 45934 | C386: Sábado | D386: 1 | E386: 1 | G386: =TEXT(B386,"MMMM") -> outubro
A387: CODI.COM - LOJA BASIC 1 | B387: 45936 | C387: Segunda-feira | D387: 5 | E387: 102 | G387: =TEXT(B387,"MMMM") -> outubro
A388: CODI.COM - LOJA BASIC 2 | B388: 45936 | C388: Segunda-feira | D388: 1 | E388: 2 | G388: =TEXT(B388,"MMMM") -> outubro
A389: CODI.COM - LOJA BASIC 1 | B389: 45937 | C389: Terça-feira | D389: 11 | E389: 238 | G389: =TEXT(B389,"MMMM") -> outubro
A390: CODI.COM - LOJA BASIC 2 | B390: 45937 | C390: Terça-feira | D390: 1 | E390: 1 | G390: =TEXT(B390,"MMMM") -> outubro
A391: CODI.COM - LOJA BASIC 1 | B391: 45938 | C391: Quarta-feira | D391: 5 | E391: 301 | G391: =TEXT(B391,"MMMM") -> outubro
A392: CODI.COM - LOJA BASIC 2 | B392: 45938 | C392: Quarta-feira | D392: 4 | E392: 15 | G392: =TEXT(B392,"MMMM") -> outubro
... A399: CODI.COM - LOJA BASIC 2 | B399: 45943 | C399: Segunda-feira | D399: 3 | E399: 10 | G399: =TEXT(B399,"MMMM") -> outubro
A400: CODI.COM - LOJA BASIC 1 | B400: 45944 | C400: Terça-feira | F400: 204360.6 | G400: =TEXT(B400,"MMMM") -> outubro
A401: CODI.COM - LOJA BASIC 2 | B401: 45944 | C401: Terça-feira | G401: =TEXT(B401,"MMMM") -> outubro
